Workbook
Name A_impresión_IM: #REF!
Name ANNUAL_OTHER_TAX: [1]Assumptions!$B$48
Name ANNUAL_PERS_PROPERTY_TAX: [1]Assumptions!$B$47
Name ANNUAL_REAL_PROPERTY_TAX: [1]Assumptions!$B$46
Name AVG_NO_EMPLOYEES: [1]Assumptions!$B$74
Name BUDGET_YEAR: [1]Assumptions!$B$4
Name CELL_PHONE_100: [1]Assumptions!$B$35
Name CELL_PHONE_50: [1]Assumptions!$B$34
Name CLEANING_MINS_PER_ROOM: [1]Assumptions!$B$27
Name COST_OF_BEER: [1]Assumptions!$B$155
Name COST_OF_BEVERAGE: [1]Assumptions!$B$154
Name COST_OF_FOOD: [1]Assumptions!$B$152
Name COST_OF_LIQUOR: [1]Assumptions!$B$156
Name COST_OF_PREPACKAGED: [1]Assumptions!$B$153
Name COST_OF_WINE: [1]Assumptions!$B$157
Name CREDIT_CARD_COMMISSION_RATE: [1]Assumptions!$B$12
Name DATE_REV_FIGURES: [1]Assumptions!$B$7
Name Demand2Data: #REF!
Name Demand2Date2: #REF!
Name Demand2Metric: #REF!
Name EMPLOYEE_BENEFITS: [1]Assumptions!$F$59
Name EMPLOYEE_ONBOARDING: [1]Assumptions!#REF!
Name EMPLOYEE_TRAINING: [1]Assumptions!$B$32
Name ESDG_FACTOR: [1]Assumptions!$B$16
Name ESDG_PER_STAY: [1]Assumptions!$B$17
Name FAIR_TRADE_PRICING: [1]Assumptions!$B$14
Name FechaDeInicioelañoFiscal: '[2]FLUJO DE EFECTIVO'!$B$7
Name FEE_ACCOUNTING: [1]Assumptions!$B$38
Name FEE_BACKGROUND_CHECK: [1]Assumptions!$B$33
Name FEE_MANAGEMENT: [1]Assumptions!$B$8
Name FEE_MARKETING_BRAND: [1]Assumptions!$B$11
Name FEE_MARKETING_CENTRALIZED_SERVICES: [1]Assumptions!$B$41
Name FEE_REVMGMT_CENTRALIZED_SERVICES: [1]Assumptions!$B$39
Name FEE_ROYALTY_FB: [1]Assumptions!$B$10
Name FEE_ROYALTY_ROOMS: [1]Assumptions!$B$9
Name FEE_SALES_CENTRALIZED_SERVICES: [1]Assumptions!$B$40
Name FEE_TECHNOLOGY: [1]Assumptions!$B$37
Name FFE_RESERVE: [1]Assumptions!$B$13
Name HOTEL_NAME: [1]Assumptions!$B$2
Name MEMBERSHIP_COST_MULTIPLIER: #REF!
Name MEMBERSHIP_FEE_REVENUE: [1]Assumptions!$B$147
Name MINS_PER_HOUR: [1]Assumptions!$B$51
Name MONTHLY_INTERNET_SERVICE: [1]Assumptions!$B$43
Name MONTHLY_PHONE_SERVICE: [1]Assumptions!$B$44
Name MONTHLY_WASTE_REMOVAL: [1]Assumptions!$B$45
Name MY_FUNCTION1: _xludf.LAMBDA(SUM('[3]RATES CWL 2023-2024'!$B$48-500)/3)
Name MY_FUNCTION1: _xludf.LAMBDA(SUM('[3]RATES CWL 2023-2024'!$B$48-500)/3)
Name MY_FUNCTION1: _xludf.LAMBDA(SUM('[3]RATES CWL 2023-2024'!$B$48-500)/3)
Name MY_FUNCTION1: _xludf.LAMBDA(SUM('[3]RATES CWL 2023-2024'!$B$48-500)/3)
Name NO_OF_ROOMS: [1]Assumptions!$B$5
Name PAYROLL_TAXES: [1]Assumptions!$F$57
Name PET_FEE_MULTIPLIER: [1]Assumptions!$B$26
Name PET_FEE_PER_STAY: [1]Assumptions!$B$25
Name PRIOR_YEAR_TOTAL_OCCUPIED_ROOMS: Summary!$T$12
Name RESORT_FEE_MULTIPLIER: [1]Assumptions!$B$23
Name RESORT_FEE_PER_STAY: [1]Assumptions!$B$22
Name SUPPPAY: [1]Assumptions!$F$58
Name Tipo1: '[4]Tipo Cambio'!$1:$1048576
Name Tipo2: '[4]Tipo Cambio'!$1:$1
Name TOTAL_OCCUPIED_ROOMS: [1]Assumptions!$B$6

Sheet Summary
A1: Go to tabs: | B1: Rooms | C1: Food Revenue | D1: Beverage Revenue | E1: F&B Mis Revenue | F1: Spa Revenue | G1: Retail Gift Shop | H1: Activities | I1: Transportation | J1: Innoceanna | K1: Sustainability Fee | L1: Laundry
A3: Enter 2026 monthly budget in B10:M10 of each tab. Summary pulls those cells.
B5: January | C5: February | D5: March | E5: April | F5: May | G5: June | H5: July | I5: August | J5: September | K5: October | L5: November | M5: December | N5: TOTAL
A7: 2026 Revenue Budget – Summary
A9: Key Indicators 2026 (Budget) | B9: January | C9: February | D9: March | E9: April | F9: May | G9: June | H9: July | I9: August | J9: September | K9: October | L9: November | M9: December | N9: TOTAL
A10: Indicator
A12: Total available Rooms | B12: =+Rooms!C27 -> 930 | C12: =+Rooms!D27 -> 840 | D12: =+Rooms!E27 -> 930 | E12: =+Rooms!F27 -> 900 | F12: =+Rooms!G27 -> 930 | G12: =+Rooms!H27 -> 900 | H12: =+Rooms!I27 -> 930 | I12: =+Rooms!J27 -> 930 | ... N12: =+Rooms!O27 -> 10020 | O12: =+N46 -> 10950 | P12: =+N12+O12 -> 20970
A13: Total Rooms Occupied | B13: =+Rooms!C28 -> 697.5 | C13: =+Rooms!D28 -> 638.4 | D13: =+Rooms!E28 -> 607.7 | E13: =+Rooms!F28 -> 332 | F13: =+Rooms!G28 -> 232.48621 | G13: =+Rooms!H28 -> 167.65517 | H13: =+Rooms!I28 -> 332.1 | I13: =+Rooms!J28 -> 251.32 | ... N13: =+Rooms!O28 -> 4363.2889 | O13: =+N47 -> 3179
A14: Total Guests | B14: =+Rooms!C29 -> 1255.5 | C14: =+Rooms!D29 -> 1149.12 | D14: =+Rooms!E29 -> 1093.86 | E14: =+Rooms!F29 -> 597.6 | F14: =+Rooms!G29 -> 418.47517 | G14: =+Rooms!H29 -> 301.77931 | H14: =+Rooms!I29 -> 597.78 | I14: =+Rooms!J29 -> 452.376 | ... N14: =+Rooms!O29 -> 7853.92 | O14: =+N48 -> 5677
A15: % Occupancy | B15: =+Rooms!C30 -> 0.75 | C15: =+Rooms!D30 -> 0.76 | D15: =+Rooms!E30 -> 0.65344086 | E15: =+Rooms!F30 -> 0.36888889 | F15: =+Rooms!G30 -> 0.24998517 | G15: =+Rooms!H30 -> 0.18628352 | H15: =+Rooms!I30 -> 0.35709677 | I15: =+Rooms!J30 -> 0.27023656 | J15: =+Rooms!K30 -> 0.091466667 | L15: =+Rooms!M30 -> 0.45566667 | M15: =+Rooms!N30 -> 0.65775 | N15: =+Rooms!O30 -> 0.43545797 | O15: =+N49 -> 0.29031963 | P15: =+N15-O15 -> 0.14513834
A16: ADR | B16: =+Rooms!C31 -> 595.27155 | C16: =+Rooms!D31 -> 583.47405 | D16: =+Rooms!E31 -> 590.96203 | E16: =+Rooms!F31 -> 635.29075 | F16: =+Rooms!G31 -> 521.40328 | G16: =+Rooms!H31 -> 553.7017 | H16: =+Rooms!I31 -> 566.23141 | I16: =+Rooms!J31 -> 520.6179 | J16: =+Rooms!K31 -> 485.58682 | L16: =+Rooms!M31 -> 548.40744 | M16: =+Rooms!N31 -> 733.76344 | N16: =+Rooms!O31 -> 596.88852 | O16: =+N50 -> 484.67682 | P16: =+N16-O16 -> 112.2117 | Q16: =+P16/O16 -> 0.23151861
A18: Rooms | B18: =+Rooms!C38 -> 415201.91 | C18: =+Rooms!D38 -> 372489.83 | D18: =+Rooms!E38 -> 359127.63 | E18: =+Rooms!F38 -> 210916.53 | F18: =+Rooms!G38 -> 121219.07 | G18: =+Rooms!H38 -> 92830.953 | H18: =+Rooms!I38 -> 188045.45 | I18: =+Rooms!J38 -> 130841.69 | ... M18: =+Rooms!N38 -> 448848.6 | N18: =SUM(B18:M18) -> 2604397.1 | O18: =+N52 -> 1540787.6
A19: Food Revenue | B19: ='Food Revenue'!C38 -> 113356.58 | C19: ='Food Revenue'!D38 -> 103751.75 | D19: ='Food Revenue'!E38 -> 98762.432 | E19: ='Food Revenue'!F38 -> 53956.109 | F19: ='Food Revenue'!G38 -> 37783.286 | G19: ='Food Revenue'!H38 -> 27247.05 | H19: ='Food Revenue'!I38 -> 53972.361 | I19: ='Food Revenue'!J38 -> 40844.124 | ... M19: ='Food Revenue'!N38 -> 99413.724 | N19: =SUM(B19:M19) -> 709114.73 | O19: =+N53 -> 428040.29
A20: Beverage Revenue | B20: ='Beverage Revenue'!B38 -> 38541.239 | C20: ='Beverage Revenue'!C38 -> 35275.594 | D20: ='Beverage Revenue'!D38 -> 33579.227 | E20: ='Beverage Revenue'!E38 -> 18345.077 | F20: ='Beverage Revenue'!F38 -> 12846.317 | G20: ='Beverage Revenue'!G38 -> 9263.9971 | H20: ='Beverage Revenue'!H38 -> 18350.603 | I20: ='Beverage Revenue'!I38 -> 13887.002 | ... M20: ='Beverage Revenue'!M38 -> 33800.666 | N20: =SUM(B20:M20) -> 241099.01 | O20: =+N54 -> 136270.41
A21: F&B Mis Revenue | B21: ='F&B Mis Revenue'!B38 -> 0 | C21: ='F&B Mis Revenue'!C38 -> 0 | D21: ='F&B Mis Revenue'!D38 -> 0 | E21: ='F&B Mis Revenue'!E38 -> 0 | F21: ='F&B Mis Revenue'!F38 -> 0 | G21: ='F&B Mis Revenue'!G38 -> 0 | H21: ='F&B Mis Revenue'!H38 -> 0 | I21: ='F&B Mis Revenue'!I38 -> 0 | ... M21: ='F&B Mis Revenue'!M38 -> 0 | N21: =SUM(B21:M21) -> 0 | O21: =+N55 -> 33723.037
A22: Spa Revenue | B22: ='Spa Revenue'!B38 -> 5812.5 | C22: ='Spa Revenue'!C38 -> 5250 | D22: ='Spa Revenue'!D38 -> 5812.5 | E22: ='Spa Revenue'!E38 -> 5625 | F22: ='Spa Revenue'!F38 -> 5812.5 | G22: ='Spa Revenue'!G38 -> 5625 | H22: ='Spa Revenue'!H38 -> 5812.5 | I22: ='Spa Revenue'!I38 -> 5812.5 | ... M22: ='Spa Revenue'!M38 -> 5812.5 | N22: =SUM(B22:M22) -> 62625 | O22: =+N56 -> 32500.473
A23: Retail Gift Shop | B23: ='Retail Gift Shop'!B38 -> 4982.4229 | C23: ='Retail Gift Shop'!C38 -> 4469.878 | D23: ='Retail Gift Shop'!D38 -> 4309.5315 | E23: ='Retail Gift Shop'!E38 -> 2530.9984 | F23: ='Retail Gift Shop'!F38 -> 1454.6288 | G23: ='Retail Gift Shop'!G38 -> 1113.9714 | H23: ='Retail Gift Shop'!H38 -> 2256.5454 | I23: ='Retail Gift Shop'!I38 -> 1570.1003 | ... M23: ='Retail Gift Shop'!M38 -> 5386.1832 | N23: =SUM(B23:M23) -> 31252.765 | O23: =+N57 -> 18170.774
A24: Activities | B24: =Activities!B38 -> 106009.4 | C24: =Activities!C38 -> 97027.096 | D24: =Activities!D38 -> 92361.163 | E24: =Activities!E38 -> 50458.954 | F24: =Activities!F38 -> 35334.37 | G24: =Activities!G38 -> 25481.038 | H24: =Activities!H38 -> 50474.152 | I24: =Activities!I38 -> 38196.82 | ... M24: =Activities!M38 -> 92970.242 | N24: =SUM(B24:M24) -> 663153.59 | O24: =+N58 -> 303352.17 | P24: =+O26 -> 178974.46 | Q24: =+O24+P24 -> 482326.63 | R24: =+N24-Q24 -> 180826.96
A25: Transportation | B25: =Transportation!B38 -> 36735.93 | C25: =Transportation!C38 -> 33623.251 | D25: =Transportation!D38 -> 32006.344 | E25: =Transportation!E38 -> 17485.776 | F25: =Transportation!F38 -> 12244.584 | G25: =Transportation!G38 -> 8830.0626 | H25: =Transportation!H38 -> 17491.043 | I25: =Transportation!I38 -> 13236.522 | ... M25: =Transportation!M38 -> 32217.411 | N25: =SUM(B25:M25) -> 229805.7 | O25: =+N59 -> 121193.38
A26: Innoceanna | B26: =Innoceanna!B38 -> 2076.0095 | C26: =Innoceanna!C38 -> 1862.4492 | D26: =Innoceanna!D38 -> 1795.6381 | E26: =Innoceanna!E38 -> 1054.5827 | F26: =Innoceanna!F38 -> 606.09535 | G26: =Innoceanna!G38 -> 464.15477 | H26: =Innoceanna!H38 -> 940.22726 | I26: =Innoceanna!I38 -> 654.20846 | ... M26: =Innoceanna!M38 -> 2244.243 | N26: =SUM(B26:M26) -> 13021.985 | O26: =+N60 -> 178974.46
A27: Sustainability Fee | B27: ='Sustainability Fee'!B38 -> 35154 | C27: ='Sustainability Fee'!C38 -> 32175.36 | D27: ='Sustainability Fee'!D38 -> 30628.08 | E27: ='Sustainability Fee'!E38 -> 16732.8 | F27: ='Sustainability Fee'!F38 -> 11717.305 | G27: ='Sustainability Fee'!G38 -> 8449.8207 | H27: ='Sustainability Fee'!H38 -> 16737.84 | I27: ='Sustainability Fee'!I38 -> 12666.528 | ... M27: ='Sustainability Fee'!M38 -> 30830.058 | N27: =SUM(B27:M27) -> 219909.76 | O27: =+N61 -> 105632.78
A28: Laundry | B28: =Laundry!B38 -> 900 | C28: =Laundry!C38 -> 900 | D28: =Laundry!D38 -> 900 | E28: =Laundry!E38 -> 900 | F28: =Laundry!F38 -> 900 | G28: =Laundry!G38 -> 900 | H28: =Laundry!H38 -> 900 | I28: =Laundry!I38 -> 900 | ... M28: =Laundry!M38 -> 900 | N28: =SUM(B28:M28) -> 9900 | O28: =+N62 -> 6079.9388
A29: TOTAL REVENUE | B29: =SUM(B18:B28) -> 758769.99 | C29: =SUM(C18:C28) -> 686825.21 | D29: =SUM(D18:D28) -> 659282.54 | E29: =SUM(E18:E28) -> 378005.83 | F29: =SUM(F18:F28) -> 239918.16 | G29: =SUM(G18:G28) -> 180206.05 | H29: =SUM(H18:H28) -> 354980.72 | I29: =SUM(I18:I28) -> 258609.5 | ... O29: =SUM(O18:O28) -> 2904725.3 | P29: =(N29-O29)/O29 -> 0.64706782
A31: Hotel Package | B31: =+B18+B19+B24+B25+B27 -> 706457.82 | C31: =+C18+C19+C24+C25+C27 -> 639067.29 | D31: =+D18+D19+D24+D25+D27 -> 612885.64 | E31: =+E18+E19+E24+E25+E27 -> 349550.17 | F31: =+F18+F19+F24+F25+F27 -> 218298.61 | G31: =+G18+G19+G24+G25+G27 -> 162838.92 | H31: =+H18+H19+H24+H25+H27 -> 326720.85 | I31: =+I18+I19+I24+I25+I27 -> 235785.69 | ... N31: =+N18+N19+N24+N25+N27 -> 4426380.8
A32: Hotel Sales on Property | B32: =+B20+B22+B23+B26+B28 -> 52312.171 | C32: =+C20+C22+C23+C26+C28 -> 47757.921 | D32: =+D20+D22+D23+D26+D28 -> 46396.896 | E32: =+E20+E22+E23+E26+E28 -> 28455.658 | F32: =+F20+F22+F23+F26+F28 -> 21619.542 | G32: =+G20+G22+G23+G26+G28 -> 17367.123 | H32: =+H20+H22+H23+H26+H28 -> 28259.875 | I32: =+I20+I22+I23+I26+I28 -> 22823.811 | ... N32: =+N20+N22+N23+N26+N28 -> 357898.76
A34: Total | B34: =SUM(B31:B33) -> 758769.99 | C34: =SUM(C31:C33) -> 686825.21 | D34: =SUM(D31:D33) -> 659282.54 | E34: =SUM(E31:E33) -> 378005.83 | F34: =SUM(F31:F33) -> 239918.16 | G34: =SUM(G31:G33) -> 180206.05 | H34: =SUM(H31:H33) -> 354980.72 | I34: =SUM(I31:I33) -> 258609.5 | ... N34: =SUM(N31:N33) -> 4784279.6
A36: Relation Package and Property Sales | B36: =+B32/B31 -> 0.074048541 | C36: =+C32/C31 -> 0.074730661 | D36: =+D32/D31 -> 0.075702371 | E36: =+E32/E31 -> 0.081406506 | F36: =+F32/F31 -> 0.099036549 | G36: =+G32/G31 -> 0.10665216 | H36: =+H32/H31 -> 0.086495476 | I36: =+I32/I31 -> 0.096798968 | ... N36: =+N32/N31 -> 0.080855844
A38: Relation Rooms Only and Property Sales | B38: =+B32/B18 -> 0.12599213 | C38: =+C32/C18 -> 0.12821268 | D38: =+D32/D18 -> 0.12919334 | E38: =+E32/E18 -> 0.13491431 | F38: =+F32/F18 -> 0.17835099 | G38: =+G32/G18 -> 0.18708332 | H38: =+H32/H18 -> 0.15028215 | I38: =+I32/I18 -> 0.17443837 | ... N38: =+N32/N18 -> 0.13742097
A41: 2025 Revenue Forecast – Summary
A43: Key Indicators 2025 (Forecast) | B43: January | C43: February | D43: March | E43: April | F43: May | G43: June | H43: July | I43: August | J43: September | K43: October | L43: November | M43: December | N43: TOTAL
A44: Indicator
A46: Total available Rooms | B46: =+Rooms!C20 -> 930 | C46: =+Rooms!D20 -> 840 | D46: =+Rooms!E20 -> 930 | E46: =+Rooms!F20 -> 900 | F46: =+Rooms!G20 -> 930 | G46: =+Rooms!H20 -> 900 | H46: =+Rooms!I20 -> 930 | I46: =+Rooms!J20 -> 930 | J46: =+Rooms!K20 -> 900 | L46: =+Rooms!M20 -> 900 | M46: =+Rooms!N20 -> 930 | N46: =+Rooms!O20 -> 10950
A47: Total Rooms Occupied | B47: =+Rooms!C21 -> 454 | C47: =+Rooms!D21 -> 479 | D47: =+Rooms!E21 -> 519 | E47: =+Rooms!F21 -> 239 | F47: =+Rooms!G21 -> 114 | G47: =+Rooms!H21 -> 102 | H47: =+Rooms!I21 -> 274 | I47: =+Rooms!J21 -> 220 | J47: =+Rooms!K21 -> 28 | L47: =+Rooms!M21 -> 230 | M47: =+Rooms!N21 -> 470 | N47: =+Rooms!O21 -> 3179 | O47: =+N13-N47 -> 1184.2889 | P47: =+O47/N47 -> 0.37253504
A48: Total Guests | B48: =+Rooms!C22 -> 809 | C48: =+Rooms!D22 -> 893 | D48: =+Rooms!E22 -> 962 | E48: =+Rooms!F22 -> 428 | F48: =+Rooms!G22 -> 228 | G48: =+Rooms!H22 -> 183 | H48: =+Rooms!I22 -> 611 | I48: =+Rooms!J22 -> 411 | J48: =+Rooms!K22 -> 27 | L48: =+Rooms!M22 -> 345 | M48: =+Rooms!N22 -> 705 | N48: =+Rooms!O22 -> 5677 | O48: =+N14-N48 -> 2176.92 | P48: =+O48/N48 -> 0.38346309
A49: % Occupancy | B49: =+Rooms!C23 -> 0.48817204 | C49: =+Rooms!D23 -> 0.5702381 | D49: =+Rooms!E23 -> 0.55806452 | E49: =+Rooms!F23 -> 0.26555556 | F49: =+Rooms!G23 -> 0.12258065 | G49: =+Rooms!H23 -> 0.11333333 | H49: =+Rooms!I23 -> 0.29462366 | I49: =+Rooms!J23 -> 0.23655914 | J49: =+Rooms!K23 -> 0.031111111 | L49: =+Rooms!M23 -> 0.25555556 | M49: =+Rooms!N23 -> 0.50537634 | N49: =+Rooms!O23 -> 0.29031963 | O49: =+N15-N49 -> 0.14513834 | P49: =+O49/N49 -> 0.49992601
A50: ADR | B50: =+Rooms!C24 -> 473.50649 | C50: =+Rooms!D24 -> 550.00104 | D50: =+Rooms!E24 -> 478.48852 | E50: =+Rooms!F24 -> 497.89901 | F50: =+Rooms!G24 -> 482.76039 | G50: =+Rooms!H24 -> 379.47717 | H50: =+Rooms!I24 -> 508.05451 | I50: =+Rooms!J24 -> 371.59366 | J50: =+Rooms!K24 -> 402.95929 | L50: =+Rooms!M24 -> 405 | M50: =+Rooms!N24 -> 545 | N50: =+Rooms!O24 -> 484.67682 | O50: =+N16-N50 -> 112.2117 | P50: =+O50/N50 -> 0.23151861
A52: Rooms | B52: =+Rooms!C37 -> 214971.95 | C52: =+Rooms!D37 -> 263450.5 | D52: =+Rooms!E37 -> 248335.54 | E52: =+Rooms!F37 -> 118997.86 | F52: =+Rooms!G37 -> 55034.684 | G52: =+Rooms!H37 -> 38706.671 | H52: =+Rooms!I37 -> 139206.94 | I52: =+Rooms!J37 -> 81750.604 | ... M52: =+Rooms!N37 -> 256150 | N52: =SUM(B52:M52) -> 1540787.6
A53: Food Revenue | B53: ='Food Revenue'!C37 -> 55354.294 | C53: ='Food Revenue'!D37 -> 72196.172 | D53: ='Food Revenue'!E37 -> 70786.323 | E53: ='Food Revenue'!F37 -> 36330.097 | F53: ='Food Revenue'!G37 -> 16129.355 | G53: ='Food Revenue'!H37 -> 13689.425 | H53: ='Food Revenue'!I37 -> 46042.427 | I53: ='Food Revenue'!J37 -> 26588.885 | ... M53: ='Food Revenue'!N37 -> 55066.23 | N53: =SUM(B53:M53) -> 428040.29
A54: Beverage Revenue | B54: ='Beverage Revenue'!B37 -> 25207.195 | C54: ='Beverage Revenue'!C37 -> 20197.816 | D54: ='Beverage Revenue'!D37 -> 24274.211 | E54: ='Beverage Revenue'!E37 -> 12316.933 | F54: ='Beverage Revenue'!F37 -> 6154.7577 | G54: ='Beverage Revenue'!G37 -> 4103.4464 | H54: ='Beverage Revenue'!H37 -> 10937.432 | I54: ='Beverage Revenue'!I37 -> 10347.794 | ... M54: ='Beverage Revenue'!M37 -> 13766.558 | N54: =SUM(B54:M54) -> 136270.41
A55: F&B Mis Revenue | B55: ='F&B Mis Revenue'!B37 -> 0 | C55: ='F&B Mis Revenue'!C37 -> 0 | D55: ='F&B Mis Revenue'!D37 -> 0 | E55: ='F&B Mis Revenue'!E37 -> 0 | F55: ='F&B Mis Revenue'!F37 -> 0 | G55: ='F&B Mis Revenue'!G37 -> 0 | H55: ='F&B Mis Revenue'!H37 -> 33694.582 | I55: ='F&B Mis Revenue'!I37 -> 28.455862 | ... M55: ='F&B Mis Revenue'!M37 -> 0 | N55: =SUM(B55:M55) -> 33723.037
A56: Spa Revenue | B56: ='Spa Revenue'!B37 -> 4663.1676 | C56: ='Spa Revenue'!C37 -> 2486.391 | D56: ='Spa Revenue'!D37 -> 3391.2718 | E56: ='Spa Revenue'!E37 -> 1621.2288 | F56: ='Spa Revenue'!F37 -> 1606.5792 | G56: ='Spa Revenue'!G37 -> 926.92807 | H56: ='Spa Revenue'!H37 -> 2384.8766 | I56: ='Spa Revenue'!I37 -> 1345.0302 | ... M56: ='Spa Revenue'!M37 -> 6200 | N56: =SUM(B56:M56) -> 32500.473
A57: Retail Gift Shop | B57: ='Retail Gift Shop'!B37 -> 2988.2954 | C57: ='Retail Gift Shop'!C37 -> 2207.0827 | D57: ='Retail Gift Shop'!D37 -> 3171.7132 | E57: ='Retail Gift Shop'!E37 -> 2096.9719 | F57: ='Retail Gift Shop'!F37 -> 814.49086 | G57: ='Retail Gift Shop'!G37 -> 645.62889 | H57: ='Retail Gift Shop'!H37 -> 2120.9385 | I57: ='Retail Gift Shop'!I37 -> 1361.6524 | ... M57: ='Retail Gift Shop'!M37 -> 1874.8 | N57: =SUM(B57:M57) -> 18170.774
A58: Activities | B58: =Activities!B37 -> 40198.406 | C58: =Activities!C37 -> 42643.297 | D58: =Activities!D37 -> 49187.767 | E58: =Activities!E37 -> 27966.927 | F58: =Activities!F37 -> 11004.493 | G58: =Activities!G37 -> 8206.2238 | H58: =Activities!H37 -> 25587.581 | I58: =Activities!I37 -> 17736.76 | ... M58: =Activities!M37 -> 48947.76 | N58: =SUM(B58:M58) -> 303352.17
A59: Transportation | B59: =Transportation!B37 -> 11835.556 | C59: =Transportation!C37 -> 14786.668 | D59: =Transportation!D37 -> 17991.069 | E59: =Transportation!E37 -> 18846.319 | F59: =Transportation!F37 -> 4777.0945 | G59: =Transportation!G37 -> 5542.9628 | H59: =Transportation!H37 -> 10251.493 | I59: =Transportation!I37 -> 9337.3146 | ... M59: =Transportation!M37 -> 16851.7 | N59: =SUM(B59:M59) -> 121193.38
A60: Innoceanna | B60: =Innoceanna!B37 -> 23824.917 | C60: =Innoceanna!C37 -> 29052.61 | D60: =Innoceanna!D37 -> 29098.835 | E60: =Innoceanna!E37 -> 17280.51 | F60: =Innoceanna!F37 -> 6406.4185 | G60: =Innoceanna!G37 -> 8041.9542 | H60: =Innoceanna!H37 -> 18147.843 | I60: =Innoceanna!I37 -> 12571.37 | ... M60: =Innoceanna!M37 -> 23435 | N60: =SUM(B60:M60) -> 178974.46
A61: Sustainability Fee | B61: ='Sustainability Fee'!B37 -> 12471.268 | C61: ='Sustainability Fee'!C37 -> 15628.972 | D61: ='Sustainability Fee'!D37 -> 16011.264 | E61: ='Sustainability Fee'!E37 -> 10939.195 | F61: ='Sustainability Fee'!F37 -> 5052.0297 | G61: ='Sustainability Fee'!G37 -> 3797.2238 | H61: ='Sustainability Fee'!H37 -> 8661.5231 | I61: ='Sustainability Fee'!I37 -> 6901.8361 | ... M61: ='Sustainability Fee'!M37 -> 15849.115 | N61: =SUM(B61:M61) -> 105632.78
A62: Laundry | B62: =Laundry!B37 -> 639.97343 | C62: =Laundry!C37 -> 509.78357 | D62: =Laundry!D37 -> 575.97723 | E62: =Laundry!E37 -> 309.64348 | F62: =Laundry!F37 -> 331.48465 | G62: =Laundry!G37 -> 88.58094 | H62: =Laundry!H37 -> 450.38698 | I62: =Laundry!I37 -> 474.10849 | ... M62: =Laundry!M37 -> 900 | N62: =SUM(B62:M62) -> 6079.9388
A63: TOTAL REVENUE | B63: =SUM(B52:B62) -> 392155.02 | C63: =SUM(C52:C62) -> 463159.29 | D63: =SUM(D52:D62) -> 462823.97 | E63: =SUM(E52:E62) -> 246705.69 | F63: =SUM(F52:F62) -> 107311.39 | G63: =SUM(G52:G62) -> 83749.045 | H63: =SUM(H52:H62) -> 297486.02 | I63: =SUM(I52:I62) -> 168443.81 | ... N63: =SUM(N52:N62) -> 2904725.3 | O63: =+N29-N63 -> 1879554.3
O65: =+O63/N63 -> 0.64706782
A66: 2024 Revenue Actual – Summary
A68: Key Indicators 2024 (Actual) | B68: January | C68: February | D68: March | E68: April | F68: May | G68: June | H68: July | I68: August | J68: September | K68: October | L68: November | M68: December | N68: TOTAL
A69: Indicator
A71: Total available Rooms | B71: =+Rooms!C13 -> 930 | C71: =+Rooms!D13 -> 870 | D71: =+Rooms!E13 -> 930 | E71: =+Rooms!F13 -> 900 | F71: =+Rooms!G13 -> 930 | G71: =+Rooms!H13 -> 900 | H71: =+Rooms!I13 -> 930 | I71: =+Rooms!J13 -> 930 | J71: =+Rooms!K13 -> 900 | L71: =+Rooms!M13 -> 900 | M71: =+Rooms!N13 -> 930 | N71: =+Rooms!O13 -> 10980
A72: Total Rooms Occupied | B72: =+Rooms!C14 -> 429 | C72: =+Rooms!D14 -> 456 | D72: =+Rooms!E14 -> 448 | E72: =+Rooms!F14 -> 259 | F72: =+Rooms!G14 -> 176 | G72: =+Rooms!H14 -> 98 | H72: =+Rooms!I14 -> 249 | I72: =+Rooms!J14 -> 157 | ... N72: =+Rooms!O14 -> 2774
A73: Total Guests | B73: =+Rooms!C15 -> 711 | C73: =+Rooms!D15 -> 834 | D73: =+Rooms!E15 -> 835 | E73: =+Rooms!F15 -> 544 | F73: =+Rooms!G15 -> 311 | G73: =+Rooms!H15 -> 160 | H73: =+Rooms!I15 -> 429 | I73: =+Rooms!J15 -> 310 | ... N73: =+Rooms!O15 -> 5076
A74: % Occupancy | B74: =+Rooms!C16 -> 0.4613 | C74: =+Rooms!D16 -> 0.5241 | D74: =+Rooms!E16 -> 0.4817 | E74: =+Rooms!F16 -> 0.2878 | F74: =+Rooms!G16 -> 0.1892 | G74: =+Rooms!H16 -> 0.1089 | H74: =+Rooms!I16 -> 0.2677 | I74: =+Rooms!J16 -> 0.1688 | J74: =+Rooms!K16 -> 0.0067 | L74: =+Rooms!M16 -> 0.1989 | M74: =+Rooms!N16 -> 0.3409 | N74: =+Rooms!O16 -> 0.25264117
A75: ADR | B75: =+Rooms!C17 -> 359.84047 | C75: =+Rooms!D17 -> 465.18852 | D75: =+Rooms!E17 -> 389.00314 | E75: =+Rooms!F17 -> 378.9522 | F75: =+Rooms!G17 -> 231.30814 | G75: =+Rooms!H17 -> 291.12236 | H75: =+Rooms!I17 -> 426.03102 | I75: =+Rooms!J17 -> 403.28888 | J75: =+Rooms!K17 -> 434.33013 | L75: =+Rooms!M17 -> 471.30737 | M75: =+Rooms!N17 -> 729.00372 | N75: =+Rooms!O17 -> 431.01011
A77: Rooms | B77: =+Rooms!C36 -> 154371.56 | C77: =+Rooms!D36 -> 212125.96 | D77: =+Rooms!E36 -> 174273.41 | E77: =+Rooms!F36 -> 98148.619 | F77: =+Rooms!G36 -> 40710.232 | G77: =+Rooms!H36 -> 28529.992 | H77: =+Rooms!I36 -> 106081.72 | I77: =+Rooms!J36 -> 63316.354 | ... M77: =+Rooms!N36 -> 231094.18 | N77: =SUM(B77:M77) -> 1195622
A78: Food Revenue | B78: ='Food Revenue'!C36 -> 40539.559 | C78: ='Food Revenue'!D36 -> 51930.053 | D78: ='Food Revenue'!E36 -> 51479.405 | E78: ='Food Revenue'!F36 -> 31261.324 | F78: ='Food Revenue'!G36 -> 12340.602 | G78: ='Food Revenue'!H36 -> 10377.842 | H78: ='Food Revenue'!I36 -> 27201.505 | I78: ='Food Revenue'!J36 -> 20146.528 | ... M78: ='Food Revenue'!N36 -> 48192.13 | N78: =SUM(B78:M78) -> 317918.87
A79: Beverage Revenue | B79: ='Beverage Revenue'!B36 -> 13382.938 | C79: ='Beverage Revenue'!C36 -> 18605.558 | D79: ='Beverage Revenue'!D36 -> 15732.728 | E79: ='Beverage Revenue'!E36 -> 9825.4252 | F79: ='Beverage Revenue'!F36 -> 6010.1144 | G79: ='Beverage Revenue'!G36 -> 1924.1243 | H79: ='Beverage Revenue'!H36 -> 5599.9203 | I79: ='Beverage Revenue'!I36 -> 5103.7981 | ... M79: ='Beverage Revenue'!M36 -> 11187.446 | N79: =SUM(B79:M79) -> 95399.695
A80: F&B Mis Revenue | B80: ='F&B Mis Revenue'!B36 -> 0 | C80: ='F&B Mis Revenue'!C36 -> 0 | D80: ='F&B Mis Revenue'!D36 -> 0 | E80: ='F&B Mis Revenue'!E36 -> 0 | F80: ='F&B Mis Revenue'!F36 -> 0 | G80: ='F&B Mis Revenue'!G36 -> 0 | H80: ='F&B Mis Revenue'!H36 -> 0 | I80: ='F&B Mis Revenue'!I36 -> 0 | ... L80: ='F&B Mis Revenue'!L36 -> 0 | M80: 2745.8276 | N80: =SUM(B80:M80) -> 2745.8276
A81: Spa Revenue | B81: ='Spa Revenue'!B36 -> 2609.9181 | C81: ='Spa Revenue'!C36 -> 2686.4514 | D81: ='Spa Revenue'!D36 -> 2436.6407 | E81: ='Spa Revenue'!E36 -> 2246.1571 | F81: ='Spa Revenue'!F36 -> 1706.7846 | G81: ='Spa Revenue'!G36 -> 829.79373 | H81: ='Spa Revenue'!H36 -> 780.02352 | I81: ='Spa Revenue'!I36 -> 1309.8757 | ... M81: ='Spa Revenue'!M36 -> 2891.0677 | N81: =SUM(B81:M81) -> 18187.705
A82: Retail Gift Shop | B82: ='Retail Gift Shop'!B36 -> 778.5 | C82: ='Retail Gift Shop'!C36 -> 778.5 | D82: ='Retail Gift Shop'!D36 -> 778.5 | E82: ='Retail Gift Shop'!E36 -> 778.5 | F82: ='Retail Gift Shop'!F36 -> 778.5 | G82: ='Retail Gift Shop'!G36 -> 778.5 | H82: ='Retail Gift Shop'!H36 -> 778.5 | I82: ='Retail Gift Shop'!I36 -> 778.5 | ... M82: ='Retail Gift Shop'!M36 -> 778.5 | N82: =SUM(B82:M82) -> 9342
A83: Activities | B83: =Activities!B36 -> 23251.898 | C83: =Activities!C36 -> 35457.988 | D83: =Activities!D36 -> 29360.589 | E83: =Activities!E36 -> 19914.132 | F83: =Activities!F36 -> 4278.6451 | G83: =Activities!G36 -> 4884.2611 | H83: =Activities!H36 -> 12683.715 | I83: =Activities!I36 -> 11513.628 | ... M83: =Activities!M36 -> 28389.368 | N83: =SUM(B83:M83) -> 186552.73
A84: Transportation | B84: =Transportation!B36 -> 6839.4117 | C84: =Transportation!C36 -> 8643.119 | D84: =Transportation!D36 -> 9479.8495 | E84: =Transportation!E36 -> 4705.2109 | F84: =Transportation!F36 -> 971.64709 | G84: =Transportation!G36 -> 1180.5132 | H84: =Transportation!H36 -> 18097.012 | I84: =Transportation!I36 -> 2716.9387 | ... M84: =Transportation!M36 -> 7363.247 | N84: =SUM(B84:M84) -> 64448.166
A85: Innoceanna | B85: =Innoceanna!B36 -> 19035.44 | C85: =Innoceanna!C36 -> 24083.111 | D85: =Innoceanna!D36 -> 23552.045 | E85: =Innoceanna!E36 -> 14307.943 | F85: =Innoceanna!F36 -> 5683.7656 | G85: =Innoceanna!G36 -> 6108.9314 | H85: =Innoceanna!H36 -> 11978.498 | I85: =Innoceanna!I36 -> 9877.4202 | ... M85: =Innoceanna!M36 -> 18996.75 | N85: =SUM(B85:M85) -> 141959.13
A86: Sustainability Fee | B86: ='Sustainability Fee'!B36 -> 0 | C86: ='Sustainability Fee'!C36 -> 0 | D86: ='Sustainability Fee'!D36 -> 0 | E86: ='Sustainability Fee'!E36 -> 0 | F86: ='Sustainability Fee'!F36 -> 0 | G86: ='Sustainability Fee'!G36 -> 44.357877 | H86: ='Sustainability Fee'!H36 -> 753.07831 | I86: ='Sustainability Fee'!I36 -> 1265.7321 | ... M86: ='Sustainability Fee'!M36 -> 7524.7718 | N86: =SUM(B86:M86) -> 13594.122
A87: Laundry | B87: =Laundry!B36 -> 1057.5777 | C87: =Laundry!C36 -> 1705.995 | D87: =Laundry!D36 -> 2060.9848 | E87: =Laundry!E36 -> 1412.55 | F87: =Laundry!F36 -> 445.89118 | G87: =Laundry!G36 -> 569.43434 | H87: =Laundry!H36 -> 421.22071 | I87: =Laundry!I36 -> 338.19589 | ... M87: =Laundry!M36 -> 33.48 | N87: =SUM(B87:M87) -> 9916.657
A88: TOTAL REVENUE | B88: =SUM(B77:B87) -> 261866.8 | C88: =SUM(C77:C87) -> 356016.74 | D88: =SUM(D77:D87) -> 309154.15 | E88: =SUM(E77:E87) -> 182599.86 | F88: =SUM(F77:F87) -> 72926.183 | G88: =SUM(G77:G87) -> 55227.749 | H88: =SUM(H77:H87) -> 184375.2 | I88: =SUM(I77:I87) -> 116366.97 | ... N88: =SUM(N77:N87) -> 2055686.9
A93: 2026 Revenue Budget – Summary ON THE BOOKS | D93: as of Today October 28th, 2025 from Opera on the book report.
B95: January | C95: February | D95: March | E95: April | F95: May | G95: June | H95: July | I95: August | J95: September | K95: October | L95: November | M95: December | N95: TOTAL
A96: Indicator | N96: =SUM(B96:M96) -> 0
N97: =SUM(B97:M97) -> 0
A98: Total available Rooms | B98: =30*31 -> 930 | C98: =30*29 -> 870 | D98: =30*31 -> 930 | E98: =+Rooms!F40 -> 0 | F98: =+Rooms!G40 -> 0 | G98: =+Rooms!H40 -> 0 | H98: =+Rooms!I40 -> 0 | I98: =+Rooms!J40 -> 0 | J98: =+Rooms!K40 -> 0 | K98: =+Rooms!L40 -> 0 | L98: =+Rooms!M40 -> 0 | M98: =+Rooms!N40 -> 0 | N98: =SUM(B98:M98) -> 2730
A99: Total Rooms Occupied | B99: 403 | C99: 278 | D99: 240 | E99: =+Rooms!F41 -> 0.77243964 | F99: =+Rooms!G41 -> 1.2025941 | G99: =+Rooms!H41 -> 1.3983192 | H99: =+Rooms!I41 -> 0.35083391 | I99: =+Rooms!J41 -> 0.60049815 | J99: =+Rooms!K41 -> 2.5428524 | K99: =+Rooms!L41 -> -1 | L99: =+Rooms!M41 -> 1.4144057 | M99: =+Rooms!N41 -> 0.7522881 | N99: =SUM(B99:M99) -> 929.03423
A100: Total Guests | B100: 775 | C100: 547 | D100: 437 | E100: =+Rooms!F42 -> 91918.667 | F100: =+Rooms!G42 -> 66184.386 | G100: =+Rooms!H42 -> 54124.282 | H100: =+Rooms!I42 -> 48838.514 | I100: =+Rooms!J42 -> 49091.087 | J100: =+Rooms!K42 -> 28690.647 | K100: =+Rooms!L42 -> -19750 | L100: =+Rooms!M42 -> 131751.89 | M100: =+Rooms!O42 -> 1063609.4 | N100: =SUM(B100:M100) -> 1516217.9
A101: % Occupancy | B101: =+B99/B98 -> 0.43333333 | C101: =+C99/C98 -> 0.31954023 | D101: =+D99/D98 -> 0.25806452 | E101: =+Rooms!F43 -> 0 | F101: =+Rooms!G43 -> 0 | G101: =+Rooms!H43 -> 0 | H101: =+Rooms!I43 -> 0 | I101: =+Rooms!J43 -> 0 | J101: =+Rooms!K43 -> 0 | K101: =+Rooms!L43 -> 0 | L101: =+Rooms!M43 -> 0 | ... N101: =+Rooms!O43 -> 0
A102: ADR | B102: =+B104/B99 -> 1398.5692 | C102: =+C104/C99 -> 1187.3068 | D102: =+D104/D99 -> 1178.0147 | E102: =+E104/E99 -> 140494.71 | F102: =+Rooms!G44 -> 0 | G102: =+Rooms!H44 -> 0 | H102: =+Rooms!I44 -> 0 | I102: =+Rooms!J44 -> 0 | J102: =+Rooms!K44 -> 0 | K102: =+Rooms!L44 -> 0 | L102: =+Rooms!M44 -> 0 | M102: =+Rooms!N44 -> 0 | N102: =+Rooms!O44 -> 0
A104: TOTAL REVENUE | B104: 563623.37 | C104: 330071.3 | D104: 282723.53 | E104: 108523.68 | F104: 64106.33 | G104: 13553.99 | H104: 5023 | I104: 8704.33 | J104: 4941.49 | K104: 0 | L104: 57721.5 | M104: 5798.2 | N104: =SUM(B104:M104) -> 1444790.7
N105: =SUM(B105:M105) -> 0
A106: TOTAL REVENUE | B106: =SUM(B104:B105) -> 563623.37 | C106: =SUM(C104:C105) -> 330071.3 | D106: =SUM(D104:D105) -> 282723.53 | E106: =SUM(E104:E105) -> 108523.68 | F106: =SUM(F104:F105) -> 64106.33 | G106: =SUM(G104:G105) -> 13553.99 | H106: =SUM(H104:H105) -> 5023 | I106: =SUM(I104:I105) -> 8704.33 | ... N106: =SUM(N104:N105) -> 1444790.7
A108: GAP | B108: =+B104-B29 -> -195146.62 | C108: =+C104-C29 -> -356753.91 | D108: =+D104-D29 -> -376559.01 | E108: =+E104-E29 -> -269482.15 | F108: =+F104-F29 -> -175811.83 | G108: =+G104-G29 -> -166652.06 | H108: =+H104-H29 -> -349957.72 | I108: =+I104-I29 -> -249905.17 | ... M108: =+M104-M29 -> -746625.42 | N108: =SUM(B108:M108) -> -3339488.9

Sheet Rates 2026
C4: 46023 | D4: 46024 | E4: 46025 | F4: 46026 | G4: 46027 | H4: 46028 | I4: 46029 | J4: 46030 | K4: 46031 | L4: 46032 | M4: 46033 | N4: 46034
B6: Units Available | C6: 30 | D6: 30 | E6: 30 | F6: 30 | G6: 30 | H6: 30 | I6: 30 | J6: 30 | K6: 30 | L6: 30 | M6: 30 | N6: 30
B7: Day per month | C7: 31 | D7: 28 | E7: 31 | F7: 30 | G7: 31 | H7: 30 | I7: 31 | J7: 31 | K7: 30 | L7: 31 | M7: 30 | N7: 31
B9: Total Nights Available | C9: =+C6*C7 -> 930 | D9: =+D6*D7 -> 840 | E9: =+E6*E7 -> 930 | F9: =+F6*F7 -> 900 | G9: =+G6*G7 -> 930 | H9: =+H6*H7 -> 900 | I9: =+I6*I7 -> 930 | J9: =+J6*J7 -> 930 | ... N9: =+N6*N7 -> 930
B12: Units Category
A14: 1 | B14: Corcovado Deluxe Villas, King bed | C14: 6 | D14: 6 | E14: 6 | F14: 6 | G14: 6 | H14: 6 | I14: 6 | J14: 6 | K14: 6 | L14: 6 | M14: 6 | N14: 6
A15: 2 | B15: Carate Deluxe Villa Double Beds | C15: 2 | D15: 2 | E15: 2 | F15: 2 | G15: 2 | H15: 2 | I15: 2 | J15: 2 | K15: 2 | L15: 2 | M15: 2 | N15: 2
A16: 3 | B16: Agujas Villa 2 Queen Beds | C16: 4 | D16: 4 | E16: 4 | F16: 4 | G16: 4 | H16: 4 | I16: 4 | J16: 4 | K16: 4 | L16: 4 | M16: 4 | N16: 4
A17: 4 | B17: Sirena Suites, Queen Bed (conecting) | C17: 8 | D17: 8 | E17: 8 | F17: 8 | G17: 8 | H17: 8 | I17: 8 | J17: 8 | K17: 8 | L17: 8 | M17: 8 | N17: 8
A18: 5 | B18: Treehouse king bed | C18: 5 | D18: 5 | E18: 5 | F18: 5 | G18: 5 | H18: 5 | I18: 5 | J18: 5 | K18: 5 | L18: 5 | M18: 5 | N18: 5
A19: 6 | B19: 5 Elements Treehouse king bed | C19: 5 | D19: 5 | E19: 5 | F19: 5 | G19: 5 | H19: 5 | I19: 5 | J19: 5 | K19: 5 | L19: 5 | M19: 5 | N19: 5
B20: Total | C20: =SUM(C14:C19) -> 30 | D20: =SUM(D14:D19) -> 30 | E20: =SUM(E14:E19) -> 30 | F20: =SUM(F14:F19) -> 30 | G20: =SUM(G14:G19) -> 30 | H20: =SUM(H14:H19) -> 30 | I20: =SUM(I14:I19) -> 30 | J20: =SUM(J14:J19) -> 30 | ... N20: =SUM(N14:N19) -> 30
B23: Total Room Nights Available per Category
A25: 1 | B25: Corcovado Deluxe Villas, King bed | C25: =+C14*C$7 -> 186 | D25: =+D14*D$7 -> 168 | E25: =+E14*E$7 -> 186 | F25: =+F14*F$7 -> 180 | G25: =+G14*G$7 -> 186 | H25: =+H14*H$7 -> 180 | I25: =+I14*I$7 -> 186 | J25: =+J14*J$7 -> 186 | K25: =+K14*K$7 -> 180 | M25: =+M14*M$7 -> 180 | N25: =+N14*N$7 -> 186 | O25: =SUM(C25:N25) -> 2004
A26: 2 | B26: Carate Deluxe Villa Double Beds | C26: =+C15*C$7 -> 62 | D26: =+D15*D$7 -> 56 | E26: =+E15*E$7 -> 62 | F26: =+F15*F$7 -> 60 | G26: =+G15*G$7 -> 62 | H26: =+H15*H$7 -> 60 | I26: =+I15*I$7 -> 62 | J26: =+J15*J$7 -> 62 | K26: =+K15*K$7 -> 60 | M26: =+M15*M$7 -> 60 | N26: =+N15*N$7 -> 62 | O26: =SUM(C26:N26) -> 668
A27: 3 | B27: Agujas Villa 2 Queen Beds | C27: =+C16*C$7 -> 124 | D27: =+D16*D$7 -> 112 | E27: =+E16*E$7 -> 124 | F27: =+F16*F$7 -> 120 | G27: =+G16*G$7 -> 124 | H27: =+H16*H$7 -> 120 | I27: =+I16*I$7 -> 124 | J27: =+J16*J$7 -> 124 | K27: =+K16*K$7 -> 120 | M27: =+M16*M$7 -> 120 | N27: =+N16*N$7 -> 124 | O27: =SUM(C27:N27) -> 1336
A28: 4 | B28: Sirena Suites, Queen Bed (conecting) | C28: =+C17*C$7 -> 248 | D28: =+D17*D$7 -> 224 | E28: =+E17*E$7 -> 248 | F28: =+F17*F$7 -> 240 | G28: =+G17*G$7 -> 248 | H28: =+H17*H$7 -> 240 | I28: =+I17*I$7 -> 248 | J28: =+J17*J$7 -> 248 | K28: =+K17*K$7 -> 240 | M28: =+M17*M$7 -> 240 | N28: =+N17*N$7 -> 248 | O28: =SUM(C28:N28) -> 2672
A29: 5 | B29: Treehouse king bed | C29: =+C18*C$7 -> 155 | D29: =+D18*D$7 -> 140 | E29: =+E18*E$7 -> 155 | F29: =+F18*F$7 -> 150 | G29: =+G18*G$7 -> 155 | H29: =+H18*H$7 -> 150 | I29: =+I18*I$7 -> 155 | J29: =+J18*J$7 -> 155 | K29: =+K18*K$7 -> 150 | M29: =+M18*M$7 -> 150 | N29: =+N18*N$7 -> 155 | O29: =SUM(C29:N29) -> 1670
A30: 6 | B30: 5 Elements Treehouse king bed | C30: =+C19*C$7 -> 155 | D30: =+D19*D$7 -> 140 | E30: =+E19*E$7 -> 155 | F30: =+F19*F$7 -> 150 | G30: =+G19*G$7 -> 155 | H30: =+H19*H$7 -> 150 | I30: =+I19*I$7 -> 155 | J30: =+J19*J$7 -> 155 | K30: =+K19*K$7 -> 150 | M30: =+M19*M$7 -> 150 | N30: =+N19*N$7 -> 155 | O30: =SUM(C30:N30) -> 1670
B32: Total | C32: =SUM(C25:C31) -> 930 | D32: =SUM(D25:D31) -> 840 | E32: =SUM(E25:E31) -> 930 | F32: =SUM(F25:F31) -> 900 | G32: =SUM(G25:G31) -> 930 | H32: =SUM(H25:H31) -> 900 | I32: =SUM(I25:I31) -> 930 | J32: =SUM(J25:J31) -> 930 | ... O32: =SUM(O25:O31) -> 10020
B35: Rack Rates Rooms only | R35: Rack Rates Rooms only
B37: Room Type | C37: January | D37: February | E37: March | F37: April | G37: May | H37: June | I37: July | J37: August | K37: September | L37: October | M37: November | N37: December | R37: Room Type | S37: January | T37: February | U37: March | V37: April | W37: May | X37: June | Y37: July | Z37: August | AA37: September | AB37: October | AC37: November | AD37: December
A38: 1 | B38: Corcovado Deluxe Villas, King bed | C38: 725 | D38: 725 | E38: 725 | F38: 725 | G38: 615 | H38: 615 | I38: 615 | J38: 615 | K38: 560 | L38: 560 | M38: 575 | N38: 830 | R38: Corcovado Deluxe Villas, King bed | S38: 525 | T38: 525 | U38: 525 | V38: 505 | W38: 455 | X38: 440 | Y38: 440 | Z38: 440 | AA38: 405 | AB38: 395 | AC38: 415 | AD38: 575
A39: 2 | B39: Carate Deluxe Villa Double Beds | C39: 670 | D39: 670 | E39: 670 | F39: 635 | G39: 565 | H39: 565 | I39: 565 | J39: 565 | K39: 515 | L39: 515 | M39: 535 | N39: 775 | R39: Carate Deluxe Villa Double Beds | S39: 485 | T39: 485 | U39: 485 | V39: 460 | W39: 435 | X39: 420 | Y39: 420 | Z39: 420 | AA39: 395 | AB39: 375 | AC39: 440 | AD39: 520
A40: 3 | B40: Agujas Villa 2 Queen Beds | C40: 540 | D40: 540 | E40: 540 | F40: 510 | G40: 445 | H40: 445 | I40: 445 | J40: 445 | K40: 405 | L40: 405 | M40: 415 | N40: 630 | R40: Agujas Villa 2 Queen Beds | S40: 445 | T40: 445 | U40: 445 | V40: 415 | W40: 395 | X40: 375 | Y40: 375 | Z40: 375 | AA40: 355 | AB40: 330 | AC40: 360 | AD40: 485
A41: 4 | B41: Sirena Suites, Queen Bed (conecting) | C41: 485 | D41: 485 | E41: 485 | F41: 445 | G41: 395 | H41: 395 | I41: 395 | J41: 395 | K41: 360 | L41: 360 | M41: 375 | N41: 575 | R41: Sirena Suites, Queen Bed (conecting) | S41: 395 | T41: 395 | U41: 395 | V41: 360 | W41: 330 | X41: 315 | Y41: 315 | Z41: 315 | AA41: 290 | AB41: 275 | AC41: 295 | AD41: 410
A42: 5 | B42: Treehouse king bed | C42: 1015 | D42: 1015 | E42: 1015 | F42: 970 | G42: 875 | H42: 875 | I42: 875 | J42: 875 | K42: 810 | L42: 810 | M42: 845 | N42: 1150 | R42: Treehouse king bed | S42: 795 | T42: 795 | U42: 795 | V42: 725 | W42: 655 | X42: 620 | Y42: 620 | Z42: 620 | AA42: 585 | AB42: 530 | AC42: 605 | AD42: 785
A43: 6 | B43: 5 Elements Treehouse king bed | C43: 1130 | D43: 1130 | E43: 1130 | F43: 1065 | G43: 980 | H43: 980 | I43: 980 | J43: 980 | K43: 910 | L43: 910 | M43: 965 | N43: 1282 | R43: 5 Elements Treehouse king bed | S43: 895 | T43: 895 | U43: 895 | V43: 830 | W43: 740 | X43: 685 | Y43: 685 | Z43: 685 | AA43: 630 | AB43: 605 | AC43: 685 | AD43: 895
B47: NET RATE | Q47: =+#REF!/#REF! -> #REF! | AE47: 500
AE48: =+#REF!/AE47 -> #REF!
B50: Occupancy
B51: Room Type | C51: January | D51: February | E51: March | F51: April | G51: May | H51: June | I51: July | J51: August | K51: September | L51: October | M51: November | N51: December | O51: TOTAL | AE51: 650
B52: Corcovado Deluxe Villas, King bed | C52: 606.1 | D52: 606.1 | E52: 606.1 | F52: 606.1 | G52: 514.14 | H52: 514.14 | I52: 514.14 | J52: 514.14 | K52: 468.16 | M52: 480.7 | N52: 693.88 | O52: 589.6608
B53: Carate Deluxe Villa Double Beds | C53: 560.12 | D53: 560.12 | E53: 560.12 | F53: 530.86 | G53: 472.34 | H53: 472.34 | I53: 472.34 | J53: 472.34 | K53: 430.54 | M53: 447.26 | N53: 647.9 | O53: 537.62728 | AE53: 676.41
B54: Agujas Villa 2 Queen Beds | C54: 451.44 | D54: 451.44 | E54: 451.44 | F54: 426.36 | G54: 372.02 | H54: 372.02 | I54: 372.02 | J54: 372.02 | K54: 338.58 | M54: 346.94 | N54: 526.68 | O54: 431.54041
B55: Sirena Suites, Queen Bed (conecting) | C55: 405.46 | D55: 405.46 | E55: 405.46 | F55: 372.02 | G55: 330.22 | H55: 330.22 | I55: 330.22 | J55: 330.22 | M55: 313.5 | N55: 480.7 | O55: 388.71626
B56: Treehouse king bed | C56: 848.54 | D56: 848.54 | E56: 848.54 | F56: 810.92 | G56: 731.5 | H56: 731.5 | I56: 731.5 | J56: 731.5 | M56: 706.42 | N56: 961.4 | O56: 806.34693
B57: 5 Elements Treehouse king bed | C57: 944.68 | D57: 944.68 | E57: 944.68 | F57: 890.34 | G57: 819.28 | H57: 819.28 | I57: 819.28 | J57: 819.28 | M57: 806.74 | N57: 1071.752 | O57: 909.38828
B58: TOTAL | C58: 595.27155 | D58: 583.47405 | E58: 590.96203 | F58: 635.29075 | G58: 521.40328 | H58: 553.7017 | I58: 566.23141 | J58: 520.6179 | K58: 485.58682 | M58: 548.40744 | N58: 733.76344 | O58: 596.88852

Sheet Key Indicators
C4: 46023 | D4: 46024 | E4: 46025 | F4: 46026 | G4: 46027 | H4: 46028 | I4: 46029 | J4: 46030 | K4: 46031 | L4: 46032 | M4: 46033 | N4: 46034
B6: Units Available | C6: 30 | D6: 30 | E6: 30 | F6: 30 | G6: 30 | H6: 30 | I6: 30 | J6: 30 | K6: 30 | L6: 30 | M6: 30 | N6: 30
B7: Day per month | C7: 31 | D7: 28 | E7: 31 | F7: 30 | G7: 31 | H7: 30 | I7: 31 | J7: 31 | K7: 30 | L7: 31 | M7: 30 | N7: 31
B9: Total Nights Available | C9: =+C6*C7 -> 930 | D9: =+D6*D7 -> 840 | E9: =+E6*E7 -> 930 | F9: =+F6*F7 -> 900 | G9: =+G6*G7 -> 930 | H9: =+H6*H7 -> 900 | I9: =+I6*I7 -> 930 | J9: =+J6*J7 -> 930 | ... N9: =+N6*N7 -> 930
B12: Units Category
A14: 1 | B14: Corcovado Deluxe Villas, King bed | C14: 6 | D14: 6 | E14: 6 | F14: 6 | G14: 6 | H14: 6 | I14: 6 | J14: 6 | K14: 6 | L14: 6 | M14: 6 | N14: 6
A15: 2 | B15: Carate Deluxe Villa Double Beds | C15: 2 | D15: 2 | E15: 2 | F15: 2 | G15: 2 | H15: 2 | I15: 2 | J15: 2 | K15: 2 | L15: 2 | M15: 2 | N15: 2
A16: 3 | B16: Agujas Villa 2 Queen Beds | C16: 4 | D16: 4 | E16: 4 | F16: 4 | G16: 4 | H16: 4 | I16: 4 | J16: 4 | K16: 4 | L16: 4 | M16: 4 | N16: 4
A17: 4 | B17: Sirena Suites, Queen Bed (conecting) | C17: 8 | D17: 8 | E17: 8 | F17: 8 | G17: 8 | H17: 8 | I17: 8 | J17: 8 | K17: 8 | L17: 8 | M17: 8 | N17: 8
A18: 5 | B18: Treehouse king bed | C18: 5 | D18: 5 | E18: 5 | F18: 5 | G18: 5 | H18: 5 | I18: 5 | J18: 5 | K18: 5 | L18: 5 | M18: 5 | N18: 5
A19: 6 | B19: 5 Elements Treehouse king bed | C19: 5 | D19: 5 | E19: 5 | F19: 5 | G19: 5 | H19: 5 | I19: 5 | J19: 5 | K19: 5 | L19: 5 | M19: 5 | N19: 5
B20: Total | C20: =SUM(C14:C19) -> 30 | D20: =SUM(D14:D19) -> 30 | E20: =SUM(E14:E19) -> 30 | F20: =SUM(F14:F19) -> 30 | G20: =SUM(G14:G19) -> 30 | H20: =SUM(H14:H19) -> 30 | I20: =SUM(I14:I19) -> 30 | J20: =SUM(J14:J19) -> 30 | ... N20: =SUM(N14:N19) -> 30
B23: Total Room Nights Available per Category
A25: 1 | B25: Corcovado Deluxe Villas, King bed | C25: =+C14*C$7 -> 186 | D25: =+D14*D$7 -> 168 | E25: =+E14*E$7 -> 186 | F25: =+F14*F$7 -> 180 | G25: =+G14*G$7 -> 186 | H25: =+H14*H$7 -> 180 | I25: =+I14*I$7 -> 186 | J25: =+J14*J$7 -> 186 | K25: =+K14*K$7 -> 180 | M25: =+M14*M$7 -> 180 | N25: =+N14*N$7 -> 186 | O25: =SUM(C25:N25) -> 2004
A26: 2 | B26: Carate Deluxe Villa Double Beds | C26: =+C15*C$7 -> 62 | D26: =+D15*D$7 -> 56 | E26: =+E15*E$7 -> 62 | F26: =+F15*F$7 -> 60 | G26: =+G15*G$7 -> 62 | H26: =+H15*H$7 -> 60 | I26: =+I15*I$7 -> 62 | J26: =+J15*J$7 -> 62 | K26: =+K15*K$7 -> 60 | M26: =+M15*M$7 -> 60 | N26: =+N15*N$7 -> 62 | O26: =SUM(C26:N26) -> 668
A27: 3 | B27: Agujas Villa 2 Queen Beds | C27: =+C16*C$7 -> 124 | D27: =+D16*D$7 -> 112 | E27: =+E16*E$7 -> 124 | F27: =+F16*F$7 -> 120 | G27: =+G16*G$7 -> 124 | H27: =+H16*H$7 -> 120 | I27: =+I16*I$7 -> 124 | J27: =+J16*J$7 -> 124 | K27: =+K16*K$7 -> 120 | M27: =+M16*M$7 -> 120 | N27: =+N16*N$7 -> 124 | O27: =SUM(C27:N27) -> 1336
A28: 4 | B28: Sirena Suites, Queen Bed (conecting) | C28: =+C17*C$7 -> 248 | D28: =+D17*D$7 -> 224 | E28: =+E17*E$7 -> 248 | F28: =+F17*F$7 -> 240 | G28: =+G17*G$7 -> 248 | H28: =+H17*H$7 -> 240 | I28: =+I17*I$7 -> 248 | J28: =+J17*J$7 -> 248 | K28: =+K17*K$7 -> 240 | M28: =+M17*M$7 -> 240 | N28: =+N17*N$7 -> 248 | O28: =SUM(C28:N28) -> 2672
A29: 5 | B29: Treehouse king bed | C29: =+C18*C$7 -> 155 | D29: =+D18*D$7 -> 140 | E29: =+E18*E$7 -> 155 | F29: =+F18*F$7 -> 150 | G29: =+G18*G$7 -> 155 | H29: =+H18*H$7 -> 150 | I29: =+I18*I$7 -> 155 | J29: =+J18*J$7 -> 155 | K29: =+K18*K$7 -> 150 | M29: =+M18*M$7 -> 150 | N29: =+N18*N$7 -> 155 | O29: =SUM(C29:N29) -> 1670
A30: 6 | B30: 5 Elements Treehouse king bed | C30: =+C19*C$7 -> 155 | D30: =+D19*D$7 -> 140 | E30: =+E19*E$7 -> 155 | F30: =+F19*F$7 -> 150 | G30: =+G19*G$7 -> 155 | H30: =+H19*H$7 -> 150 | I30: =+I19*I$7 -> 155 | J30: =+J19*J$7 -> 155 | K30: =+K19*K$7 -> 150 | M30: =+M19*M$7 -> 150 | N30: =+N19*N$7 -> 155 | O30: =SUM(C30:N30) -> 1670
B32: Total | C32: =SUM(C25:C31) -> 930 | D32: =SUM(D25:D31) -> 840 | E32: =SUM(E25:E31) -> 930 | F32: =SUM(F25:F31) -> 900 | G32: =SUM(G25:G31) -> 930 | H32: =SUM(H25:H31) -> 900 | I32: =SUM(I25:I31) -> 930 | J32: =SUM(J25:J31) -> 930 | ... O32: =SUM(O25:O31) -> 10020
B35: Rack Rates Rooms only | R35: Rack Rates Rooms only
B37: Room Type | C37: January | D37: February | E37: March | F37: April | G37: May | H37: June | I37: July | J37: August | K37: September | L37: October | M37: November | N37: December | R37: Room Type | S37: January | T37: February | U37: March | V37: April | W37: May | X37: June | Y37: July | Z37: August | AA37: September | AB37: October | AC37: November | AD37: December
A38: 1 | B38: Corcovado Deluxe Villas, King bed | C38: 725 | D38: 725 | E38: 725 | F38: 725 | G38: 615 | H38: 615 | I38: 615 | J38: 615 | K38: 560 | L38: 560 | M38: 575 | N38: 830 | R38: Corcovado Deluxe Villas, King bed | S38: 525 | T38: 525 | U38: 525 | V38: 505 | W38: 455 | X38: 440 | Y38: 440 | Z38: 440 | AA38: 405 | AB38: 395 | AC38: 415 | AD38: 575
A39: 2 | B39: Carate Deluxe Villa Double Beds | C39: 670 | D39: 670 | E39: 670 | F39: 635 | G39: 565 | H39: 565 | I39: 565 | J39: 565 | K39: 515 | L39: 515 | M39: 535 | N39: 775 | R39: Carate Deluxe Villa Double Beds | S39: 485 | T39: 485 | U39: 485 | V39: 460 | W39: 435 | X39: 420 | Y39: 420 | Z39: 420 | AA39: 395 | AB39: 375 | AC39: 440 | AD39: 520
A40: 3 | B40: Agujas Villa 2 Queen Beds | C40: 540 | D40: 540 | E40: 540 | F40: 510 | G40: 445 | H40: 445 | I40: 445 | J40: 445 | K40: 405 | L40: 405 | M40: 415 | N40: 630 | R40: Agujas Villa 2 Queen Beds | S40: 445 | T40: 445 | U40: 445 | V40: 415 | W40: 395 | X40: 375 | Y40: 375 | Z40: 375 | AA40: 355 | AB40: 330 | AC40: 360 | AD40: 485
A41: 4 | B41: Sirena Suites, Queen Bed (conecting) | C41: 485 | D41: 485 | E41: 485 | F41: 445 | G41: 395 | H41: 395 | I41: 395 | J41: 395 | K41: 360 | L41: 360 | M41: 375 | N41: 575 | R41: Sirena Suites, Queen Bed (conecting) | S41: 395 | T41: 395 | U41: 395 | V41: 360 | W41: 330 | X41: 315 | Y41: 315 | Z41: 315 | AA41: 290 | AB41: 275 | AC41: 295 | AD41: 410
A42: 5 | B42: Treehouse king bed | C42: 1015 | D42: 1015 | E42: 1015 | F42: 970 | G42: 875 | H42: 875 | I42: 875 | J42: 875 | K42: 810 | L42: 810 | M42: 845 | N42: 1150 | R42: Treehouse king bed | S42: 795 | T42: 795 | U42: 795 | V42: 725 | W42: 655 | X42: 620 | Y42: 620 | Z42: 620 | AA42: 585 | AB42: 530 | AC42: 605 | AD42: 785
A43: 6 | B43: 5 Elements Treehouse king bed | C43: 1130 | D43: 1130 | E43: 1130 | F43: 1065 | G43: 980 | H43: 980 | I43: 980 | J43: 980 | K43: 910 | L43: 910 | M43: 965 | N43: 1282 | R43: 5 Elements Treehouse king bed | S43: 895 | T43: 895 | U43: 895 | V43: 830 | W43: 740 | X43: 685 | Y43: 685 | Z43: 685 | AA43: 630 | AB43: 605 | AC43: 685 | AD43: 895
B48: % of Sale by Channel | Q48: % of Sale by Channel today and Proforma
C49: =+C37 -> January | D49: =+D37 -> February | E49: =+E37 -> March | F49: =+F37 -> April | G49: =+G37 -> May | H49: =+H37 -> June | I49: =+I37 -> July | J49: =+J37 -> August | ... M49: =+M37 -> November | R49: Forecast 2025 | S49: Proforma
B50: Travel Agency | C50: 0.6 | D50: 0.6 | E50: 0.6 | F50: 0.6 | G50: 0.6 | H50: 0.6 | I50: 0.6 | J50: 0.6 | K50: 0.6 | L50: 0.6 | M50: 0.6 | Q50: Travel Agency | R50: 0.7 | S50: =+C50 -> 0.6
B51: OTAS | C51: 0.05 | D51: 0.05 | E51: 0.05 | F51: 0.05 | G51: 0.05 | H51: 0.05 | I51: 0.05 | J51: 0.05 | K51: 0.05 | L51: 0.05 | M51: 0.05 | Q51: OTAS | R51: 0.05 | S51: =+C51 -> 0.05
B52: DIRECT | C52: 0.35 | D52: 0.35 | E52: 0.35 | F52: 0.35 | G52: 0.35 | H52: 0.35 | I52: 0.35 | J52: 0.35 | K52: 0.35 | L52: 0.35 | M52: 0.35 | Q52: DIRECT | R52: 0.2 | S52: =+C52 -> 0.35
Q54: Commissions by Channel
B55: Total | C55: =SUM(C50:C54) -> 1 | D55: =SUM(D50:D54) -> 1 | E55: =SUM(E50:E54) -> 1 | F55: =SUM(F50:F54) -> 1 | G55: =SUM(G50:G54) -> 1 | H55: =SUM(H50:H54) -> 1 | I55: =SUM(I50:I54) -> 1 | J55: =SUM(J50:J54) -> 1 | ... M55: =SUM(M50:M54) -> 1
R56: Forecast 2025 | S56: Proforma
Q57: Travel Agency | R57: 0.28 | S57: =+M61 -> 0.28
Q58: OTAS | R58: 0.2 | S58: =+M62 -> 0.2
B59: COMMISSIONS By channel | Q59: DIRECT | R59: =+C63 -> 0 | S59: =+M63 -> 0
C60: =+C37 -> January | D60: =+D37 -> February | E60: =+E37 -> March | F60: =+F37 -> April | G60: =+G37 -> May | H60: =+H37 -> June | I60: =+I37 -> July | J60: =+J37 -> August | ... N60: =+N37 -> December
B61: Travel Agency | C61: 0.28 | D61: 0.28 | E61: 0.28 | F61: 0.28 | G61: 0.28 | H61: 0.28 | I61: 0.28 | J61: 0.28 | K61: 0.28 | L61: 0.28 | M61: 0.28 | N61: 0.28
B62: OTAS | C62: 0.2 | D62: 0.2 | E62: 0.2 | F62: 0.2 | G62: 0.2 | H62: 0.2 | I62: 0.2 | J62: 0.2 | K62: 0.2 | L62: 0.2 | M62: 0.2 | N62: 0.2
B63: DIRECT | C63: 0 | D63: 0 | E63: 0 | F63: 0 | G63: 0 | H63: 0 | I63: 0 | J63: 0 | K63: 0 | L63: 0 | M63: 0 | N63: 0
B66: Package Components by person 3DAYS
C68: RACK | Q68: Notas
B69: Transfer In&Out | C69: 105 | D69: =+C69 -> 105 | E69: =+D69 -> 105 | F69: =+E69 -> 105 | G69: =+F69 -> 105 | H69: =+G69 -> 105 | I69: =+H69 -> 105 | J69: =+I69 -> 105 | K69: =+J69 -> 105 | ... N69: =+M69 -> 105 | Q69: =+C69/2 -> 52.5 | R69: Se cobra $57.75 por viaje | T69: =+O69 -> 0 | U69: =+T69*2 -> 0
B70: Breakfast Included | C70: =18*3 -> 54 | D70: =+C70 -> 54 | E70: =+D70 -> 54 | F70: =+E70 -> 54 | G70: =+F70 -> 54 | H70: =+G70 -> 54 | I70: =+H70 -> 54 | J70: =+I70 -> 54 | K70: =+J70 -> 54 | ... N70: =+M70 -> 54 | Q70: Valor del desayuno $16.50 | T70: =+O70+O71+O72 -> 0 | U70: =+T70*3 -> 0
B71: Lunch Included | C71: =36*3 -> 108 | D71: =+C71 -> 108 | E71: =+D71 -> 108 | F71: =+E71 -> 108 | G71: =+F71 -> 108 | H71: =+G71 -> 108 | I71: =+H71 -> 108 | J71: =+I71 -> 108 | K71: =+J71 -> 108 | ... N71: =+M71 -> 108 | Q71: valor del almuerzo $33
B72: Dinner Included | C72: =54*3 -> 162 | D72: =+C72 -> 162 | E72: =+D72 -> 162 | F72: =+E72 -> 162 | G72: =+F72 -> 162 | H72: =+G72 -> 162 | I72: =+H72 -> 162 | J72: =+I72 -> 162 | K72: =+J72 -> 162 | ... N72: =+M72 -> 162 | Q72: valor de la Cena $49.50
B73: Snorkeling Tour | C73: 144 | D73: =+C73 -> 144 | E73: =+D73 -> 144 | F73: =+E73 -> 144 | G73: =+F73 -> 144 | H73: =+G73 -> 144 | I73: =+H73 -> 144 | J73: =+I73 -> 144 | K73: =+J73 -> 144 | ... N73: =+M73 -> 144 | Q73: Precio del tour $297 | T73: =+O73 -> 0 | U73: =+T73+T74 -> 0
B74: PN Walk San Pedrillo | C74: 159 | D74: =+C74 -> 159 | E74: =+D74 -> 159 | F74: =+E74 -> 159 | G74: =+F74 -> 159 | H74: =+G74 -> 159 | I74: =+H74 -> 159 | J74: =+I74 -> 159 | K74: =+J74 -> 159 | ... N74: =+M74 -> 159 | T74: =+O74 -> 0
B76: Total | C76: =SUM(C69:C75) -> 732 | D76: =SUM(D69:D75) -> 732 | E76: =SUM(E69:E75) -> 732 | F76: =SUM(F69:F75) -> 732 | G76: =SUM(G69:G75) -> 732 | H76: =SUM(H69:H75) -> 732 | I76: =SUM(I69:I75) -> 732 | J76: =SUM(J69:J75) -> 732 | ... N76: =SUM(N69:N75) -> 732
B79: Package Components by Night by person
B80: \
C81: RACK
B82: Transfer In&Out | C82: =+C69/3 -> 35 | D82: =+D69/3 -> 35 | E82: =+E69/3 -> 35 | F82: =+F69/3 -> 35 | G82: =+G69/3 -> 35 | H82: =+H69/3 -> 35 | I82: =+I69/3 -> 35 | J82: =+J69/3 -> 35 | ... N82: =+N69/3 -> 35
B83: Breakfast Included | C83: =+C70/3 -> 18 | D83: =+D70/3 -> 18 | E83: =+E70/3 -> 18 | F83: =+F70/3 -> 18 | G83: =+G70/3 -> 18 | H83: =+H70/3 -> 18 | I83: =+I70/3 -> 18 | J83: =+J70/3 -> 18 | ... N83: =+N70/3 -> 18
B84: Lunch Included | C84: =+C71/3 -> 36 | D84: =+D71/3 -> 36 | E84: =+E71/3 -> 36 | F84: =+F71/3 -> 36 | G84: =+G71/3 -> 36 | H84: =+H71/3 -> 36 | I84: =+I71/3 -> 36 | J84: =+J71/3 -> 36 | ... N84: =+N71/3 -> 36
B85: Dinner Included | C85: =+C72/3 -> 54 | D85: =+D72/3 -> 54 | E85: =+E72/3 -> 54 | F85: =+F72/3 -> 54 | G85: =+G72/3 -> 54 | H85: =+H72/3 -> 54 | I85: =+I72/3 -> 54 | J85: =+J72/3 -> 54 | ... N85: =+N72/3 -> 54
B86: Snorkeling Tour | C86: =+C73/3 -> 48 | D86: =+D73/3 -> 48 | E86: =+E73/3 -> 48 | F86: =+F73/3 -> 48 | G86: =+G73/3 -> 48 | H86: =+H73/3 -> 48 | I86: =+I73/3 -> 48 | J86: =+J73/3 -> 48 | ... N86: =+N73/3 -> 48
B87: PN Walk San Pedrillo | C87: =+C74/3 -> 53 | D87: =+D74/3 -> 53 | E87: =+E74/3 -> 53 | F87: =+F74/3 -> 53 | G87: =+G74/3 -> 53 | H87: =+H74/3 -> 53 | I87: =+I74/3 -> 53 | J87: =+J74/3 -> 53 | ... N87: =+N74/3 -> 53
B89: Total | C89: =SUM(C82:C88) -> 244 | D89: =SUM(D82:D88) -> 244 | E89: =SUM(E82:E88) -> 244 | F89: =SUM(F82:F88) -> 244 | G89: =SUM(G82:G88) -> 244 | H89: =SUM(H82:H88) -> 244 | I89: =SUM(I82:I88) -> 244 | J89: =SUM(J82:J88) -> 244 | ... N89: =SUM(N82:N88) -> 244
B92: Occupancy per Room PROPOSE TO PROFORMA
B93: We will need to go back up to 90 employees. I would model it after how we looked in the highest month this year on expenses, but for every month. I will put us out 85% occupancy January February March. April July August at 50 percent. November 60%. December 65 percent. And reduce June September and October to bring the total occupancy to 55% for the year. | R93: This is not what we will do in 2026. This maybe 2028 or whatever. At some point we will be at 60%
B95: Occupancy | C95: =+C104 -> 0.75 | D95: =+D104 -> 0.76 | E95: =+E104 -> 0.65344086 | F95: =+F104 -> 0.36888889 | G95: =+G104 -> 0.24998517 | H95: =+H104 -> 0.18628352 | I95: =+I104 -> 0.35709677 | J95: =+J104 -> 0.27023656 | ... N95: =+N104 -> 0.65775 | Q95: Rooms | V95: revenue | AA95: RATE
B96: Room Type | C96: January | D96: February | E96: March | F96: April | G96: May | H96: June | I96: July | J96: August | K96: September | L96: October | M96: November | N96: December | O96: TOTAL | Q96: High Season | R96: shoulder Season | S96: Low Season | T96: Total RN | V96: High Season | W96: shoulder Season | X96: Low Season | Y96: Total Rev | AA96: High Season | AB96: shoulder Season | AC96: Low Season | AD96: ADR
B97: Corcovado Deluxe Villas, King bed | C97: 167.4 | D97: 139.6 | E97: 124.5 | F97: 93 | G97: 47.9 | H97: 27 | I97: 46.5 | J97: 37.2 | K97: 11.52 | L97: 0 | M97: 72 | N97: 120.9 | O97: =SUM(C97:N97) -> 887.52 | P97: We can run the pro forma at 55% | Q97: =+C97+D97+E97+F97+N97 -> 645.4 | R97: =+G97+H97+I97+J97+M97 -> 230.6 | S97: =+L97+K97 -> 11.52 | T97: =SUM(Q97:S97) -> 887.52 | V97: =+C153+D153+E153+F153+N153 -> 401789.54 | W97: =+G153+H153+I153+J153+M153 -> 116153 | X97: =+K153+L153 -> 5393.2032 | Y97: =SUM(V97:X97) -> 523335.75 | AA97: =+V97/Q97 -> 622.54345 | AB97: =+W97/R97 -> 503.69906 | AC97: =+X97/S97 -> 468.16 | AD97: =+Y97/T97 -> 589.6608
B98: Carate Deluxe Villa Double Beds | C98: 55.8 | D98: 68.2 | E98: 55.8 | F98: 21 | G98: 19.017241 | H98: 9.8275862 | I98: 21.7 | J98: 22.32 | K98: 9.6 | L98: 0 | M98: 43.47 | N98: 52.7 | O98: =SUM(C98:N98) -> 379.43483 | Q98: =+C98+D98+E98+F98+N98 -> 253.5 | R98: =+G98+H98+I98+J98+M98 -> 116.33483 | S98: =+L98+K98 -> 9.6 | T98: =SUM(Q98:S98) -> 379.43483 | V98: =+C154+D154+E154+F154+N154 -> 146001.97 | W98: =+G154+H154+I154+J154+M154 -> 53859.365 | X98: =+K154+L154 -> 4133.184 | Y98: =SUM(V98:X98) -> 203994.51 | AA98: =+V98/Q98 -> 575.94464 | AB98: =+W98/R98 -> 462.96854 | AC98: =+X98/S98 -> 430.54 | AD98: =+Y98/T98 -> 537.62728
B99: Agujas Villa 2 Queen Beds | C99: 111.6 | D99: 99.4 | E99: 96.6 | F99: 36 | G99: 31 | H99: 22 | I99: 55.4 | J99: 40.72 | K99: 14.4 | L99: 0 | M99: 49.68 | N99: 89.16 | O99: =SUM(C99:N99) -> 645.96 | P99: This is just a show what we will look like when we’re stabilized. This is not the 2026 budget. | Q99: =+C99+D99+E99+F99+N99 -> 432.76 | R99: =+G99+H99+I99+J99+M99 -> 198.8 | S99: =+L99+K99 -> 14.4 | T99: =SUM(Q99:S99) -> 645.96 | V99: =+C155+D155+E155+F155+N155 -> 201170.69 | W99: =+G155+H155+I155+J155+M155 -> 72711.602 | X99: =+K155+L155 -> 4875.552 | Y99: =SUM(V99:X99) -> 278757.85 | AA99: =+V99/Q99 -> 464.8551 | AB99: =+W99/R99 -> 365.75252 | AC99: =+X99/S99 -> 338.58 | AD99: =+Y99/T99 -> 431.54041
B100: Sirena Suites, Queen Bed (conecting) | C100: 188.4 | D100: 184.2 | E100: 178.4 | F100: 56 | G100: 64.482759 | H100: 40.034483 | I100: 62 | J100: 69.44 | K100: 19.2 | L100: 0 | M100: 67.8 | N100: 133.68 | O100: =SUM(C100:N100) -> 1063.6372 | Q100: =+C100+D100+E100+F100+N100 -> 740.68 | R100: =+G100+H100+I100+J100+M100 -> 303.75724 | S100: =+L100+K100 -> 19.2 | T100: =SUM(Q100:S100) -> 1063.6372 | V100: =+C156+D156+E156+F156+N156 -> 308501.56 | W100: =+G156+H156+I156+J156+M156 -> 99173.1 | X100: =+K156+L156 -> 5778.432 | Y100: =SUM(V100:X100) -> 413453.09 | AA100: =+V100/Q100 -> 416.51125 | AB100: =+W100/R100 -> 326.48802 | AD100: =+Y100/T100 -> 388.71626
B101: Treehouse king bed | C101: 93 | D101: 91 | E101: 78 | F101: 62.5 | G101: 30.043103 | H101: 39.396552 | I101: 82.25 | J101: 43.2 | K101: 14.4 | L101: 0 | M101: 105.225 | N101: 100.75 | O101: =SUM(C101:N101) -> 739.76466 | P101: We will need to go back up to 90 employees. I would model it after how we looked in the highest month this year on expenses, but for every month. I will put us out 85% occupancy January February March. April July August at 50 percent. November 60%. December 65 percent. And reduce June September and October to bring the total occupancy to 55% for the year. | Q101: =+C101+D101+E101+F101+N101 -> 425.25 | R101: =+G101+H101+I101+J101+M101 -> 300.11466 | S101: =+L101+K101 -> 14.4 | T101: =SUM(Q101:S101) -> 739.76466 | V101: =+C157+D157+E157+F157+N157 -> 369861.03 | W101: =+G157+H157+I157+J157+M157 -> 216894.83 | X101: =+K157+L157 -> 9751.104 | Y101: =SUM(V101:X101) -> 596506.96 | AA101: =+V101/Q101 -> 869.74963 | AB101: =+W101/R101 -> 722.70655 | AD101: =+Y101/T101 -> 806.34693
B102: 5 Elements Treehouse king bed | C102: 81.3 | D102: 56 | E102: 74.4 | F102: 63.5 | G102: 40.043103 | H102: 29.396552 | I102: 64.25 | J102: 38.44 | K102: 13.2 | L102: 0 | M102: 71.925 | N102: 114.5175 | O102: =SUM(C102:N102) -> 646.97216 | Q102: =+C102+D102+E102+F102+N102 -> 389.7175 | R102: =+G102+H102+I102+J102+M102 -> 244.05466 | S102: =+L102+K102 -> 13.2 | T102: =SUM(Q102:S102) -> 646.97216 | V102: =+C158+D158+E158+F158+N158 -> 379259.71 | W102: =+G158+H158+I158+J158+M158 -> 199047.16 | X102: =+K158+L158 -> 10042.032 | Y102: =SUM(V102:X102) -> 588348.9 | AA102: =+V102/Q102 -> 973.16571 | AB102: =+W102/R102 -> 815.58435 | AD102: =+Y102/T102 -> 909.38828
B103: TOTAL | C103: =SUM(C97:C102) -> 697.5 | D103: =SUM(D97:D102) -> 638.4 | E103: =SUM(E97:E102) -> 607.7 | F103: =SUM(F97:F102) -> 332 | G103: =SUM(G97:G102) -> 232.48621 | H103: =SUM(H97:H102) -> 167.65517 | I103: =SUM(I97:I102) -> 332.1 | J103: =SUM(J97:J102) -> 251.32 | ... N103: =SUM(N97:N102) -> 611.7075 | O103: =SUM(C103:N103) -> 4363.2889 | Q103: =SUM(Q97:Q102) -> 2887.3075 | R103: =SUM(R97:R102) -> 1393.6614 | S103: =SUM(S97:S102) -> 82.32 | T103: =SUM(T97:T102) -> 4363.2889 | V103: =+C159+D159+E159+F159+N159 -> 1806584.5 | W103: =+G159+H159+I159+J159+M159 -> 757839.06 | X103: =+K159+L159 -> 39973.507 | Y103: =SUM(Y97:Y102) -> 2604397.1 | AA103: =+V103/Q103 -> 625.69868 | AB103: =+W103/R103 -> 543.7756 | AC103: =+X103/S103 -> 485.58682 | AD103: =+Y103/T103 -> 596.88852
C104: =+C103/C32 -> 0.75 | D104: =+D103/D32 -> 0.76 | E104: =+E103/E32 -> 0.65344086 | F104: =+F103/F32 -> 0.36888889 | G104: =+G103/G32 -> 0.24998517 | H104: =+H103/H32 -> 0.18628352 | I104: =+I103/I32 -> 0.35709677 | J104: =+J103/J32 -> 0.27023656 | K104: =+K103/K32 -> 0.091466667 | M104: =+M103/M32 -> 0.45566667 | N104: =+N103/N32 -> 0.65775 | O104: =+O103/O32 -> 0.43545797 | AA104: =(AA103-AD103)/AD103 -> 0.048267232 | AB104: =(AB103-AD103)/AD103 -> -0.088982982 | AC104: =(AC103-AD103)/AD103 -> -0.18646983
B107: TOTAL REVENUE ACCORDING TO PROFORMA
B110: Occupancy | C110: =+C95 -> 0.75 | D110: =+D95 -> 0.76 | E110: =+E95 -> 0.65344086 | F110: =+F95 -> 0.36888889 | G110: =+G95 -> 0.24998517 | H110: =+H95 -> 0.18628352 | I110: =+I95 -> 0.35709677 | J110: =+J95 -> 0.27023656 | ... N110: =+N95 -> 0.65775
B111: Room Type | C111: January | D111: February | E111: March | F111: April | G111: May | H111: June | I111: July | J111: August | K111: September | L111: October | M111: November | N111: December | O111: TOTAL
B112: Corcovado Deluxe Villas, King bed | C112: =+C97*C38 -> 121365 | D112: =+D97*D38 -> 101210 | E112: =+E97*E38 -> 90262.5 | F112: =+F97*F38 -> 67425 | G112: =+G97*G38 -> 29458.5 | H112: =+H97*H38 -> 16605 | I112: =+I97*I38 -> 28597.5 | J112: =+J97*J38 -> 22878 | ... N112: =+N97*N38 -> 100347 | O112: =SUM(C112:N112) -> 625999.7
B113: Carate Deluxe Villa Double Beds | C113: =+C98*C39 -> 37386 | D113: =+D98*D39 -> 45694 | E113: =+E98*E39 -> 37386 | F113: =+F98*F39 -> 13335 | G113: =+G98*G39 -> 10744.741 | H113: =+H98*H39 -> 5552.5862 | I113: =+I98*I39 -> 12260.5 | J113: =+J98*J39 -> 12610.8 | ... N113: =+N98*N39 -> 40842.5 | O113: =SUM(C113:N113) -> 244012.58
B114: Agujas Villa 2 Queen Beds | C114: =+C99*C40 -> 60264 | D114: =+D99*D40 -> 53676 | E114: =+E99*E40 -> 52164 | F114: =+F99*F40 -> 18360 | G114: =+G99*G40 -> 13795 | H114: =+H99*H40 -> 9790 | I114: =+I99*I40 -> 24653 | J114: =+J99*J40 -> 18120.4 | ... N114: =+N99*N40 -> 56170.8 | O114: =SUM(C114:N114) -> 333442.4
B115: Sirena Suites, Queen Bed (conecting) | C115: =+C100*C41 -> 91374 | D115: =+D100*D41 -> 89337 | E115: =+E100*E41 -> 86524 | F115: =+F100*F41 -> 24920 | G115: =+G100*G41 -> 25470.69 | H115: =+H100*H41 -> 15813.621 | I115: =+I100*I41 -> 24490 | J115: =+J100*J41 -> 27428.8 | ... N115: =+N100*N41 -> 76866 | O115: =SUM(C115:N115) -> 494561.11
B116: Treehouse king bed | C116: =+C101*C42 -> 94395 | D116: =+D101*D42 -> 92365 | E116: =+E101*E42 -> 79170 | F116: =+F101*F42 -> 60625 | G116: =+G101*G42 -> 26287.716 | H116: =+H101*H42 -> 34471.983 | I116: =+I101*I42 -> 71968.75 | J116: =+J101*J42 -> 37800 | ... N116: =+N101*N42 -> 115862.5 | O116: =SUM(C116:N116) -> 713525.07
B117: 5 Elements Treehouse king bed | C117: =+C102*C43 -> 91869 | D117: =+D102*D43 -> 63280 | E117: =+E102*E43 -> 84072 | F117: =+F102*F43 -> 67627.5 | G117: =+G102*G43 -> 39242.241 | H117: =+H102*H43 -> 28808.621 | I117: =+I102*I43 -> 62965 | J117: =+J102*J43 -> 37671.2 | ... N117: =+N102*N43 -> 146811.43 | O117: =SUM(C117:N117) -> 703766.62
B119: TOTAL | C119: =SUM(C112:C118) -> 496653 | D119: =SUM(D112:D118) -> 445562 | E119: =SUM(E112:E118) -> 429578.5 | F119: =SUM(F112:F118) -> 252292.5 | G119: =SUM(G112:G118) -> 144998.89 | H119: =SUM(H112:H118) -> 111041.81 | I119: =SUM(I112:I118) -> 224934.75 | J119: =SUM(J112:J118) -> 156509.2 | ... N119: =SUM(N112:N118) -> 536900.23 | O119: =SUM(C119:N119) -> 3115307.5
B123: comision pagada para tarifa neta
D124: % VENTAS | E124: % COM
B125: Travel Agency | D125: 0.55 | E125: =+C61 -> 0.28
B126: OTAS | D126: =+C51 -> 0.05 | E126: =+C62 -> 0.2
B127: DIRECT | D127: 0.4 | E127: =+C63 -> 0
D129: =SUM(D125:D128) -> 1
B131: SUMPRODUCT | D131: {=SUMPRODUCT(D125:D127,1-(E125:E127))} -> 0.836
B133: COMMISION PAID TO CHANNELS ACCORDING TO COMMISSIONS AND % OF SALE
B136: Occupancy | C136: =+C110 -> 0.75 | D136: =+D110 -> 0.76 | E136: =+E110 -> 0.65344086 | F136: =+F110 -> 0.36888889 | G136: =+G110 -> 0.24998517 | H136: =+H110 -> 0.18628352 | I136: =+I110 -> 0.35709677 | J136: =+J110 -> 0.27023656 | ... N136: =+N110 -> 0.65775 | O136: =+O104 -> 0.43545797
B137: Room Type | C137: January | D137: February | E137: March | F137: April | G137: May | H137: June | I137: July | J137: August | K137: September | L137: October | M137: November | N137: December | O137: TOTAL
B138: Corcovado Deluxe Villas, King bed | C138: =(1-$D$131)*C112 -> 19903.86 | D138: =(1-$D$131)*D112 -> 16598.44 | E138: =(1-$D$131)*E112 -> 14803.05 | F138: =(1-$D$131)*F112 -> 11057.7 | G138: =(1-$D$131)*G112 -> 4831.194 | H138: =(1-$D$131)*H112 -> 2723.22 | I138: =(1-$D$131)*I112 -> 4689.99 | J138: =(1-$D$131)*J112 -> 3751.992 | ... N138: =(1-$D$131)*N112 -> 16456.908 | O138: =SUM(C138:N138) -> 102663.95
B139: Carate Deluxe Villa Double Beds | C139: =(1-$D$131)*C113 -> 6131.304 | D139: =(1-$D$131)*D113 -> 7493.816 | E139: =(1-$D$131)*E113 -> 6131.304 | F139: =(1-$D$131)*F113 -> 2186.94 | G139: =(1-$D$131)*G113 -> 1762.1376 | H139: =(1-$D$131)*H113 -> 910.62414 | I139: =(1-$D$131)*I113 -> 2010.722 | J139: =(1-$D$131)*J113 -> 2068.1712 | ... N139: =(1-$D$131)*N113 -> 6698.17 | O139: =SUM(C139:N139) -> 40018.063
B140: Agujas Villa 2 Queen Beds | C140: =(1-$D$131)*C114 -> 9883.296 | D140: =(1-$D$131)*D114 -> 8802.864 | E140: =(1-$D$131)*E114 -> 8554.896 | F140: =(1-$D$131)*F114 -> 3011.04 | G140: =(1-$D$131)*G114 -> 2262.38 | H140: =(1-$D$131)*H114 -> 1605.56 | I140: =(1-$D$131)*I114 -> 4043.092 | J140: =(1-$D$131)*J114 -> 2971.7456 | ... N140: =(1-$D$131)*N114 -> 9212.0112 | O140: =SUM(C140:N140) -> 54684.554
B141: Sirena Suites, Queen Bed (conecting) | C141: =(1-$D$131)*C115 -> 14985.336 | D141: =(1-$D$131)*D115 -> 14651.268 | E141: =(1-$D$131)*E115 -> 14189.936 | F141: =(1-$D$131)*F115 -> 4086.88 | G141: =(1-$D$131)*G115 -> 4177.1931 | H141: =(1-$D$131)*H115 -> 2593.4338 | I141: =(1-$D$131)*I115 -> 4016.36 | J141: =(1-$D$131)*J115 -> 4498.3232 | ... N141: =(1-$D$131)*N115 -> 12606.024 | O141: =SUM(C141:N141) -> 81108.022
B142: Treehouse king bed | C142: =(1-$D$131)*C116 -> 15480.78 | D142: =(1-$D$131)*D116 -> 15147.86 | E142: =(1-$D$131)*E116 -> 12983.88 | F142: =(1-$D$131)*F116 -> 9942.5 | G142: =(1-$D$131)*G116 -> 4311.1853 | H142: =(1-$D$131)*H116 -> 5653.4052 | I142: =(1-$D$131)*I116 -> 11802.875 | J142: =(1-$D$131)*J116 -> 6199.2 | ... N142: =(1-$D$131)*N116 -> 19001.45 | O142: =SUM(C142:N142) -> 117018.11
B143: 5 Elements Treehouse king bed | C143: =(1-$D$131)*C117 -> 15066.516 | D143: =(1-$D$131)*D117 -> 10377.92 | E143: =(1-$D$131)*E117 -> 13787.808 | F143: =(1-$D$131)*F117 -> 11090.91 | G143: =(1-$D$131)*G117 -> 6435.7276 | H143: =(1-$D$131)*H117 -> 4724.6138 | I143: =(1-$D$131)*I117 -> 10326.26 | J143: =(1-$D$131)*J117 -> 6178.0768 | ... N143: =(1-$D$131)*N117 -> 24077.075 | O143: =SUM(C143:N143) -> 115417.73 | Q143: Paso 1 – Definir variables
...

Sheet Key LIGIA (2)
C4: 46023 | D4: 46024 | E4: 46025 | F4: 46026 | G4: 46027 | H4: 46028 | I4: 46029 | J4: 46030 | K4: 46031 | L4: 46032 | M4: 46033 | N4: 46034
B6: Units Available | C6: 30 | D6: 30 | E6: 30 | F6: 30 | G6: 30 | H6: 30 | I6: 30 | J6: 30 | K6: 30 | L6: 30 | M6: 30 | N6: 30
B7: Day per month | C7: 31 | D7: 28 | E7: 31 | F7: 30 | G7: 31 | H7: 30 | I7: 31 | J7: 31 | K7: 30 | L7: 11 | M7: 30 | N7: 31
B9: Total Nights Available | C9: =+C6*C7 -> 930 | D9: =+D6*D7 -> 840 | E9: =+E6*E7 -> 930 | F9: =+F6*F7 -> 900 | G9: =+G6*G7 -> 930 | H9: =+H6*H7 -> 900 | I9: =+I6*I7 -> 930 | J9: =+J6*J7 -> 930 | ... N9: =+N6*N7 -> 930
B12: Units Category
A14: 1 | B14: Corcovado Deluxe Villas, King bed | C14: 6 | D14: 6 | E14: 6 | F14: 6 | G14: 6 | H14: 6 | I14: 6 | J14: 6 | K14: 6 | L14: 6 | M14: 6 | N14: 6
A15: 2 | B15: Carate Deluxe Villa Double Beds | C15: 2 | D15: 2 | E15: 2 | F15: 2 | G15: 2 | H15: 2 | I15: 2 | J15: 2 | K15: 2 | L15: 2 | M15: 2 | N15: 2
A16: 3 | B16: Agujas Villa 2 Queen Beds | C16: 3 | D16: 3 | E16: 3 | F16: 3 | G16: 3 | H16: 3 | I16: 3 | J16: 3 | K16: 3 | L16: 3 | M16: 3 | N16: 3
A17: 4 | B17: Sirena Suites, Queen Bed (conecting) | C17: 8 | D17: 8 | E17: 8 | F17: 8 | G17: 8 | H17: 8 | I17: 8 | J17: 8 | K17: 8 | L17: 8 | M17: 8 | N17: 8
A18: 5 | B18: Treehouse king bed | C18: 5 | D18: 5 | E18: 5 | F18: 5 | G18: 5 | H18: 5 | I18: 5 | J18: 5 | K18: 5 | L18: 5 | M18: 5 | N18: 5
A19: 6 | B19: 5 Elements Treehouse king bed | C19: 6 | D19: 6 | E19: 6 | F19: 6 | G19: 6 | H19: 6 | I19: 6 | J19: 6 | K19: 6 | L19: 6 | M19: 6 | N19: 6
B20: Total | C20: =SUM(C14:C19) -> 30 | D20: =SUM(D14:D19) -> 30 | E20: =SUM(E14:E19) -> 30 | F20: =SUM(F14:F19) -> 30 | G20: =SUM(G14:G19) -> 30 | H20: =SUM(H14:H19) -> 30 | I20: =SUM(I14:I19) -> 30 | J20: =SUM(J14:J19) -> 30 | ... N20: =SUM(N14:N19) -> 30
B23: Total Room Nights Available per Category
A25: 1 | B25: Corcovado Deluxe Villas, King bed | C25: =+C14*C$7 -> 186 | D25: =+D14*D$7 -> 168 | E25: =+E14*E$7 -> 186 | F25: =+F14*F$7 -> 180 | G25: =+G14*G$7 -> 186 | H25: =+H14*H$7 -> 180 | I25: =+I14*I$7 -> 186 | J25: =+J14*J$7 -> 186 | K25: =+K14*K$7 -> 180 | M25: =+M14*M$7 -> 180 | N25: =+N14*N$7 -> 186 | O25: =SUM(C25:N25) -> 2004
A26: 2 | B26: Carate Deluxe Villa Double Beds | C26: =+C15*C$7 -> 62 | D26: =+D15*D$7 -> 56 | E26: =+E15*E$7 -> 62 | F26: =+F15*F$7 -> 60 | G26: =+G15*G$7 -> 62 | H26: =+H15*H$7 -> 60 | I26: =+I15*I$7 -> 62 | J26: =+J15*J$7 -> 62 | K26: =+K15*K$7 -> 60 | M26: =+M15*M$7 -> 60 | N26: =+N15*N$7 -> 62 | O26: =SUM(C26:N26) -> 668
A27: 3 | B27: Agujas Villa 2 Queen Beds | C27: =+C16*C$7 -> 93 | D27: =+D16*D$7 -> 84 | E27: =+E16*E$7 -> 93 | F27: =+F16*F$7 -> 90 | G27: =+G16*G$7 -> 93 | H27: =+H16*H$7 -> 90 | I27: =+I16*I$7 -> 93 | J27: =+J16*J$7 -> 93 | K27: =+K16*K$7 -> 90 | M27: =+M16*M$7 -> 90 | N27: =+N16*N$7 -> 93 | O27: =SUM(C27:N27) -> 1002
A28: 4 | B28: Sirena Suites, Queen Bed (conecting) | C28: =+C17*C$7 -> 248 | D28: =+D17*D$7 -> 224 | E28: =+E17*E$7 -> 248 | F28: =+F17*F$7 -> 240 | G28: =+G17*G$7 -> 248 | H28: =+H17*H$7 -> 240 | I28: =+I17*I$7 -> 248 | J28: =+J17*J$7 -> 248 | K28: =+K17*K$7 -> 240 | M28: =+M17*M$7 -> 240 | N28: =+N17*N$7 -> 248 | O28: =SUM(C28:N28) -> 2672
A29: 5 | B29: Treehouse king bed | C29: =+C18*C$7 -> 155 | D29: =+D18*D$7 -> 140 | E29: =+E18*E$7 -> 155 | F29: =+F18*F$7 -> 150 | G29: =+G18*G$7 -> 155 | H29: =+H18*H$7 -> 150 | I29: =+I18*I$7 -> 155 | J29: =+J18*J$7 -> 155 | K29: =+K18*K$7 -> 150 | M29: =+M18*M$7 -> 150 | N29: =+N18*N$7 -> 155 | O29: =SUM(C29:N29) -> 1670
A30: 6 | B30: 5 Elements Treehouse king bed | C30: =+C19*C$7 -> 186 | D30: =+D19*D$7 -> 168 | E30: =+E19*E$7 -> 186 | F30: =+F19*F$7 -> 180 | G30: =+G19*G$7 -> 186 | H30: =+H19*H$7 -> 180 | I30: =+I19*I$7 -> 186 | J30: =+J19*J$7 -> 186 | K30: =+K19*K$7 -> 180 | M30: =+M19*M$7 -> 180 | N30: =+N19*N$7 -> 186 | O30: =SUM(C30:N30) -> 2004
B32: Total | C32: =SUM(C25:C31) -> 930 | D32: =SUM(D25:D31) -> 840 | E32: =SUM(E25:E31) -> 930 | F32: =SUM(F25:F31) -> 900 | G32: =SUM(G25:G31) -> 930 | H32: =SUM(H25:H31) -> 900 | I32: =SUM(I25:I31) -> 930 | J32: =SUM(J25:J31) -> 930 | ... O32: =SUM(O25:O31) -> 10020
B35: Rack Rates Rooms only | G35: LIGIA PUT IN THE 2026 RATES
B37: Room Type | C37: January | D37: February | E37: March | F37: April | G37: May | H37: June | I37: July | J37: August | K37: September | L37: October | M37: November | N37: December
A38: 1 | B38: Corcovado Deluxe Villas, King bed | C38: 725 | D38: 725 | E38: 725 | F38: 725 | G38: 615 | H38: 615 | I38: 615 | J38: 615 | K38: 560 | L38: 560 | M38: 575 | N38: 830
A39: 2 | B39: Carate Deluxe Villa Double Beds | C39: 670 | D39: 670 | E39: 670 | F39: 635 | G39: 565 | H39: 565 | I39: 565 | J39: 565 | K39: 515 | L39: 515 | M39: 535 | N39: 775
A40: 3 | B40: Agujas Villa 2 Queen Beds | C40: 540 | D40: 540 | E40: 540 | F40: 510 | G40: 445 | H40: 445 | I40: 445 | J40: 445 | K40: 405 | L40: 405 | M40: 415 | N40: 630
A41: 4 | B41: Sirena Suites, Queen Bed (conecting) | C41: 485 | D41: 485 | E41: 485 | F41: 445 | G41: 395 | H41: 395 | I41: 395 | J41: 395 | K41: 360 | L41: 360 | M41: 375 | N41: 575
A42: 5 | B42: Treehouse king bed | C42: 1015 | D42: 1015 | E42: 1015 | F42: 970 | G42: 875 | H42: 875 | I42: 875 | J42: 875 | K42: 810 | L42: 810 | M42: 845 | N42: 1150
A43: 6 | B43: 5 Elements Treehouse king bed | C43: 1130 | D43: 1130 | E43: 1130 | F43: 1065 | G43: 980 | H43: 980 | I43: 980 | J43: 980 | K43: 910 | L43: 910 | M43: 965 | N43: 1282
B48: % of Sale by Channel
C49: =+C37 -> January | D49: =+D37 -> February | E49: =+E37 -> March | F49: =+F37 -> April | G49: =+G37 -> May | H49: =+H37 -> June | I49: =+I37 -> July | J49: =+J37 -> August | ... M49: =+M37 -> November | N49: December
B50: Travel Agency | C50: 0.6 | D50: 0.6 | E50: 0.6 | F50: 0.55 | G50: 0.55 | H50: 0.55 | I50: 0.55 | J50: 0.55 | K50: 0.55 | L50: 0.55 | M50: 0.55 | N50: 0.55
B51: OTAS | C51: 0.05 | D51: 0.05 | E51: 0.05 | F51: 0.05 | G51: 0.05 | H51: 0.05 | I51: 0.05 | J51: 0.05 | K51: 0.05 | L51: 0.05 | M51: 0.05 | N51: 0.05
B52: DIRECT | C52: 0.35 | D52: 0.35 | E52: 0.35 | F52: 0.4 | G52: 0.4 | H52: 0.4 | I52: 0.4 | J52: 0.4 | K52: 0.4 | L52: 0.4 | M52: 0.4 | N52: 0.4
B53: NEW CHANNELS
B54: NEW CHANNELS
B56: Total | C56: =SUM(C50:C55) -> 1 | D56: =SUM(D50:D55) -> 1 | E56: =SUM(E50:E55) -> 1 | F56: =SUM(F50:F55) -> 1 | G56: =SUM(G50:G55) -> 1 | H56: =SUM(H50:H55) -> 1 | I56: =SUM(I50:I55) -> 1 | J56: =SUM(J50:J55) -> 1 | ... N56: =SUM(N50:N55) -> 1
B60: COMMISSIONS By channel
C61: =+C37 -> January
B62: Travel Agency | C62: 0.28
B63: OTAS | C63: 0.2
B64: DIRECT | C64: 0
B65: NEW CHANNELS | C65: 0
B66: NEW CHANNELS | C66: 0
C72: % occupancy INPUT LIGIA
B75: Room Type | C75: January | D75: February | E75: March | F75: April | G75: May | H75: June | I75: July | J75: August | K75: September | L75: October | M75: November | N75: December
B76: Corcovado Deluxe Villas, King bed | C76: 0.42 | D76: 0.57 | E76: 0.58 | F76: 0.32 | G76: 0.35 | H76: 0.25 | I76: 0.25 | J76: 0.25 | K76: 0.08 | L76: 0 | M76: 0.27 | N76: 0.45
B77: Carate Deluxe Villa Double Beds | C77: 0.67 | D77: 0.85 | E77: 0.9 | F77: 0.62 | G77: 0.52 | H77: 0.28 | I77: 0.87 | J77: 0.62 | K77: 0.28 | L77: 0 | M77: 0.63 | N77: 0.78
B78: Agujas Villa 2 Queen Beds | C78: 0.87 | D78: 0.92 | E78: 0.96 | F78: 0.83 | G78: 0.56 | H78: 0.54 | I78: 0.76 | J78: 0.35 | K78: 0.28 | L78: 0 | M78: 0.36 | N78: 0.89
B79: Sirena Suites, Queen Bed (conecting) | C79: 0.45 | D79: 0.55 | E79: 0.56 | F79: 0.28 | G79: 0.18 | H79: 0.15 | I79: 0.24 | J79: 0.48 | K79: 0.1 | L79: 0 | M79: 0.3 | N79: 0.46
B80: Treehouse king bed | C80: 0.9 | D80: 0.92 | E80: 0.9 | F80: 0.52 | G80: 0.36 | H80: 0.35 | I80: 0.48 | J80: 0.6 | K80: 0.12 | L80: 0 | M80: 0.61 | N80: 0.93
B81: 5 Elements Treehouse king bed | C81: 0.46 | D81: 0.45 | E81: 0.48 | F81: 0.37 | G81: 0.27 | H81: 0.21 | I81: 0.32 | J81: 0.31 | K81: 0.11 | L81: 0 | M81: 0.33 | N81: 0.39
B82: TOTAL
B87: Occupancy per Room PROPOSE TO PROFORMA
B88: We will need to go back up to 90 employees. I would model it after how we looked in the highest month this year on expenses, but for every month. I will put us out 85% occupancy January February March. April July August at 50 percent. November 60%. December 65 percent. And reduce June September and October to bring the total occupancy to 55% for the year. | R88: This is not what we will do in 2026. This maybe 2028 or whatever. At some point we will be at 60%
B90: Occupancy
B91: Room Type | C91: January | D91: February | E91: March | F91: April | G91: May | H91: June | I91: July | J91: August | K91: September | L91: October | M91: November | N91: December | O91: TOTAL
B92: Corcovado Deluxe Villas, King bed | C92: =+C76*C25 -> 78.12 | D92: =+D76*D25 -> 95.76 | E92: =+E76*E25 -> 107.88 | F92: =+F76*F25 -> 57.6 | G92: =+G76*G25 -> 65.1 | H92: =+H76*H25 -> 45 | I92: =+I76*I25 -> 46.5 | J92: =+J76*J25 -> 46.5 | K92: 19 | L92: =+L76*L25 -> 0 | M92: =+M76*M25 -> 48.6 | N92: =+N76*N25 -> 83.7 | O92: =SUM(C92:N92) -> 693.76 | R92: We can run the pro forma at 55%
B93: Carate Deluxe Villa Double Beds | C93: =+C77*C26 -> 41.54 | D93: =+D77*D26 -> 47.6 | E93: =+E77*E26 -> 55.8 | F93: =+F77*F26 -> 37.2 | G93: =+G77*G26 -> 32.24 | H93: =+H77*H26 -> 16.8 | I93: =+I77*I26 -> 53.94 | J93: =+J77*J26 -> 38.44 | K93: 22 | L93: =+L77*L26 -> 0 | M93: =+M77*M26 -> 37.8 | N93: =+N77*N26 -> 48.36 | O93: =SUM(C93:N93) -> 431.72
B94: Agujas Villa 2 Queen Beds | C94: =+C78*C27 -> 80.91 | D94: =+D78*D27 -> 77.28 | E94: =+E78*E27 -> 89.28 | F94: =+F78*F27 -> 74.7 | G94: =+G78*G27 -> 52.08 | H94: =+H78*H27 -> 48.6 | I94: =+I78*I27 -> 70.68 | J94: =+J78*J27 -> 32.55 | K94: 28 | L94: =+L78*L27 -> 0 | M94: =+M78*M27 -> 32.4 | N94: =+N78*N27 -> 82.77 | O94: =SUM(C94:N94) -> 669.25 | R94: This is just a show what we will look like when we’re stabilized. This is not the 2026 budget.
B95: Sirena Suites, Queen Bed (conecting) | C95: =+C79*C28 -> 111.6 | D95: =+D79*D28 -> 123.2 | E95: =+E79*E28 -> 138.88 | F95: =+F79*F28 -> 67.2 | G95: =+G79*G28 -> 44.64 | H95: =+H79*H28 -> 36 | I95: =+I79*I28 -> 59.52 | J95: 4 | K95: =+K79*K28 -> 24 | L95: =+L79*L28 -> 0 | M95: =+M79*M28 -> 72 | N95: =+N79*N28 -> 114.08 | O95: =SUM(C95:N95) -> 795.12
B96: Treehouse king bed | C96: =+C80*C29 -> 139.5 | D96: =+D80*D29 -> 128.8 | E96: =+E80*E29 -> 139.5 | F96: =+F80*F29 -> 78 | G96: =+G80*G29 -> 55.8 | H96: =+H80*H29 -> 52.5 | I96: =+I80*I29 -> 74.4 | J96: =+J80*J29 -> 93 | ... N96: =+N80*N29 -> 144.15 | O96: =SUM(C96:N96) -> 1015.15 | R96: We will need to go back up to 90 employees. I would model it after how we looked in the highest month this year on expenses, but for every month. I will put us out 85% occupancy January February March. April July August at 50 percent. November 60%. December 65 percent. And reduce June September and October to bring the total occupancy to 55% for the year.
B97: 5 Elements Treehouse king bed | C97: =+C81*C30 -> 85.56 | D97: =+D81*D30 -> 75.6 | E97: =+E81*E30 -> 89.28 | F97: =+F81*F30 -> 66.6 | G97: =+G81*G30 -> 50.22 | H97: =+H81*H30 -> 37.8 | I97: =+I81*I30 -> 59.52 | J97: =+J81*J30 -> 57.66 | ... N97: =+N81*N30 -> 72.54 | O97: =SUM(C97:N97) -> 673.98
B98: TOTAL | C98: =SUM(C92:C97) -> 537.23 | D98: =SUM(D92:D97) -> 548.24 | E98: =SUM(E92:E97) -> 620.62 | F98: =SUM(F92:F97) -> 381.3 | G98: =SUM(G92:G97) -> 300.08 | H98: =SUM(H92:H97) -> 236.7 | I98: =SUM(I92:I97) -> 364.56 | J98: =SUM(J92:J97) -> 272.15 | ... N98: =SUM(N92:N97) -> 545.6 | O98: =SUM(C98:N98) -> 4278.98
C99: =+C98/C32 -> 0.57766667 | D99: =+D98/D32 -> 0.65266667 | E99: =+E98/E32 -> 0.66733333 | F99: =+F98/F32 -> 0.42366667 | G99: =+G98/G32 -> 0.32266667 | H99: =+H98/H32 -> 0.263 | I99: =+I98/I32 -> 0.392 | J99: =+J98/J32 -> 0.29263441 | ... O99: =+O98/O32 -> 0.42704391
B102: TOTAL REVENUE ACCORDING TO PROFORMA
B105: Occupancy | C105: =+C90 -> 0 | D105: =+D90 -> 0 | E105: =+E90 -> 0 | F105: =+F90 -> 0 | G105: =+G90 -> 0 | H105: =+H90 -> 0 | I105: =+I90 -> 0 | J105: =+J90 -> 0 | ... N105: =+N90 -> 0
B106: Room Type | C106: January | D106: February | E106: March | F106: April | G106: May | H106: June | I106: July | J106: August | K106: September | L106: October | M106: November | N106: December | O106: TOTAL
B107: Corcovado Deluxe Villas, King bed | C107: =+C92*C38 -> 56637 | D107: =+D92*D38 -> 69426 | E107: =+E92*E38 -> 78213 | F107: =+F92*F38 -> 41760 | G107: =+G92*G38 -> 40036.5 | H107: =+H92*H38 -> 27675 | I107: =+I92*I38 -> 28597.5 | J107: =+J92*J38 -> 28597.5 | ... N107: =+N92*N38 -> 69471 | O107: =SUM(C107:N107) -> 478998.5
B108: Carate Deluxe Villa Double Beds | C108: =+C93*C39 -> 27831.8 | D108: =+D93*D39 -> 31892 | E108: =+E93*E39 -> 37386 | F108: =+F93*F39 -> 23622 | G108: =+G93*G39 -> 18215.6 | H108: =+H93*H39 -> 9492 | I108: =+I93*I39 -> 30476.1 | J108: =+J93*J39 -> 21718.6 | ... N108: =+N93*N39 -> 37479 | O108: =SUM(C108:N108) -> 269666.1
B109: Agujas Villa 2 Queen Beds | C109: =+C94*C40 -> 43691.4 | D109: =+D94*D40 -> 41731.2 | E109: =+E94*E40 -> 48211.2 | F109: =+F94*F40 -> 38097 | G109: =+G94*G40 -> 23175.6 | H109: =+H94*H40 -> 21627 | I109: =+I94*I40 -> 31452.6 | J109: =+J94*J40 -> 14484.75 | ... N109: =+N94*N40 -> 52145.1 | O109: =SUM(C109:N109) -> 339401.85
B110: Sirena Suites, Queen Bed (conecting) | C110: =+C95*C41 -> 54126 | D110: =+D95*D41 -> 59752 | E110: =+E95*E41 -> 67356.8 | F110: =+F95*F41 -> 29904 | G110: =+G95*G41 -> 17632.8 | H110: =+H95*H41 -> 14220 | I110: =+I95*I41 -> 23510.4 | J110: =+J95*J41 -> 1580 | ... N110: =+N95*N41 -> 65596 | O110: =SUM(C110:N110) -> 369318
B111: Treehouse king bed | C111: =+C96*C42 -> 141592.5 | D111: =+D96*D42 -> 130732 | E111: =+E96*E42 -> 141592.5 | F111: =+F96*F42 -> 75660 | G111: =+G96*G42 -> 48825 | H111: =+H96*H42 -> 45937.5 | I111: =+I96*I42 -> 65100 | J111: =+J96*J42 -> 81375 | ... N111: =+N96*N42 -> 165772.5 | O111: =SUM(C111:N111) -> 988484.5
B112: 5 Elements Treehouse king bed | C112: =+C97*C43 -> 96682.8 | D112: =+D97*D43 -> 85428 | E112: =+E97*E43 -> 100886.4 | F112: =+F97*F43 -> 70929 | G112: =+G97*G43 -> 49215.6 | H112: =+H97*H43 -> 37044 | I112: =+I97*I43 -> 58329.6 | J112: =+J97*J43 -> 56506.8 | ... N112: =+N97*N43 -> 92996.28 | O112: =SUM(C112:N112) -> 723357.48
B114: TOTAL | C114: =SUM(C107:C113) -> 420561.5 | D114: =SUM(D107:D113) -> 418961.2 | E114: =SUM(E107:E113) -> 473645.9 | F114: =SUM(F107:F113) -> 279972 | G114: =SUM(G107:G113) -> 197101.1 | H114: =SUM(H107:H113) -> 155995.5 | I114: =SUM(I107:I113) -> 237466.2 | J114: =SUM(J107:J113) -> 204262.65 | ... N114: =SUM(N107:N113) -> 483459.88 | O114: =SUM(C114:N114) -> 3169226.4
B118: comision pagada para tarifa neta
D119: % VENTAS | E119: % COM
B120: Travel Agency | D120: =+C50 -> 0.6 | E120: =+C62 -> 0.28
B121: OTAS | D121: =+C51 -> 0.05 | E121: =+C63 -> 0.2
B122: DIRECT | D122: =+C52 -> 0.35 | E122: =+C64 -> 0
B123: NEW CHANNELS | D123: 0 | E123: 0
B124: NEW CHANNELS | D124: 0 | E124: 0
B126: SUMPRODUCT | D126: {=SUMPRODUCT(D120:D124,1-(E120:E124))} -> 0.822
B128: COMMISION PAID TO CHANNELS ACCORDING TO COMMISSIONS AND % OF SALE
B131: Occupancy | C131: =+C105 -> 0 | D131: =+D105 -> 0 | E131: =+E105 -> 0 | F131: =+F105 -> 0 | G131: =+G105 -> 0 | H131: =+H105 -> 0 | I131: =+I105 -> 0 | J131: =+J105 -> 0 | ... N131: =+N105 -> 0 | O131: =+O99 -> 0.42704391
B132: Room Type | C132: January | D132: February | E132: March | F132: April | G132: May | H132: June | I132: July | J132: August | K132: September | L132: October | M132: November | N132: December | O132: TOTAL
B133: Corcovado Deluxe Villas, King bed | C133: =(1-$D$126)*C107 -> 10081.386 | D133: =(1-$D$126)*D107 -> 12357.828 | E133: =(1-$D$126)*E107 -> 13921.914 | F133: =(1-$D$126)*F107 -> 7433.28 | G133: =(1-$D$126)*G107 -> 7126.497 | H133: =(1-$D$126)*H107 -> 4926.15 | I133: =(1-$D$126)*I107 -> 5090.355 | J133: =(1-$D$126)*J107 -> 5090.355 | ... N133: =(1-$D$126)*N107 -> 12365.838 | O133: =SUM(C133:N133) -> 85261.733
B134: Carate Deluxe Villa Double Beds | C134: =(1-$D$126)*C108 -> 4954.0604 | D134: =(1-$D$126)*D108 -> 5676.776 | E134: =(1-$D$126)*E108 -> 6654.708 | F134: =(1-$D$126)*F108 -> 4204.716 | G134: =(1-$D$126)*G108 -> 3242.3768 | H134: =(1-$D$126)*H108 -> 1689.576 | I134: =(1-$D$126)*I108 -> 5424.7458 | J134: =(1-$D$126)*J108 -> 3865.9108 | ... N134: =(1-$D$126)*N108 -> 6671.262 | O134: =SUM(C134:N134) -> 48000.566
B135: Agujas Villa 2 Queen Beds | C135: =(1-$D$126)*C109 -> 7777.0692 | D135: =(1-$D$126)*D109 -> 7428.1536 | E135: =(1-$D$126)*E109 -> 8581.5936 | F135: =(1-$D$126)*F109 -> 6781.266 | G135: =(1-$D$126)*G109 -> 4125.2568 | H135: =(1-$D$126)*H109 -> 3849.606 | I135: =(1-$D$126)*I109 -> 5598.5628 | J135: =(1-$D$126)*J109 -> 2578.2855 | ... N135: =(1-$D$126)*N109 -> 9281.8278 | O135: =SUM(C135:N135) -> 60413.529
B136: Sirena Suites, Queen Bed (conecting) | C136: =(1-$D$126)*C110 -> 9634.428 | D136: =(1-$D$126)*D110 -> 10635.856 | E136: =(1-$D$126)*E110 -> 11989.51 | F136: =(1-$D$126)*F110 -> 5322.912 | G136: =(1-$D$126)*G110 -> 3138.6384 | H136: =(1-$D$126)*H110 -> 2531.16 | I136: =(1-$D$126)*I110 -> 4184.8512 | J136: =(1-$D$126)*J110 -> 281.24 | ... N136: =(1-$D$126)*N110 -> 11676.088 | O136: =SUM(C136:N136) -> 65738.604
B137: Treehouse king bed | C137: =(1-$D$126)*C111 -> 25203.465 | D137: =(1-$D$126)*D111 -> 23270.296 | E137: =(1-$D$126)*E111 -> 25203.465 | F137: =(1-$D$126)*F111 -> 13467.48 | G137: =(1-$D$126)*G111 -> 8690.85 | H137: =(1-$D$126)*H111 -> 8176.875 | I137: =(1-$D$126)*I111 -> 11587.8 | J137: =(1-$D$126)*J111 -> 14484.75 | ... N137: =(1-$D$126)*N111 -> 29507.505 | O137: =SUM(C137:N137) -> 175950.24
B138: 5 Elements Treehouse king bed | C138: =(1-$D$126)*C112 -> 17209.538 | D138: =(1-$D$126)*D112 -> 15206.184 | E138: =(1-$D$126)*E112 -> 17957.779 | F138: =(1-$D$126)*F112 -> 12625.362 | G138: =(1-$D$126)*G112 -> 8760.3768 | H138: =(1-$D$126)*H112 -> 6593.832 | I138: =(1-$D$126)*I112 -> 10382.669 | J138: =(1-$D$126)*J112 -> 10058.21 | ... N138: =(1-$D$126)*N112 -> 16553.338 | O138: =SUM(C138:N138) -> 128757.63
B140: TOTAL | C140: =SUM(C133:C139) -> 74859.947 | D140: =SUM(D133:D139) -> 74575.094 | E140: =SUM(E133:E139) -> 84308.97 | F140: =SUM(F133:F139) -> 49835.016 | G140: =SUM(G133:G139) -> 35083.996 | H140: =SUM(H133:H139) -> 27767.199 | I140: =SUM(I133:I139) -> 42268.984 | J140: =SUM(J133:J139) -> 36358.752 | ... N140: =SUM(N133:N139) -> 86055.859 | O140: =SUM(C140:N140) -> 564122.3
B143: Net rate after commissions
B146: Occupancy | C146: 0.85 | D146: 0.85 | E146: 0.85 | F146: 0.5 | G146: 0.5 | H146: 0.5 | I146: 0.5 | J146: 0.5 | K146: 0.5 | L146: 0.5 | M146: 0.6 | N146: 0.65
B147: Room Type | C147: January | D147: February | E147: March | F147: April | G147: May | H147: June | I147: July | J147: August | K147: September | L147: October | M147: November | N147: December | O147: TOTAL
B148: Corcovado Deluxe Villas, King bed | C148: =+C107-C133 -> 46555.614 | D148: =+D107-D133 -> 57068.172 | E148: =+E107-E133 -> 64291.086 | F148: =+F107-F133 -> 34326.72 | G148: =+G107-G133 -> 32910.003 | H148: =+H107-H133 -> 22748.85 | I148: =+I107-I133 -> 23507.145 | J148: =+J107-J133 -> 23507.145 | ... N148: =+N107-N133 -> 57105.162 | O148: =SUM(C148:N148) -> 393736.77
B149: Carate Deluxe Villa Double Beds | C149: =+C108-C134 -> 22877.74 | D149: =+D108-D134 -> 26215.224 | E149: =+E108-E134 -> 30731.292 | F149: =+F108-F134 -> 19417.284 | G149: =+G108-G134 -> 14973.223 | H149: =+H108-H134 -> 7802.424 | I149: =+I108-I134 -> 25051.354 | J149: =+J108-J134 -> 17852.689 | ... N149: =+N108-N134 -> 30807.738 | O149: =SUM(C149:N149) -> 221665.53
B150: Agujas Villa 2 Queen Beds | C150: =+C109-C135 -> 35914.331 | D150: =+D109-D135 -> 34303.046 | E150: =+E109-E135 -> 39629.606 | F150: =+F109-F135 -> 31315.734 | G150: =+G109-G135 -> 19050.343 | H150: =+H109-H135 -> 17777.394 | I150: =+I109-I135 -> 25854.037 | J150: =+J109-J135 -> 11906.464 | ... N150: =+N109-N135 -> 42863.272 | O150: =SUM(C150:N150) -> 278988.32
B151: Sirena Suites, Queen Bed (conecting) | C151: =+C110-C136 -> 44491.572 | D151: =+D110-D136 -> 49116.144 | E151: =+E110-E136 -> 55367.29 | F151: =+F110-F136 -> 24581.088 | G151: =+G110-G136 -> 14494.162 | H151: =+H110-H136 -> 11688.84 | I151: =+I110-I136 -> 19325.549 | J151: =+J110-J136 -> 1298.76 | ... N151: =+N110-N136 -> 53919.912 | O151: =SUM(C151:N151) -> 303579.4
B152: Treehouse king bed | C152: =+C111-C137 -> 116389.03 | D152: =+D111-D137 -> 107461.7 | E152: =+E111-E137 -> 116389.03 | F152: =+F111-F137 -> 62192.52 | G152: =+G111-G137 -> 40134.15 | H152: =+H111-H137 -> 37760.625 | I152: =+I111-I137 -> 53512.2 | J152: =+J111-J137 -> 66890.25 | ... N152: =+N111-N137 -> 136264.99 | O152: =SUM(C152:N152) -> 812534.26
...

Sheet Key LIGIA
C4: 46023 | D4: 46024 | E4: 46025 | F4: 46026 | G4: 46027 | H4: 46028 | I4: 46029 | J4: 46030 | K4: 46031 | L4: 46032 | M4: 46033 | N4: 46034
B6: Units Available | C6: 30 | D6: 30 | E6: 30 | F6: 30 | G6: 30 | H6: 30 | I6: 30 | J6: 30 | K6: 30 | L6: 30 | M6: 30 | N6: 30
B7: Day per month | C7: 31 | D7: 28 | E7: 31 | F7: 30 | G7: 31 | H7: 30 | I7: 31 | J7: 31 | K7: 30 | L7: 31 | M7: 30 | N7: 31
B9: Total Nights Available | C9: =+C6*C7 -> 930 | D9: =+D6*D7 -> 840 | E9: =+E6*E7 -> 930 | F9: =+F6*F7 -> 900 | G9: =+G6*G7 -> 930 | H9: =+H6*H7 -> 900 | I9: =+I6*I7 -> 930 | J9: =+J6*J7 -> 930 | ... N9: =+N6*N7 -> 930
B12: Units Category
A14: 1 | B14: Corcovado Deluxe Villas, King bed | C14: 6 | D14: 6 | E14: 6 | F14: 6 | G14: 6 | H14: 6 | I14: 6 | J14: 6 | K14: 6 | L14: 6 | M14: 6 | N14: 6
A15: 2 | B15: Carate Deluxe Villa Double Beds | C15: 2 | D15: 2 | E15: 2 | F15: 2 | G15: 2 | H15: 2 | I15: 2 | J15: 2 | K15: 2 | L15: 2 | M15: 2 | N15: 2
A16: 3 | B16: Agujas Villa 2 Queen Beds | C16: 3 | D16: 3 | E16: 3 | F16: 3 | G16: 3 | H16: 3 | I16: 3 | J16: 3 | K16: 3 | L16: 3 | M16: 3 | N16: 3
A17: 4 | B17: Sirena Suites, Queen Bed (conecting) | C17: 8 | D17: 8 | E17: 8 | F17: 8 | G17: 8 | H17: 8 | I17: 8 | J17: 8 | K17: 8 | L17: 8 | M17: 8 | N17: 8
A18: 5 | B18: Treehouse king bed | C18: 5 | D18: 5 | E18: 5 | F18: 5 | G18: 5 | H18: 5 | I18: 5 | J18: 5 | K18: 5 | L18: 5 | M18: 5 | N18: 5
A19: 6 | B19: 5 Elements Treehouse king bed | C19: 6 | D19: 6 | E19: 6 | F19: 6 | G19: 6 | H19: 6 | I19: 6 | J19: 6 | K19: 6 | L19: 6 | M19: 6 | N19: 6
B20: Total | C20: =SUM(C14:C19) -> 30 | D20: =SUM(D14:D19) -> 30 | E20: =SUM(E14:E19) -> 30 | F20: =SUM(F14:F19) -> 30 | G20: =SUM(G14:G19) -> 30 | H20: =SUM(H14:H19) -> 30 | I20: =SUM(I14:I19) -> 30 | J20: =SUM(J14:J19) -> 30 | ... N20: =SUM(N14:N19) -> 30
B23: Total Room Nights Available per Category
A25: 1 | B25: Corcovado Deluxe Villas, King bed | C25: =+C14*C$7 -> 186 | D25: =+D14*D$7 -> 168 | E25: =+E14*E$7 -> 186 | F25: =+F14*F$7 -> 180 | G25: =+G14*G$7 -> 186 | H25: =+H14*H$7 -> 180 | I25: =+I14*I$7 -> 186 | J25: =+J14*J$7 -> 186 | ... N25: =+N14*N$7 -> 186 | O25: =SUM(C25:N25) -> 2190
A26: 2 | B26: Carate Deluxe Villa Double Beds | C26: =+C15*C$7 -> 62 | D26: =+D15*D$7 -> 56 | E26: =+E15*E$7 -> 62 | F26: =+F15*F$7 -> 60 | G26: =+G15*G$7 -> 62 | H26: =+H15*H$7 -> 60 | I26: =+I15*I$7 -> 62 | J26: =+J15*J$7 -> 62 | ... N26: =+N15*N$7 -> 62 | O26: =SUM(C26:N26) -> 730
A27: 3 | B27: Agujas Villa 2 Queen Beds | C27: =+C16*C$7 -> 93 | D27: =+D16*D$7 -> 84 | E27: =+E16*E$7 -> 93 | F27: =+F16*F$7 -> 90 | G27: =+G16*G$7 -> 93 | H27: =+H16*H$7 -> 90 | I27: =+I16*I$7 -> 93 | J27: =+J16*J$7 -> 93 | ... N27: =+N16*N$7 -> 93 | O27: =SUM(C27:N27) -> 1095
A28: 4 | B28: Sirena Suites, Queen Bed (conecting) | C28: =+C17*C$7 -> 248 | D28: =+D17*D$7 -> 224 | E28: =+E17*E$7 -> 248 | F28: =+F17*F$7 -> 240 | G28: =+G17*G$7 -> 248 | H28: =+H17*H$7 -> 240 | I28: =+I17*I$7 -> 248 | J28: =+J17*J$7 -> 248 | ... N28: =+N17*N$7 -> 248 | O28: =SUM(C28:N28) -> 2920
A29: 5 | B29: Treehouse king bed | C29: =+C18*C$7 -> 155 | D29: =+D18*D$7 -> 140 | E29: =+E18*E$7 -> 155 | F29: =+F18*F$7 -> 150 | G29: =+G18*G$7 -> 155 | H29: =+H18*H$7 -> 150 | I29: =+I18*I$7 -> 155 | J29: =+J18*J$7 -> 155 | ... N29: =+N18*N$7 -> 155 | O29: =SUM(C29:N29) -> 1825
A30: 6 | B30: 5 Elements Treehouse king bed | C30: =+C19*C$7 -> 186 | D30: =+D19*D$7 -> 168 | E30: =+E19*E$7 -> 186 | F30: =+F19*F$7 -> 180 | G30: =+G19*G$7 -> 186 | H30: =+H19*H$7 -> 180 | I30: =+I19*I$7 -> 186 | J30: =+J19*J$7 -> 186 | ... N30: =+N19*N$7 -> 186 | O30: =SUM(C30:N30) -> 2190
B32: Total | C32: =SUM(C25:C31) -> 930 | D32: =SUM(D25:D31) -> 840 | E32: =SUM(E25:E31) -> 930 | F32: =SUM(F25:F31) -> 900 | G32: =SUM(G25:G31) -> 930 | H32: =SUM(H25:H31) -> 900 | I32: =SUM(I25:I31) -> 930 | J32: =SUM(J25:J31) -> 930 | ... O32: =SUM(O25:O31) -> 10950
B35: Rack Rates Rooms only | G35: LIGIA PUT IN THE 2026 RATES
B37: Room Type | C37: January | D37: February | E37: March | F37: April | G37: May | H37: June | I37: July | J37: August | K37: September | L37: October | M37: November | N37: December
A38: 1 | B38: Corcovado Deluxe Villas, King bed | C38: =708.75/1.1 -> 644.31818 | D38: =708.75/1.1 -> 644.31818 | E38: =708.75/1.1 -> 644.31818 | F38: =681.75/1.1 -> 619.77273 | G38: =614.25/1.1 -> 558.40909 | H38: =594/1.1 -> 540 | I38: =594/1.1 -> 540 | J38: =594/1.1 -> 540 | K38: =546.75/1.1 -> 497.04545 | L38: =533.25/1.1 -> 484.77273 | M38: =560.25/1.1 -> 509.31818 | N38: =776.25/1.1 -> 705.68182
A39: 2 | B39: Carate Deluxe Villa Double Beds | C39: =654.75/1.1 -> 595.22727 | D39: =654.75/1.1 -> 595.22727 | E39: =654.75/1.1 -> 595.22727 | F39: =621/1.1 -> 564.54545 | G39: =587.25/1.1 -> 533.86364 | H39: =567/1.1 -> 515.45455 | I39: =567/1.1 -> 515.45455 | J39: =567/1.1 -> 515.45455 | K39: =533.25/1.1 -> 484.77273 | L39: =506.25/1.1 -> 460.22727 | M39: =594/1.1 -> 540 | N39: =702/1.1 -> 638.18182
A40: 3 | B40: Agujas Villa 2 Queen Beds | C40: =600.75/1.1 -> 546.13636 | D40: =600.75/1.1 -> 546.13636 | E40: =600.75/1.1 -> 546.13636 | F40: =560.25/1.1 -> 509.31818 | G40: =533.25/1.1 -> 484.77273 | H40: =506.25/1.1 -> 460.22727 | I40: =506.25/1.1 -> 460.22727 | J40: =506.25/1.1 -> 460.22727 | K40: =479.25/1.1 -> 435.68182 | L40: =445.5/1.1 -> 405 | M40: =486/1.1 -> 441.81818 | N40: =654.75/1.1 -> 595.22727
A41: 4 | B41: Sirena Suites, Queen Bed (conecting) | C41: =533.25/1.1 -> 484.77273 | D41: =533.25/1.1 -> 484.77273 | E41: =533.25/1.1 -> 484.77273 | F41: =486/1.1 -> 441.81818 | G41: =445.5/1.1 -> 405 | H41: =425.25/1.1 -> 386.59091 | I41: =425.25/1.1 -> 386.59091 | J41: =425.25/1.1 -> 386.59091 | K41: =391.5/1.1 -> 355.90909 | L41: =371.25/1.1 -> 337.5 | M41: =398.25/1.1 -> 362.04545 | N41: =553.5/1.1 -> 503.18182
A42: 5 | B42: Treehouse king bed | C42: =1073.25/1.1 -> 975.68182 | D42: =1073.25/1.1 -> 975.68182 | E42: =1073.25/1.1 -> 975.68182 | F42: =978.75/1.1 -> 889.77273 | G42: =884.25/1.1 -> 803.86364 | H42: =837/1.1 -> 760.90909 | I42: =837/1.1 -> 760.90909 | J42: =837/1.1 -> 760.90909 | K42: =789.75/1.1 -> 717.95455 | L42: =715.5/1.1 -> 650.45455 | M42: =816.75/1.1 -> 742.5 | N42: =1059.75/1.1 -> 963.40909
A43: 6 | B43: 5 Elements Treehouse king bed | C43: =1208.25/1.1 -> 1098.4091 | D43: =1208.25/1.1 -> 1098.4091 | E43: =1208.25/1.1 -> 1098.4091 | F43: =1120.5/1.1 -> 1018.6364 | G43: =999/1.1 -> 908.18182 | H43: =924.75/1.1 -> 840.68182 | I43: =924.75/1.1 -> 840.68182 | J43: =924.75/1.1 -> 840.68182 | K43: =850.5/1.1 -> 773.18182 | L43: =816.75/1.1 -> 742.5 | M43: =924.75/1.1 -> 840.68182 | N43: =1307.45/1.1 -> 1188.5909
B48: % of Sale by Channel
C49: =+C37 -> January | D49: =+D37 -> February | E49: =+E37 -> March | F49: =+F37 -> April | G49: =+G37 -> May | H49: =+H37 -> June | I49: =+I37 -> July | J49: =+J37 -> August | ... M49: =+M37 -> November
B50: Travel Agency | C50: 0.6 | D50: 0.6 | E50: 0.6 | F50: 0.6 | G50: 0.6 | H50: 0.6 | I50: 0.6 | J50: 0.6 | K50: 0.6 | L50: 0.6 | M50: 0.6
B51: OTAS | C51: 0.05 | D51: 0.05 | E51: 0.05 | F51: 0.05 | G51: 0.05 | H51: 0.05 | I51: 0.05 | J51: 0.05 | K51: 0.05 | L51: 0.05 | M51: 0.05
B52: DIRECT | C52: 0.35 | D52: 0.35 | E52: 0.35 | F52: 0.35 | G52: 0.35 | H52: 0.35 | I52: 0.35 | J52: 0.35 | K52: 0.35 | L52: 0.35 | M52: 0.35
B53: NEW CHANNELS
B54: NEW CHANNELS
B56: Total | C56: =SUM(C50:C55) -> 1 | D56: =SUM(D50:D55) -> 1 | E56: =SUM(E50:E55) -> 1 | F56: =SUM(F50:F55) -> 1 | G56: =SUM(G50:G55) -> 1 | H56: =SUM(H50:H55) -> 1 | I56: =SUM(I50:I55) -> 1 | J56: =SUM(J50:J55) -> 1 | ... M56: =SUM(M50:M55) -> 1
B60: COMMISSIONS By channel
C61: =+C37 -> January
B62: Travel Agency | C62: 0.28
B63: OTAS | C63: 0.2
B64: DIRECT | C64: 0
B65: NEW CHANNELS | C65: 0
B66: NEW CHANNELS | C66: 0
B71: Occupancy per Room PROPOSE TO PROFORMA
B72: We will need to go back up to 90 employees. I would model it after how we looked in the highest month this year on expenses, but for every month. I will put us out 85% occupancy January February March. April July August at 50 percent. November 60%. December 65 percent. And reduce June September and October to bring the total occupancy to 55% for the year. | R72: This is not what we will do in 2026. This maybe 2028 or whatever. At some point we will be at 60%
B74: Occupancy | C74: 0.65 | D74: 0.65 | E74: 0.65 | F74: 0.35 | G74: 0.35 | H74: 0.35 | I74: 0.35 | J74: 0.35 | K74: 0.35 | L74: 0 | M74: 0.45 | N74: 0.65
B75: Room Type | C75: January | D75: February | E75: March | F75: April | G75: May | H75: June | I75: July | J75: August | K75: September | L75: October | M75: November | N75: December | O75: TOTAL
B76: Corcovado Deluxe Villas, King bed | C76: =+C25*C$74 -> 120.9 | D76: =+D25*D$74 -> 109.2 | E76: =+E25*E$74 -> 120.9 | F76: =+F25*F$74 -> 63 | G76: =+G25*G$74 -> 65.1 | H76: =+H25*H$74 -> 63 | I76: =+I25*I$74 -> 65.1 | J76: =+J25*J$74 -> 65.1 | ... N76: =+N25*N$74 -> 120.9 | O76: =SUM(C76:N76) -> 937.2 | R76: We can run the pro forma at 55%
B77: Carate Deluxe Villa Double Beds | C77: =+C26*C$74 -> 40.3 | D77: =+D26*D$74 -> 36.4 | E77: =+E26*E$74 -> 40.3 | F77: =+F26*F$74 -> 21 | G77: =+G26*G$74 -> 21.7 | H77: =+H26*H$74 -> 21 | I77: =+I26*I$74 -> 21.7 | J77: =+J26*J$74 -> 21.7 | ... N77: =+N26*N$74 -> 40.3 | O77: =SUM(C77:N77) -> 312.4
B78: Agujas Villa 2 Queen Beds | C78: =+C27*C$74 -> 60.45 | D78: =+D27*D$74 -> 54.6 | E78: =+E27*E$74 -> 60.45 | F78: =+F27*F$74 -> 31.5 | G78: =+G27*G$74 -> 32.55 | H78: =+H27*H$74 -> 31.5 | I78: =+I27*I$74 -> 32.55 | J78: =+J27*J$74 -> 32.55 | ... N78: =+N27*N$74 -> 60.45 | O78: =SUM(C78:N78) -> 468.6 | R78: This is just a show what we will look like when we’re stabilized. This is not the 2026 budget.
B79: Sirena Suites, Queen Bed (conecting) | C79: =+C28*C$74 -> 161.2 | D79: =+D28*D$74 -> 145.6 | E79: =+E28*E$74 -> 161.2 | F79: =+F28*F$74 -> 84 | G79: =+G28*G$74 -> 86.8 | H79: =+H28*H$74 -> 84 | I79: =+I28*I$74 -> 86.8 | J79: =+J28*J$74 -> 86.8 | ... N79: =+N28*N$74 -> 161.2 | O79: =SUM(C79:N79) -> 1249.6
B80: Treehouse king bed | C80: =+C29*C$74 -> 100.75 | D80: =+D29*D$74 -> 91 | E80: =+E29*E$74 -> 100.75 | F80: =+F29*F$74 -> 52.5 | G80: =+G29*G$74 -> 54.25 | H80: =+H29*H$74 -> 52.5 | I80: =+I29*I$74 -> 54.25 | J80: =+J29*J$74 -> 54.25 | ... N80: =+N29*N$74 -> 100.75 | O80: =SUM(C80:N80) -> 781 | R80: We will need to go back up to 90 employees. I would model it after how we looked in the highest month this year on expenses, but for every month. I will put us out 85% occupancy January February March. April July August at 50 percent. November 60%. December 65 percent. And reduce June September and October to bring the total occupancy to 55% for the year.
B81: 5 Elements Treehouse king bed | C81: =+C30*C$74 -> 120.9 | D81: =+D30*D$74 -> 109.2 | E81: =+E30*E$74 -> 120.9 | F81: =+F30*F$74 -> 63 | G81: =+G30*G$74 -> 65.1 | H81: =+H30*H$74 -> 63 | I81: =+I30*I$74 -> 65.1 | J81: =+J30*J$74 -> 65.1 | ... N81: =+N30*N$74 -> 120.9 | O81: =SUM(C81:N81) -> 937.2
B82: TOTAL | C82: =SUM(C76:C81) -> 604.5 | D82: =SUM(D76:D81) -> 546 | E82: =SUM(E76:E81) -> 604.5 | F82: =SUM(F76:F81) -> 315 | G82: =SUM(G76:G81) -> 325.5 | H82: =SUM(H76:H81) -> 315 | I82: =SUM(I76:I81) -> 325.5 | J82: =SUM(J76:J81) -> 325.5 | ... N82: =SUM(N76:N81) -> 604.5 | O82: =SUM(C82:N82) -> 4686
C83: =+C82/C32 -> 0.65 | D83: =+D82/D32 -> 0.65 | E83: =+E82/E32 -> 0.65 | F83: =+F82/F32 -> 0.35 | G83: =+G82/G32 -> 0.35 | H83: =+H82/H32 -> 0.35 | I83: =+I82/I32 -> 0.35 | J83: =+J82/J32 -> 0.35 | ... O83: =+O82/O32 -> 0.42794521
B86: TOTAL REVENUE ACCORDING TO PROFORMA
B89: Occupancy | C89: =+C74 -> 0.65 | D89: =+D74 -> 0.65 | E89: =+E74 -> 0.65 | F89: =+F74 -> 0.35 | G89: =+G74 -> 0.35 | H89: =+H74 -> 0.35 | I89: =+I74 -> 0.35 | J89: =+J74 -> 0.35 | ... N89: =+N74 -> 0.65
B90: Room Type | C90: January | D90: February | E90: March | F90: April | G90: May | H90: June | I90: July | J90: August | K90: September | L90: October | M90: November | N90: December | O90: TOTAL
B91: Corcovado Deluxe Villas, King bed | C91: =+C76*C38 -> 77898.068 | D91: =+D76*D38 -> 70359.545 | E91: =+E76*E38 -> 77898.068 | F91: =+F76*F38 -> 39045.682 | G91: =+G76*G38 -> 36352.432 | H91: =+H76*H38 -> 34020 | I91: =+I76*I38 -> 35154 | J91: =+J76*J38 -> 35154 | ... N91: =+N76*N38 -> 85316.932 | O91: =SUM(C91:N91) -> 563767.36
B92: Carate Deluxe Villa Double Beds | C92: =+C77*C39 -> 23987.659 | D92: =+D77*D39 -> 21666.273 | E92: =+E77*E39 -> 23987.659 | F92: =+F77*F39 -> 11855.455 | G92: =+G77*G39 -> 11584.841 | H92: =+H77*H39 -> 10824.545 | I92: =+I77*I39 -> 11185.364 | J92: =+J77*J39 -> 11185.364 | ... N92: =+N77*N39 -> 25718.727 | O92: =SUM(C92:N92) -> 176756.11
B93: Agujas Villa 2 Queen Beds | C93: =+C78*C40 -> 33013.943 | D93: =+D78*D40 -> 29819.045 | E93: =+E78*E40 -> 33013.943 | F93: =+F78*F40 -> 16043.523 | G93: =+G78*G40 -> 15779.352 | H93: =+H78*H40 -> 14497.159 | I93: =+I78*I40 -> 14980.398 | J93: =+J78*J40 -> 14980.398 | ... N93: =+N78*N40 -> 35981.489 | O93: =SUM(C93:N93) -> 239726.86
B94: Sirena Suites, Queen Bed (conecting) | C94: =+C79*C41 -> 78145.364 | D94: =+D79*D41 -> 70582.909 | E94: =+E79*E41 -> 78145.364 | F94: =+F79*F41 -> 37112.727 | G94: =+G79*G41 -> 35154 | H94: =+H79*H41 -> 32473.636 | I94: =+I79*I41 -> 33556.091 | J94: =+J79*J41 -> 33556.091 | ... N94: =+N79*N41 -> 81112.909 | O94: =SUM(C94:N94) -> 548836.36
B95: Treehouse king bed | C95: =+C80*C42 -> 98299.943 | D95: =+D80*D42 -> 88787.045 | E95: =+E80*E42 -> 98299.943 | F95: =+F80*F42 -> 46713.068 | G95: =+G80*G42 -> 43609.602 | H95: =+H80*H42 -> 39947.727 | I95: =+I80*I42 -> 41279.318 | J95: =+J80*J42 -> 41279.318 | ... N95: =+N80*N42 -> 97063.466 | O95: =SUM(C95:N95) -> 683090.8
B96: 5 Elements Treehouse king bed | C96: =+C81*C43 -> 132797.66 | D96: =+D81*D43 -> 119946.27 | E96: =+E81*E43 -> 132797.66 | F96: =+F81*F43 -> 64174.091 | G96: =+G81*G43 -> 59122.636 | H96: =+H81*H43 -> 52962.955 | I96: =+I81*I43 -> 54728.386 | J96: =+J81*J43 -> 54728.386 | ... N96: =+N81*N43 -> 143700.64 | O96: =SUM(C96:N96) -> 931764.37
B98: TOTAL | C98: =SUM(C91:C97) -> 444142.64 | D98: =SUM(D91:D97) -> 401161.09 | E98: =SUM(E91:E97) -> 444142.64 | F98: =SUM(F91:F97) -> 214944.55 | G98: =SUM(G91:G97) -> 201602.86 | H98: =SUM(H91:H97) -> 184726.02 | I98: =SUM(I91:I97) -> 190883.56 | J98: =SUM(J91:J97) -> 190883.56 | ... N98: =SUM(N91:N97) -> 468894.16 | O98: =SUM(C98:N98) -> 3143941.9
B102: comision pagada para tarifa neta
D103: % VENTAS | E103: % COM
B104: Travel Agency | D104: =+C50 -> 0.6 | E104: =+C62 -> 0.28
B105: OTAS | D105: =+C51 -> 0.05 | E105: =+C63 -> 0.2
B106: DIRECT | D106: =+C52 -> 0.35 | E106: =+C64 -> 0
B107: NEW CHANNELS | D107: 0 | E107: 0
B108: NEW CHANNELS | D108: 0 | E108: 0
B110: SUMPRODUCT | D110: {=SUMPRODUCT(D104:D108,1-(E104:E108))} -> 0.822
B112: COMMISION PAID TO CHANNELS ACCORDING TO COMMISSIONS AND % OF SALE
B115: Occupancy | C115: =+C89 -> 0.65 | D115: =+D89 -> 0.65 | E115: =+E89 -> 0.65 | F115: =+F89 -> 0.35 | G115: =+G89 -> 0.35 | H115: =+H89 -> 0.35 | I115: =+I89 -> 0.35 | J115: =+J89 -> 0.35 | ... N115: =+N89 -> 0.65 | O115: =+O83 -> 0.42794521
B116: Room Type | C116: January | D116: February | E116: March | F116: April | G116: May | H116: June | I116: July | J116: August | K116: September | L116: October | M116: November | N116: December | O116: TOTAL
B117: Corcovado Deluxe Villas, King bed | C117: =(1-$D$110)*C91 -> 13865.856 | D117: =(1-$D$110)*D91 -> 12523.999 | E117: =(1-$D$110)*E91 -> 13865.856 | F117: =(1-$D$110)*F91 -> 6950.1314 | G117: =(1-$D$110)*G91 -> 6470.7329 | H117: =(1-$D$110)*H91 -> 6055.56 | I117: =(1-$D$110)*I91 -> 6257.412 | J117: =(1-$D$110)*J91 -> 6257.412 | ... N117: =(1-$D$110)*N91 -> 15186.414 | O117: =SUM(C117:N117) -> 100350.59
B118: Carate Deluxe Villa Double Beds | C118: =(1-$D$110)*C92 -> 4269.8033 | D118: =(1-$D$110)*D92 -> 3856.5965 | E118: =(1-$D$110)*E92 -> 4269.8033 | F118: =(1-$D$110)*F92 -> 2110.2709 | G118: =(1-$D$110)*G92 -> 2062.1017 | H118: =(1-$D$110)*H92 -> 1926.7691 | I118: =(1-$D$110)*I92 -> 1990.9947 | J118: =(1-$D$110)*J92 -> 1990.9947 | ... N118: =(1-$D$110)*N92 -> 4577.9335 | O118: =SUM(C118:N118) -> 31462.588
B119: Agujas Villa 2 Queen Beds | C119: =(1-$D$110)*C93 -> 5876.4819 | D119: =(1-$D$110)*D93 -> 5307.7901 | E119: =(1-$D$110)*E93 -> 5876.4819 | F119: =(1-$D$110)*F93 -> 2855.747 | G119: =(1-$D$110)*G93 -> 2808.7247 | H119: =(1-$D$110)*H93 -> 2580.4943 | I119: =(1-$D$110)*I93 -> 2666.5108 | J119: =(1-$D$110)*J93 -> 2666.5108 | ... N119: =(1-$D$110)*N93 -> 6404.705 | O119: =SUM(C119:N119) -> 42671.382
B120: Sirena Suites, Queen Bed (conecting) | C120: =(1-$D$110)*C94 -> 13909.875 | D120: =(1-$D$110)*D94 -> 12563.758 | E120: =(1-$D$110)*E94 -> 13909.875 | F120: =(1-$D$110)*F94 -> 6606.0655 | G120: =(1-$D$110)*G94 -> 6257.412 | H120: =(1-$D$110)*H94 -> 5780.3073 | I120: =(1-$D$110)*I94 -> 5972.9842 | J120: =(1-$D$110)*J94 -> 5972.9842 | ... N120: =(1-$D$110)*N94 -> 14438.098 | O120: =SUM(C120:N120) -> 97692.873
B121: Treehouse king bed | C121: =(1-$D$110)*C95 -> 17497.39 | D121: =(1-$D$110)*D95 -> 15804.094 | E121: =(1-$D$110)*E95 -> 17497.39 | F121: =(1-$D$110)*F95 -> 8314.9261 | G121: =(1-$D$110)*G95 -> 7762.5092 | H121: =(1-$D$110)*H95 -> 7110.6955 | I121: =(1-$D$110)*I95 -> 7347.7186 | J121: =(1-$D$110)*J95 -> 7347.7186 | ... N121: =(1-$D$110)*N95 -> 17277.297 | O121: =SUM(C121:N121) -> 121590.16
B122: 5 Elements Treehouse king bed | C122: =(1-$D$110)*C96 -> 23637.983 | D122: =(1-$D$110)*D96 -> 21350.437 | E122: =(1-$D$110)*E96 -> 23637.983 | F122: =(1-$D$110)*F96 -> 11422.988 | G122: =(1-$D$110)*G96 -> 10523.829 | H122: =(1-$D$110)*H96 -> 9427.4059 | I122: =(1-$D$110)*I96 -> 9741.6528 | J122: =(1-$D$110)*J96 -> 9741.6528 | ... N122: =(1-$D$110)*N96 -> 25578.714 | O122: =SUM(C122:N122) -> 165854.06
B124: TOTAL | C124: =SUM(C117:C123) -> 79057.389 | D124: =SUM(D117:D123) -> 71406.674 | E124: =SUM(E117:E123) -> 79057.389 | F124: =SUM(F117:F123) -> 38260.129 | G124: =SUM(G117:G123) -> 35885.31 | H124: =SUM(H117:H123) -> 32881.232 | I124: =SUM(I117:I123) -> 33977.273 | J124: =SUM(J117:J123) -> 33977.273 | ... N124: =SUM(N117:N123) -> 83463.161 | O124: =SUM(C124:N124) -> 559621.65
B127: Net rate after commissions
B130: Occupancy | C130: 0.85 | D130: 0.85 | E130: 0.85 | F130: 0.5 | G130: 0.5 | H130: 0.5 | I130: 0.5 | J130: 0.5 | K130: 0.5 | L130: 0.5 | M130: 0.6 | N130: 0.65
B131: Room Type | C131: January | D131: February | E131: March | F131: April | G131: May | H131: June | I131: July | J131: August | K131: September | L131: October | M131: November | N131: December | O131: TOTAL
B132: Corcovado Deluxe Villas, King bed | C132: =+C91-C117 -> 64032.212 | D132: =+D91-D117 -> 57835.546 | E132: =+E91-E117 -> 64032.212 | F132: =+F91-F117 -> 32095.55 | G132: =+G91-G117 -> 29881.699 | H132: =+H91-H117 -> 27964.44 | I132: =+I91-I117 -> 28896.588 | J132: =+J91-J117 -> 28896.588 | ... N132: =+N91-N117 -> 70130.518 | O132: =SUM(C132:N132) -> 463416.77
B133: Carate Deluxe Villa Double Beds | C133: =+C92-C118 -> 19717.856 | D133: =+D92-D118 -> 17809.676 | E133: =+E92-E118 -> 19717.856 | F133: =+F92-F118 -> 9745.1836 | G133: =+G92-G118 -> 9522.7392 | H133: =+H92-H118 -> 8897.7764 | I133: =+I92-I118 -> 9194.3689 | J133: =+J92-J118 -> 9194.3689 | ... N133: =+N92-N118 -> 21140.794 | O133: =SUM(C133:N133) -> 145293.53
B134: Agujas Villa 2 Queen Beds | C134: =+C93-C119 -> 27137.461 | D134: =+D93-D119 -> 24511.255 | E134: =+E93-E119 -> 27137.461 | F134: =+F93-F119 -> 13187.776 | G134: =+G93-G119 -> 12970.628 | H134: =+H93-H119 -> 11916.665 | I134: =+I93-I119 -> 12313.887 | J134: =+J93-J119 -> 12313.887 | ... N134: =+N93-N119 -> 29576.784 | O134: =SUM(C134:N134) -> 197055.48
B135: Sirena Suites, Queen Bed (conecting) | C135: =+C94-C120 -> 64235.489 | D135: =+D94-D120 -> 58019.151 | E135: =+E94-E120 -> 64235.489 | F135: =+F94-F120 -> 30506.662 | G135: =+G94-G120 -> 28896.588 | H135: =+H94-H120 -> 26693.329 | I135: =+I94-I120 -> 27583.107 | J135: =+J94-J120 -> 27583.107 | ... N135: =+N94-N120 -> 66674.811 | O135: =SUM(C135:N135) -> 451143.49
B136: Treehouse king bed | C136: =+C95-C121 -> 80802.553 | D136: =+D95-D121 -> 72982.951 | E136: =+E95-E121 -> 80802.553 | F136: =+F95-F121 -> 38398.142 | G136: =+G95-G121 -> 35847.093 | H136: =+H95-H121 -> 32837.032 | I136: =+I95-I121 -> 33931.6 | J136: =+J95-J121 -> 33931.6 | ... N136: =+N95-N121 -> 79786.169 | O136: =SUM(C136:N136) -> 561500.63
B137: 5 Elements Treehouse king bed | C137: =+C96-C122 -> 109159.68 | D137: =+D96-D122 -> 98595.836 | E137: =+E96-E122 -> 109159.68 | F137: =+F96-F122 -> 52751.103 | G137: =+G96-G122 -> 48598.807 | H137: =+H96-H122 -> 43535.549 | I137: =+I96-I122 -> 44986.734 | J137: =+J96-J122 -> 44986.734 | ... N137: =+N96-N122 -> 118121.93 | O137: =SUM(C137:N137) -> 765910.31
B138: TOTAL | C138: =SUM(C132:C137) -> 365085.25 | D138: =SUM(D132:D137) -> 329754.42 | E138: =SUM(E132:E137) -> 365085.25 | F138: =SUM(F132:F137) -> 176684.42 | G138: =SUM(G132:G137) -> 165717.55 | H138: =SUM(H132:H137) -> 151844.79 | I138: =SUM(I132:I137) -> 156906.28 | J138: =SUM(J132:J137) -> 156906.28 | ... N138: =SUM(N132:N137) -> 385431 | O138: =SUM(C138:N138) -> 2584320.2
O139: =+O138/O82 -> 551.49813 | P139: 487 | Q139: =+O139-P139 -> 64.498125
B141: NET RATE AFFECTED BY CHANNEL AND % COMMISION BY CHANNEL | Q141: =+Q139/P139 -> 0.13243968
B144: Occupancy | C144: 0.85 | D144: 0.85 | E144: 0.85 | F144: 0.5 | G144: 0.5 | H144: 0.5 | I144: 0.5 | J144: 0.5 | K144: 0.5 | L144: 0.5 | M144: 0.6 | N144: 0.65
B145: Room Type | C145: January | D145: February | E145: March | F145: April | G145: May | H145: June | I145: July | J145: August | K145: September | L145: October | M145: November | N145: December | O145: TOTAL
B146: Corcovado Deluxe Villas, King bed | C146: =+C132/C76 -> 529.62955 | D146: =+D132/D76 -> 529.62955 | E146: =+E132/E76 -> 529.62955 | F146: =+F132/F76 -> 509.45318 | G146: =+G132/G76 -> 459.01227 | H146: =+H132/H76 -> 443.88 | I146: =+I132/I76 -> 443.88 | J146: =+J132/J76 -> 443.88 | ... O146: =+O132/O76 -> 494.46945
B147: Carate Deluxe Villa Double Beds | C147: =+C133/C77 -> 489.27682 | D147: =+D133/D77 -> 489.27682 | E147: =+E133/E77 -> 489.27682 | F147: =+F133/F77 -> 464.05636 | G147: =+G133/G77 -> 438.83591 | H147: =+H133/H77 -> 423.70364 | I147: =+I133/I77 -> 423.70364 | J147: =+J133/J77 -> 423.70364 | ... O147: =+O133/O77 -> 465.08811
B148: Agujas Villa 2 Queen Beds | C148: =+C134/C78 -> 448.92409 | D148: =+D134/D78 -> 448.92409 | E148: =+E134/E78 -> 448.92409 | F148: =+F134/F78 -> 418.65955 | G148: =+G134/G78 -> 398.48318 | H148: =+H134/H78 -> 378.30682 | I148: =+I134/I78 -> 378.30682 | J148: =+J134/J78 -> 378.30682 | ... O148: =+O134/O78 -> 420.51959
...

Sheet Rooms
B1: ⟵ Back to Summary | D1: Rooms – Key Indicators & Budget
B11: Key Indicators 2024
B12: Indicator | C12: January | D12: February | E12: March | F12: April | G12: May | H12: June | I12: July | J12: August | K12: September | L12: October | M12: November | N12: December | O12: TOTAL | Q12: RATE
B13: Total available Rooms | C13: 930 | D13: 870 | E13: 930 | F13: 900 | G13: 930 | H13: 900 | I13: 930 | J13: 930 | K13: 900 | L13: 930 | M13: 900 | N13: 930 | O13: =SUM(C13:N13) -> 10980
B14: Total Rooms Occupied | C14: 429 | D14: 456 | E14: 448 | F14: 259 | G14: 176 | H14: 98 | I14: 249 | J14: 157 | K14: 6 | L14: 0 | M14: 179 | N14: 317 | O14: =SUM(C14:N14) -> 2774
B15: Total Guests | C15: 711 | D15: 834 | E15: 835 | F15: 544 | G15: 311 | H15: 160 | I15: 429 | J15: 310 | K15: 12 | M15: 316 | N15: 614 | O15: =SUM(C15:N15) -> 5076 | Q15: =+O15/O14 -> 1.8298486
B16: % Occupancy | C16: 0.4613 | D16: 0.5241 | E16: 0.4817 | F16: 0.2878 | G16: 0.1892 | H16: 0.1089 | I16: 0.2677 | J16: 0.1688 | K16: 0.0067 | M16: 0.1989 | N16: 0.3409 | O16: =+O14/O13 -> 0.25264117
B17: Average Daily Room Only | C17: =+C36/C14 -> 359.84047 | D17: =+D36/D14 -> 465.18852 | E17: =+E36/E14 -> 389.00314 | F17: =+F36/F14 -> 378.9522 | G17: =+G36/G14 -> 231.30814 | H17: =+H36/H14 -> 291.12236 | I17: =+I36/I14 -> 426.03102 | J17: =+J36/J14 -> 403.28888 | K17: =+K36/K14 -> 434.33013 | M17: =+M36/M14 -> 471.30737 | N17: =+N36/N14 -> 729.00372 | O17: =+O36/O14 -> 431.01011
B18: Key Indicators 2025
B19: Indicator | C19: January | D19: February | E19: March | F19: April | G19: May | H19: June | I19: July | J19: August | K19: September | L19: October | M19: November | N19: December | O19: TOTAL
B20: Total available Rooms | C20: 930 | D20: 840 | E20: 930 | F20: 900 | G20: 930 | H20: 900 | I20: 930 | J20: 930 | K20: 900 | L20: 930 | M20: 900 | N20: 930 | O20: =SUM(C20:N20) -> 10950
B21: Total Rooms Occupied | C21: 454 | D21: 479 | E21: 519 | F21: 239 | G21: 114 | H21: 102 | I21: 274 | J21: 220 | K21: 28 | L21: 50 | M21: 230 | N21: 470 | O21: =SUM(C21:N21) -> 3179
B22: Total Guests | C22: 809 | D22: 893 | E22: 962 | F22: 428 | G22: 228 | H22: 183 | I22: 611 | J22: 411 | K22: 27 | L22: 75 | M22: 345 | N22: 705 | O22: =SUM(C22:N22) -> 5677 | Q22: =+O22/O21 -> 1.7857817
B23: % Occupancy | C23: =+C21/C20 -> 0.48817204 | D23: =+D21/D20 -> 0.5702381 | E23: =+E21/E20 -> 0.55806452 | F23: =+F21/F20 -> 0.26555556 | G23: =+G21/G20 -> 0.12258065 | H23: =+H21/H20 -> 0.11333333 | I23: =+I21/I20 -> 0.29462366 | J23: =+J21/J20 -> 0.23655914 | ... O23: =+O21/O20 -> 0.29031963
B24: Average Daily Room Only | C24: =+C37/C21 -> 473.50649 | D24: =+D37/D21 -> 550.00104 | E24: =+E37/E21 -> 478.48852 | F24: =+F37/F21 -> 497.89901 | G24: =+G37/G21 -> 482.76039 | H24: =+H37/H21 -> 379.47717 | I24: =+I37/I21 -> 508.05451 | J24: =+J37/J21 -> 371.59366 | ... O24: =+O37/O21 -> 484.67682
B25: Key Indicators 2026 (Budget)
B26: Indicator | C26: January | D26: February | E26: March | F26: April | G26: May | H26: June | I26: July | J26: August | K26: September | L26: October | M26: November | N26: December | O26: TOTAL
B27: Total available Rooms | C27: =+'Key Indicators'!C318 -> 930 | D27: =+'Key Indicators'!D318 -> 840 | E27: =+'Key Indicators'!E318 -> 930 | F27: =+'Key Indicators'!F318 -> 900 | G27: =+'Key Indicators'!G318 -> 930 | H27: =+'Key Indicators'!H318 -> 900 | I27: =+'Key Indicators'!I318 -> 930 | J27: =+'Key Indicators'!J318 -> 930 | ... N27: =+'Key Indicators'!N318 -> 930 | O27: =SUM(C27:N27) -> 10020
B28: Total Rooms Occupied | C28: =+'Key Indicators'!C319 -> 697.5 | D28: =+'Key Indicators'!D319 -> 638.4 | E28: =+'Key Indicators'!E319 -> 607.7 | F28: =+'Key Indicators'!F319 -> 332 | G28: =+'Key Indicators'!G319 -> 232.48621 | H28: =+'Key Indicators'!H319 -> 167.65517 | I28: =+'Key Indicators'!I319 -> 332.1 | J28: =+'Key Indicators'!J319 -> 251.32 | ... N28: =+'Key Indicators'!N319 -> 611.7075 | O28: =SUM(C28:N28) -> 4363.2889
B29: Total Guests | C29: =+'Key Indicators'!C320 -> 1255.5 | D29: =+'Key Indicators'!D320 -> 1149.12 | E29: =+'Key Indicators'!E320 -> 1093.86 | F29: =+'Key Indicators'!F320 -> 597.6 | G29: =+'Key Indicators'!G320 -> 418.47517 | H29: =+'Key Indicators'!H320 -> 301.77931 | I29: =+'Key Indicators'!I320 -> 597.78 | J29: =+'Key Indicators'!J320 -> 452.376 | ... N29: =+'Key Indicators'!N320 -> 1101.0735 | O29: =SUM(C29:N29) -> 7853.92 | Q29: =+O29/O28 -> 1.8
B30: % Occupancy | C30: =+C28/C27 -> 0.75 | D30: =+D28/D27 -> 0.76 | E30: =+E28/E27 -> 0.65344086 | F30: =+F28/F27 -> 0.36888889 | G30: =+G28/G27 -> 0.24998517 | H30: =+H28/H27 -> 0.18628352 | I30: =+I28/I27 -> 0.35709677 | J30: =+J28/J27 -> 0.27023656 | K30: =+K28/K27 -> 0.091466667 | M30: =+M28/M27 -> 0.45566667 | N30: =+N28/N27 -> 0.65775 | O30: =+O28/O27 -> 0.43545797
B31: Average Daily Room Only | C31: =+C38/C28 -> 595.27155 | D31: =+D38/D28 -> 583.47405 | E31: =+E38/E28 -> 590.96203 | F31: =+F38/F28 -> 635.29075 | G31: =+G38/G28 -> 521.40328 | H31: =+H38/H28 -> 553.7017 | I31: =+I38/I28 -> 566.23141 | J31: =+J38/J28 -> 520.6179 | K31: =+K38/K28 -> 485.58682 | M31: =+M38/M28 -> 548.40744 | N31: =+N38/N28 -> 733.76344 | O31: =+O38/O28 -> 596.88852
B34: Revenue by Monthper Year
B35: Label | C35: January | D35: February | E35: March | F35: April | G35: May | H35: June | I35: July | J35: August | K35: September | L35: October | M35: November | N35: December | O35: TOTAL
B36: Revenue 2024 | C36: 154371.56 | D36: 212125.96 | E36: 174273.41 | F36: 98148.619 | G36: 40710.232 | H36: 28529.992 | I36: 106081.72 | J36: 63316.354 | K36: 2605.9808 | L36: 0 | M36: 84364.018 | N36: 231094.18 | O36: =SUM(C36:N36) -> 1195622
B37: Revenue 2025 | C37: 214971.95 | D37: 263450.5 | E37: 248335.54 | F37: 118997.86 | G37: 55034.684 | H37: 38706.671 | I37: 139206.94 | J37: 81750.604 | K37: 11282.86 | L37: 19750 | M37: 93150 | N37: 256150 | O37: =SUM(C37:N37) -> 1540787.6
B38: Revenue 2026 Budget | C38: =+'Key Indicators'!C327 -> 415201.91 | D38: =+'Key Indicators'!D327 -> 372489.83 | E38: =+'Key Indicators'!E327 -> 359127.63 | F38: =+'Key Indicators'!F327 -> 210916.53 | G38: =+'Key Indicators'!G327 -> 121219.07 | H38: =+'Key Indicators'!H327 -> 92830.953 | I38: =+'Key Indicators'!I327 -> 188045.45 | J38: =+'Key Indicators'!J327 -> 130841.69 | ... N38: =+'Key Indicators'!N327 -> 448848.6 | O38: =SUM(C38:N38) -> 2604397.1
B41: Increase from 2025 to 2026 RN | C41: =(C38-C37)/C37 -> 0.93142368 | D41: =(D38-D37)/D37 -> 0.41388926 | E41: =(E38-E37)/E37 -> 0.44613867 | F41: =(F38-F37)/F37 -> 0.77243964 | G41: =(G38-G37)/G37 -> 1.2025941 | H41: =(H38-H37)/H37 -> 1.3983192 | I41: =(I38-I37)/I37 -> 0.35083391 | J41: =(J38-J37)/J37 -> 0.60049815 | ... O41: =(O38-O37)/O37 -> 0.69030244
B42: Increase from 2025 to 2026 Rev | C42: =+C38-C37 -> 200229.96 | D42: =+D38-D37 -> 109039.33 | E42: =+E38-E37 -> 110792.09 | F42: =+F38-F37 -> 91918.667 | G42: =+G38-G37 -> 66184.386 | H42: =+H38-H37 -> 54124.282 | I42: =+I38-I37 -> 48838.514 | J42: =+J38-J37 -> 49091.087 | ... O42: =+O38-O37 -> 1063609.4

Sheet Food Revenue
B1: ⟵ Back to Summary | D1: Food Revenue – Key Indicators & Budget
B11: Key Indicators 2024
B12: Indicator | C12: January | D12: February | E12: March | F12: April | G12: May | H12: June | I12: July | J12: August | K12: September | L12: October | M12: November | N12: December | O12: TOTAL
B13: Total available Rooms | C13: =Rooms!C13 -> 930 | D13: =Rooms!D13 -> 870 | E13: =Rooms!E13 -> 930 | F13: =Rooms!F13 -> 900 | G13: =Rooms!G13 -> 930 | H13: =Rooms!H13 -> 900 | I13: =Rooms!I13 -> 930 | J13: =Rooms!J13 -> 930 | ... O13: =Rooms!O13 -> 10980
B14: Total Rooms Occupied | C14: =Rooms!C14 -> 429 | D14: =Rooms!D14 -> 456 | E14: =Rooms!E14 -> 448 | F14: =Rooms!F14 -> 259 | G14: =Rooms!G14 -> 176 | H14: =Rooms!H14 -> 98 | I14: =Rooms!I14 -> 249 | J14: =Rooms!J14 -> 157 | ... O14: =Rooms!O14 -> 2774
B15: Total Guests | C15: =Rooms!C15 -> 711 | D15: =Rooms!D15 -> 834 | E15: =Rooms!E15 -> 835 | F15: =Rooms!F15 -> 544 | G15: =Rooms!G15 -> 311 | H15: =Rooms!H15 -> 160 | I15: =Rooms!I15 -> 429 | J15: =Rooms!J15 -> 310 | ... O15: =Rooms!O15 -> 5076
B16: % Occupancy | C16: =Rooms!C16 -> 0.4613 | D16: =Rooms!D16 -> 0.5241 | E16: =Rooms!E16 -> 0.4817 | F16: =Rooms!F16 -> 0.2878 | G16: =Rooms!G16 -> 0.1892 | H16: =Rooms!H16 -> 0.1089 | I16: =Rooms!I16 -> 0.2677 | J16: =Rooms!J16 -> 0.1688 | ... O16: =Rooms!O16 -> 0.25264117
B17: Average Daily Room Only | C17: =Rooms!C17 -> 359.84047 | D17: =Rooms!D17 -> 465.18852 | E17: =Rooms!E17 -> 389.00314 | F17: =Rooms!F17 -> 378.9522 | G17: =Rooms!G17 -> 231.30814 | H17: =Rooms!H17 -> 291.12236 | I17: =Rooms!I17 -> 426.03102 | J17: =Rooms!J17 -> 403.28888 | ... O17: =Rooms!O17 -> 431.01011
B18: Key Indicators 2025
B19: Indicator | C19: January | D19: February | E19: March | F19: April | G19: May | H19: June | I19: July | J19: August | K19: September | L19: October | M19: November | N19: December | O19: TOTAL
B20: Total available Rooms | C20: =Rooms!C20 -> 930 | D20: =Rooms!D20 -> 840 | E20: =Rooms!E20 -> 930 | F20: =Rooms!F20 -> 900 | G20: =Rooms!G20 -> 930 | H20: =Rooms!H20 -> 900 | I20: =Rooms!I20 -> 930 | J20: =Rooms!J20 -> 930 | ... O20: =Rooms!O20 -> 10950
B21: Total Rooms Occupied | C21: =Rooms!C21 -> 454 | D21: =Rooms!D21 -> 479 | E21: =Rooms!E21 -> 519 | F21: =Rooms!F21 -> 239 | G21: =Rooms!G21 -> 114 | H21: =Rooms!H21 -> 102 | I21: =Rooms!I21 -> 274 | J21: =Rooms!J21 -> 220 | ... O21: =Rooms!O21 -> 3179
B22: Total Guests | C22: =Rooms!C22 -> 809 | D22: =Rooms!D22 -> 893 | E22: =Rooms!E22 -> 962 | F22: =Rooms!F22 -> 428 | G22: =Rooms!G22 -> 228 | H22: =Rooms!H22 -> 183 | I22: =Rooms!I22 -> 611 | J22: =Rooms!J22 -> 411 | ... O22: =Rooms!O22 -> 5677
B23: % Occupancy | C23: =Rooms!C23 -> 0.48817204 | D23: =Rooms!D23 -> 0.5702381 | E23: =Rooms!E23 -> 0.55806452 | F23: =Rooms!F23 -> 0.26555556 | G23: =Rooms!G23 -> 0.12258065 | H23: =Rooms!H23 -> 0.11333333 | I23: =Rooms!I23 -> 0.29462366 | J23: =Rooms!J23 -> 0.23655914 | ... O23: =Rooms!O23 -> 0.29031963
B24: Average Daily Room Only | C24: =Rooms!C24 -> 473.50649 | D24: =Rooms!D24 -> 550.00104 | E24: =Rooms!E24 -> 478.48852 | F24: =Rooms!F24 -> 497.89901 | G24: =Rooms!G24 -> 482.76039 | H24: =Rooms!H24 -> 379.47717 | I24: =Rooms!I24 -> 508.05451 | J24: =Rooms!J24 -> 371.59366 | ... O24: =Rooms!O24 -> 484.67682
B25: Key Indicators 2026 (Budget)
B26: Indicator | C26: January | D26: February | E26: March | F26: April | G26: May | H26: June | I26: July | J26: August | K26: September | L26: October | M26: November | N26: December | O26: TOTAL
B27: Total available Rooms | C27: =Rooms!C27 -> 930 | D27: =Rooms!D27 -> 840 | E27: =Rooms!E27 -> 930 | F27: =Rooms!F27 -> 900 | G27: =Rooms!G27 -> 930 | H27: =Rooms!H27 -> 900 | I27: =Rooms!I27 -> 930 | J27: =Rooms!J27 -> 930 | ... O27: =Rooms!O27 -> 10020
B28: Total Rooms Occupied | C28: =Rooms!C28 -> 697.5 | D28: =Rooms!D28 -> 638.4 | E28: =Rooms!E28 -> 607.7 | F28: =Rooms!F28 -> 332 | G28: =Rooms!G28 -> 232.48621 | H28: =Rooms!H28 -> 167.65517 | I28: =Rooms!I28 -> 332.1 | J28: =Rooms!J28 -> 251.32 | ... O28: =Rooms!O28 -> 4363.2889
B29: Total Guests | C29: =Rooms!C29 -> 1255.5 | D29: =Rooms!D29 -> 1149.12 | E29: =Rooms!E29 -> 1093.86 | F29: =Rooms!F29 -> 597.6 | G29: =Rooms!G29 -> 418.47517 | H29: =Rooms!H29 -> 301.77931 | I29: =Rooms!I29 -> 597.78 | J29: =Rooms!J29 -> 452.376 | ... O29: =Rooms!O29 -> 7853.92
B30: % Occupancy | C30: =Rooms!C30 -> 0.75 | D30: =Rooms!D30 -> 0.76 | E30: =Rooms!E30 -> 0.65344086 | F30: =Rooms!F30 -> 0.36888889 | G30: =Rooms!G30 -> 0.24998517 | H30: =Rooms!H30 -> 0.18628352 | I30: =Rooms!I30 -> 0.35709677 | J30: =Rooms!J30 -> 0.27023656 | ... O30: =Rooms!O30 -> 0.43545797
B31: Average Daily Room Only | C31: =Rooms!C31 -> 595.27155 | D31: =Rooms!D31 -> 583.47405 | E31: =Rooms!E31 -> 590.96203 | F31: =Rooms!F31 -> 635.29075 | G31: =Rooms!G31 -> 521.40328 | H31: =Rooms!H31 -> 553.7017 | I31: =Rooms!I31 -> 566.23141 | J31: =Rooms!J31 -> 520.6179 | ... O31: =Rooms!O31 -> 596.88852
B34: Revenue by Month
B35: Label | C35: January | D35: February | E35: March | F35: April | G35: May | H35: June | I35: July | J35: August | K35: September | L35: October | M35: November | N35: December | O35: TOTAL
B36: Revenue 2024 | C36: 40539.559 | D36: 51930.053 | E36: 51479.405 | F36: 31261.324 | G36: 12340.602 | H36: 10377.842 | I36: 27201.505 | J36: 20146.528 | K36: 879.44131 | L36: 0 | M36: 23570.483 | N36: 48192.13 | O36: =SUM(C36:N36) -> 317918.87
B37: Revenue 2025 | C37: 55354.294 | D37: 72196.172 | E37: 70786.323 | F37: 36330.097 | G37: 16129.355 | H37: 13689.425 | I37: 46042.427 | J37: 26588.885 | K37: 6403.05 | L37: 0 | M37: 29454.03 | N37: 55066.23 | O37: =SUM(C37:N37) -> 428040.29
B38: Revenue 2026 Budget | C38: =+'Key Indicators'!C328 -> 113356.58 | D38: =+'Key Indicators'!D328 -> 103751.75 | E38: =+'Key Indicators'!E328 -> 98762.432 | F38: =+'Key Indicators'!F328 -> 53956.109 | G38: =+'Key Indicators'!G328 -> 37783.286 | H38: =+'Key Indicators'!H328 -> 27247.05 | I38: =+'Key Indicators'!I328 -> 53972.361 | J38: =+'Key Indicators'!J328 -> 40844.124 | ... N38: =+'Key Indicators'!N328 -> 99413.724 | O38: =SUM(C38:N38) -> 709114.73
B40: Revenue per Occupied Room 2024 | C40: =+C36/C14 -> 94.497806 | D40: =+D36/D14 -> 113.8817 | E40: =+E36/E14 -> 114.90939 | F40: =+F36/F14 -> 120.70009 | G40: =+G36/G14 -> 70.11706 | H40: =+H36/H14 -> 105.89634 | I40: =+I36/I14 -> 109.24299 | J40: =+J36/J14 -> 128.32183 | ... O40: =+O36/O14 -> 114.60666
B41: Revenue per Occupied Room 2025 | C41: =+C37/C21 -> 121.92576 | D41: =+D37/D21 -> 150.7227 | E41: =+E37/E21 -> 136.38983 | F41: =+F37/F21 -> 152.00877 | G41: =+G37/G21 -> 141.48557 | H41: =+H37/H21 -> 134.21004 | I41: =+I37/I21 -> 168.03805 | J41: =+J37/J21 -> 120.85857 | ... O41: =+O37/O21 -> 134.64621
B42: Revenue per Occupied Room 2026 | C42: =+C38/C28 -> 162.5184 | D42: =+D38/D28 -> 162.5184 | E42: =+E38/E28 -> 162.5184 | F42: =+F38/F28 -> 162.5184 | G42: =+G38/G28 -> 162.5184 | H42: =+H38/H28 -> 162.5184 | I42: =+I38/I28 -> 162.5184 | J42: =+J38/J28 -> 162.5184 | ... O42: =+O38/O28 -> 162.5184 | P42: =+O42-O41 -> 27.872194 | Q42: =+P42/O41 -> 0.20700319
B44: Revenue by Guest 2024 | C44: =+C36/C15 -> 57.017664 | D44: =+D36/D15 -> 62.266251 | E44: =+E36/E15 -> 61.651981 | F44: =+F36/F15 -> 57.46567 | G44: =+G36/G15 -> 39.680394 | H44: =+H36/H15 -> 64.86151 | I44: =+I36/I15 -> 63.406772 | J44: =+J36/J15 -> 64.9888 | ... O44: =+O36/O15 -> 62.631772
B45: Revenue by Guest 2025 | C45: =+C37/C29 -> 44.089441 | D45: =+D37/D29 -> 62.827357 | E45: =+E37/E29 -> 64.712416 | F45: =+F37/F29 -> 60.793335 | G45: =+G37/G29 -> 38.543159 | H45: =+H37/H29 -> 45.36237 | I45: =+I37/I29 -> 77.022361 | J45: =+J37/J29 -> 58.776074 | ... O45: =+O37/O29 -> 54.50021
B46: Revenue by Guest 2026 | C46: =+C38/C29 -> 90.288 | D46: =+D38/D29 -> 90.288 | E46: =+E38/E29 -> 90.288 | F46: =+F38/F29 -> 90.288 | G46: =+G38/G29 -> 90.288 | H46: =+H38/H29 -> 90.288 | I46: =+I38/I29 -> 90.288 | J46: =+J38/J29 -> 90.288 | ... O46: =+O38/O29 -> 90.288
B54: Drivers (Assumptions)
B55: Driver | C55: Definition / Notes | D55: Value / Unit
B56: Driver 1
B57: Driver 2

Sheet Beverage Revenue
A1: ⟵ Back to Summary | C1: Beverage Revenue – Key Indicators & Budget
A11: Key Indicators 2024
A12: Indicator | B12: January | C12: February | D12: March | E12: April | F12: May | G12: June | H12: July | I12: August | J12: September | K12: October | L12: November | M12: December | N12: TOTAL
A13: Total available Rooms | B13: =Rooms!C13 -> 930 | C13: =Rooms!D13 -> 870 | D13: =Rooms!E13 -> 930 | E13: =Rooms!F13 -> 900 | F13: =Rooms!G13 -> 930 | G13: =Rooms!H13 -> 900 | H13: =Rooms!I13 -> 930 | I13: =Rooms!J13 -> 930 | ... N13: =Rooms!O13 -> 10980
A14: Total Rooms Occupied | B14: =Rooms!C14 -> 429 | C14: =Rooms!D14 -> 456 | D14: =Rooms!E14 -> 448 | E14: =Rooms!F14 -> 259 | F14: =Rooms!G14 -> 176 | G14: =Rooms!H14 -> 98 | H14: =Rooms!I14 -> 249 | I14: =Rooms!J14 -> 157 | ... N14: =Rooms!O14 -> 2774
A15: Total Guests | B15: =Rooms!C15 -> 711 | C15: =Rooms!D15 -> 834 | D15: =Rooms!E15 -> 835 | E15: =Rooms!F15 -> 544 | F15: =Rooms!G15 -> 311 | G15: =Rooms!H15 -> 160 | H15: =Rooms!I15 -> 429 | I15: =Rooms!J15 -> 310 | ... N15: =Rooms!O15 -> 5076
A16: % Occupancy | B16: =Rooms!C16 -> 0.4613 | C16: =Rooms!D16 -> 0.5241 | D16: =Rooms!E16 -> 0.4817 | E16: =Rooms!F16 -> 0.2878 | F16: =Rooms!G16 -> 0.1892 | G16: =Rooms!H16 -> 0.1089 | H16: =Rooms!I16 -> 0.2677 | I16: =Rooms!J16 -> 0.1688 | ... N16: =Rooms!O16 -> 0.25264117
A17: Average Daily Room Only | B17: =Rooms!C17 -> 359.84047 | C17: =Rooms!D17 -> 465.18852 | D17: =Rooms!E17 -> 389.00314 | E17: =Rooms!F17 -> 378.9522 | F17: =Rooms!G17 -> 231.30814 | G17: =Rooms!H17 -> 291.12236 | H17: =Rooms!I17 -> 426.03102 | I17: =Rooms!J17 -> 403.28888 | ... N17: =Rooms!O17 -> 431.01011
A18: Key Indicators 2025
A19: Indicator | B19: January | C19: February | D19: March | E19: April | F19: May | G19: June | H19: July | I19: August | J19: September | K19: October | L19: November | M19: December | N19: TOTAL
A20: Total available Rooms | B20: =Rooms!C20 -> 930 | C20: =Rooms!D20 -> 840 | D20: =Rooms!E20 -> 930 | E20: =Rooms!F20 -> 900 | F20: =Rooms!G20 -> 930 | G20: =Rooms!H20 -> 900 | H20: =Rooms!I20 -> 930 | I20: =Rooms!J20 -> 930 | ... N20: =Rooms!O20 -> 10950
A21: Total Rooms Occupied | B21: =Rooms!C21 -> 454 | C21: =Rooms!D21 -> 479 | D21: =Rooms!E21 -> 519 | E21: =Rooms!F21 -> 239 | F21: =Rooms!G21 -> 114 | G21: =Rooms!H21 -> 102 | H21: =Rooms!I21 -> 274 | I21: =Rooms!J21 -> 220 | ... N21: =Rooms!O21 -> 3179
A22: Total Guests | B22: =Rooms!C22 -> 809 | C22: =Rooms!D22 -> 893 | D22: =Rooms!E22 -> 962 | E22: =Rooms!F22 -> 428 | F22: =Rooms!G22 -> 228 | G22: =Rooms!H22 -> 183 | H22: =Rooms!I22 -> 611 | I22: =Rooms!J22 -> 411 | ... N22: =Rooms!O22 -> 5677
A23: % Occupancy | B23: =Rooms!C23 -> 0.48817204 | C23: =Rooms!D23 -> 0.5702381 | D23: =Rooms!E23 -> 0.55806452 | E23: =Rooms!F23 -> 0.26555556 | F23: =Rooms!G23 -> 0.12258065 | G23: =Rooms!H23 -> 0.11333333 | H23: =Rooms!I23 -> 0.29462366 | I23: =Rooms!J23 -> 0.23655914 | ... N23: =Rooms!O23 -> 0.29031963
A24: Average Daily Room Only | B24: =Rooms!C24 -> 473.50649 | C24: =Rooms!D24 -> 550.00104 | D24: =Rooms!E24 -> 478.48852 | E24: =Rooms!F24 -> 497.89901 | F24: =Rooms!G24 -> 482.76039 | G24: =Rooms!H24 -> 379.47717 | H24: =Rooms!I24 -> 508.05451 | I24: =Rooms!J24 -> 371.59366 | ... N24: =Rooms!O24 -> 484.67682
A25: Key Indicators 2026 (Budget)
A26: Indicator | B26: January | C26: February | D26: March | E26: April | F26: May | G26: June | H26: July | I26: August | J26: September | K26: October | L26: November | M26: December | N26: TOTAL
A27: Total available Rooms | B27: =Rooms!C27 -> 930 | C27: =Rooms!D27 -> 840 | D27: =Rooms!E27 -> 930 | E27: =Rooms!F27 -> 900 | F27: =Rooms!G27 -> 930 | G27: =Rooms!H27 -> 900 | H27: =Rooms!I27 -> 930 | I27: =Rooms!J27 -> 930 | ... N27: =Rooms!O27 -> 10020
A28: Total Rooms Occupied | B28: =Rooms!C28 -> 697.5 | C28: =Rooms!D28 -> 638.4 | D28: =Rooms!E28 -> 607.7 | E28: =Rooms!F28 -> 332 | F28: =Rooms!G28 -> 232.48621 | G28: =Rooms!H28 -> 167.65517 | H28: =Rooms!I28 -> 332.1 | I28: =Rooms!J28 -> 251.32 | ... N28: =Rooms!O28 -> 4363.2889
A29: Total Guests | B29: =Rooms!C29 -> 1255.5 | C29: =Rooms!D29 -> 1149.12 | D29: =Rooms!E29 -> 1093.86 | E29: =Rooms!F29 -> 597.6 | F29: =Rooms!G29 -> 418.47517 | G29: =Rooms!H29 -> 301.77931 | H29: =Rooms!I29 -> 597.78 | I29: =Rooms!J29 -> 452.376 | ... N29: =Rooms!O29 -> 7853.92
A30: % Occupancy | B30: =Rooms!C30 -> 0.75 | C30: =Rooms!D30 -> 0.76 | D30: =Rooms!E30 -> 0.65344086 | E30: =Rooms!F30 -> 0.36888889 | F30: =Rooms!G30 -> 0.24998517 | G30: =Rooms!H30 -> 0.18628352 | H30: =Rooms!I30 -> 0.35709677 | I30: =Rooms!J30 -> 0.27023656 | ... N30: =Rooms!O30 -> 0.43545797
A31: Average Daily Room Only | B31: =Rooms!C31 -> 595.27155 | C31: =Rooms!D31 -> 583.47405 | D31: =Rooms!E31 -> 590.96203 | E31: =Rooms!F31 -> 635.29075 | F31: =Rooms!G31 -> 521.40328 | G31: =Rooms!H31 -> 553.7017 | H31: =Rooms!I31 -> 566.23141 | I31: =Rooms!J31 -> 520.6179 | ... N31: =Rooms!O31 -> 596.88852
A34: Revenue by Month
A35: Label | B35: January | C35: February | D35: March | E35: April | F35: May | G35: June | H35: July | I35: August | J35: September | K35: October | L35: November | M35: December | N35: TOTAL
A36: Revenue 2024 | B36: 13382.938 | C36: 18605.558 | D36: 15732.728 | E36: 9825.4252 | F36: 6010.1144 | G36: 1924.1243 | H36: 5599.9203 | I36: 5103.7981 | J36: 221.69825 | K36: 0 | L36: 7805.9442 | M36: 11187.446 | N36: =SUM(B36:M36) -> 95399.695
A37: Revenue 2025 | B37: 25207.195 | C37: 20197.816 | D37: 24274.211 | E37: 12316.933 | F37: 6154.7577 | G37: 4103.4464 | H37: 10937.432 | I37: 10347.794 | J37: 1600.7625 | K37: 0 | L37: 7363.5075 | M37: 13766.558 | N37: =SUM(B37:M37) -> 136270.41
A38: Revenue 2026 Budget | B38: =+'Key Indicators'!C329 -> 38541.239 | C38: =+'Key Indicators'!D329 -> 35275.594 | D38: =+'Key Indicators'!E329 -> 33579.227 | E38: =+'Key Indicators'!F329 -> 18345.077 | F38: =+'Key Indicators'!G329 -> 12846.317 | G38: =+'Key Indicators'!H329 -> 9263.9971 | H38: =+'Key Indicators'!I329 -> 18350.603 | I38: =+'Key Indicators'!J329 -> 13887.002 | ... M38: =+'Key Indicators'!N329 -> 33800.666 | N38: =SUM(B38:M38) -> 241099.01
A40: Revenue per Occupied Room 2024 | B40: =+B36/B14 -> 31.19566 | C40: =+C36/C14 -> 40.801662 | D40: =+D36/D14 -> 35.117696 | E40: =+E36/E14 -> 37.936005 | F40: =+F36/F14 -> 34.148377 | G40: =+G36/G14 -> 19.633921 | H40: =+H36/H14 -> 22.48964 | I40: =+I36/I14 -> 32.508268 | ... N40: =+N36/N14 -> 34.390661
A41: Revenue per Occupied Room 2025 | B41: =+B37/B21 -> 55.522455 | C41: =+C37/C21 -> 42.166631 | D41: =+D37/D21 -> 46.77112 | E41: =+E37/E21 -> 51.535284 | F41: =+F37/F21 -> 53.989103 | G41: =+G37/G21 -> 40.229866 | H41: =+H37/H21 -> 39.917636 | I41: =+I37/I21 -> 47.035428 | ... N41: =+N37/N21 -> 42.865811
A42: Revenue per Occupied Room 2026 | B42: =+B38/B28 -> 55.256256 | C42: =+C38/C28 -> 55.256256 | D42: =+D38/D28 -> 55.256256 | E42: =+E38/E28 -> 55.256256 | F42: =+F38/F28 -> 55.256256 | G42: =+G38/G28 -> 55.256256 | H42: =+H38/H28 -> 55.256256 | I42: =+I38/I28 -> 55.256256 | ... N42: =+N38/N28 -> 55.256256
A44: Revenue by Guest 2024 | B44: =+B36/B15 -> 18.822698 | C44: =+C36/C15 -> 22.308822 | D44: =+D36/D15 -> 18.84159 | E44: =+E36/E15 -> 18.061443 | F44: =+F36/F15 -> 19.325127 | G44: =+G36/G15 -> 12.025777 | H44: =+H36/H15 -> 13.053427 | I44: =+I36/I15 -> 16.463865 | ... N44: =+N36/N15 -> 18.794266
A45: Revenue by Guest 2025 | B45: =+B37/B22 -> 31.158461 | C45: =+C37/C22 -> 22.617935 | D45: =+D37/D22 -> 25.233068 | E45: =+E37/E22 -> 28.777881 | F45: =+F37/F22 -> 26.994551 | G45: =+G37/G22 -> 22.423204 | H45: =+H37/H22 -> 17.900871 | I45: =+I37/I22 -> 25.177115 | ... N45: =+N37/N22 -> 24.003948
A46: Revenue by Guest 2026 | B46: =+B38/B29 -> 30.69792 | C46: =+C38/C29 -> 30.69792 | D46: =+D38/D29 -> 30.69792 | E46: =+E38/E29 -> 30.69792 | F46: =+F38/F29 -> 30.69792 | G46: =+G38/G29 -> 30.69792 | H46: =+H38/H29 -> 30.69792 | I46: =+I38/I29 -> 30.69792 | ... N46: =+N38/N29 -> 30.69792
A48: % sobre Food 2024 | B48: =+B36/'Food Revenue'!C36 -> 0.33012047 | C48: =+C36/'Food Revenue'!D36 -> 0.35828112 | D48: =+D36/'Food Revenue'!E36 -> 0.30561208 | E48: =+E36/'Food Revenue'!F36 -> 0.31429971 | F48: =+F36/'Food Revenue'!G36 -> 0.48701952 | G48: =+G36/'Food Revenue'!H36 -> 0.18540698 | H48: =+H36/'Food Revenue'!I36 -> 0.20586803 | I48: =+I36/'Food Revenue'!J36 -> 0.25333388 | ... N48: =+N36/'Food Revenue'!O36 -> 0.3000756
A49: % sobre Food 2025 | B49: =+B37/'Food Revenue'!C37 -> 0.45537921 | C49: =+C37/'Food Revenue'!D37 -> 0.27976298 | D49: =+D37/'Food Revenue'!E37 -> 0.34292233 | E49: =+E37/'Food Revenue'!F37 -> 0.33902835 | F49: =+F37/'Food Revenue'!G37 -> 0.38158734 | G49: =+G37/'Food Revenue'!H37 -> 0.29975302 | H49: =+H37/'Food Revenue'!I37 -> 0.23755117 | I49: =+I37/'Food Revenue'!J37 -> 0.38917743 | ... N49: =+N37/'Food Revenue'!O37 -> 0.31835885
A50: % sobre Food 2026 | B50: =+B38/'Food Revenue'!C38 -> 0.34 | C50: =+C38/'Food Revenue'!D38 -> 0.34 | D50: =+D38/'Food Revenue'!E38 -> 0.34 | E50: =+E38/'Food Revenue'!F38 -> 0.34 | F50: =+F38/'Food Revenue'!G38 -> 0.34 | G50: =+G38/'Food Revenue'!H38 -> 0.34 | H50: =+H38/'Food Revenue'!I38 -> 0.34 | I50: =+I38/'Food Revenue'!J38 -> 0.34 | ... N50: =+N38/'Food Revenue'!O38 -> 0.34
N52: GO BACK

Sheet F&B Mis Revenue
A1: ⟵ Back to Summary | C1: Miscellaneous Revnue F&B – Key Indicators & Budget
A11: Key Indicators 2024
A12: Indicator | B12: January | C12: February | D12: March | E12: April | F12: May | G12: June | H12: July | I12: August | J12: September | K12: October | L12: November | M12: December | N12: TOTAL
A13: Total available Rooms | B13: =Rooms!C13 -> 930 | C13: =Rooms!D13 -> 870 | D13: =Rooms!E13 -> 930 | E13: =Rooms!F13 -> 900 | F13: =Rooms!G13 -> 930 | G13: =Rooms!H13 -> 900 | H13: =Rooms!I13 -> 930 | I13: =Rooms!J13 -> 930 | ... N13: =Rooms!O13 -> 10980
A14: Total Rooms Occupied | B14: =Rooms!C14 -> 429 | C14: =Rooms!D14 -> 456 | D14: =Rooms!E14 -> 448 | E14: =Rooms!F14 -> 259 | F14: =Rooms!G14 -> 176 | G14: =Rooms!H14 -> 98 | H14: =Rooms!I14 -> 249 | I14: =Rooms!J14 -> 157 | ... N14: =Rooms!O14 -> 2774
A15: Total Guests | B15: =Rooms!C15 -> 711 | C15: =Rooms!D15 -> 834 | D15: =Rooms!E15 -> 835 | E15: =Rooms!F15 -> 544 | F15: =Rooms!G15 -> 311 | G15: =Rooms!H15 -> 160 | H15: =Rooms!I15 -> 429 | I15: =Rooms!J15 -> 310 | ... N15: =Rooms!O15 -> 5076
A16: % Occupancy | B16: =Rooms!C16 -> 0.4613 | C16: =Rooms!D16 -> 0.5241 | D16: =Rooms!E16 -> 0.4817 | E16: =Rooms!F16 -> 0.2878 | F16: =Rooms!G16 -> 0.1892 | G16: =Rooms!H16 -> 0.1089 | H16: =Rooms!I16 -> 0.2677 | I16: =Rooms!J16 -> 0.1688 | ... N16: =Rooms!O16 -> 0.25264117
A17: Average Daily Room Only | B17: =Rooms!C17 -> 359.84047 | C17: =Rooms!D17 -> 465.18852 | D17: =Rooms!E17 -> 389.00314 | E17: =Rooms!F17 -> 378.9522 | F17: =Rooms!G17 -> 231.30814 | G17: =Rooms!H17 -> 291.12236 | H17: =Rooms!I17 -> 426.03102 | I17: =Rooms!J17 -> 403.28888 | ... N17: =Rooms!O17 -> 431.01011
A18: Key Indicators 2025
A19: Indicator | B19: January | C19: February | D19: March | E19: April | F19: May | G19: June | H19: July | I19: August | J19: September | K19: October | L19: November | M19: December | N19: TOTAL
A20: Total available Rooms | B20: =Rooms!C20 -> 930 | C20: =Rooms!D20 -> 840 | D20: =Rooms!E20 -> 930 | E20: =Rooms!F20 -> 900 | F20: =Rooms!G20 -> 930 | G20: =Rooms!H20 -> 900 | H20: =Rooms!I20 -> 930 | I20: =Rooms!J20 -> 930 | ... N20: =Rooms!O20 -> 10950
A21: Total Rooms Occupied | B21: =Rooms!C21 -> 454 | C21: =Rooms!D21 -> 479 | D21: =Rooms!E21 -> 519 | E21: =Rooms!F21 -> 239 | F21: =Rooms!G21 -> 114 | G21: =Rooms!H21 -> 102 | H21: =Rooms!I21 -> 274 | I21: =Rooms!J21 -> 220 | ... N21: =Rooms!O21 -> 3179
A22: Total Guests | B22: =Rooms!C22 -> 809 | C22: =Rooms!D22 -> 893 | D22: =Rooms!E22 -> 962 | E22: =Rooms!F22 -> 428 | F22: =Rooms!G22 -> 228 | G22: =Rooms!H22 -> 183 | H22: =Rooms!I22 -> 611 | I22: =Rooms!J22 -> 411 | ... N22: =Rooms!O22 -> 5677
A23: % Occupancy | B23: =Rooms!C23 -> 0.48817204 | C23: =Rooms!D23 -> 0.5702381 | D23: =Rooms!E23 -> 0.55806452 | E23: =Rooms!F23 -> 0.26555556 | F23: =Rooms!G23 -> 0.12258065 | G23: =Rooms!H23 -> 0.11333333 | H23: =Rooms!I23 -> 0.29462366 | I23: =Rooms!J23 -> 0.23655914 | ... N23: =Rooms!O23 -> 0.29031963
A24: Average Daily Room Only | B24: =Rooms!C24 -> 473.50649 | C24: =Rooms!D24 -> 550.00104 | D24: =Rooms!E24 -> 478.48852 | E24: =Rooms!F24 -> 497.89901 | F24: =Rooms!G24 -> 482.76039 | G24: =Rooms!H24 -> 379.47717 | H24: =Rooms!I24 -> 508.05451 | I24: =Rooms!J24 -> 371.59366 | ... N24: =Rooms!O24 -> 484.67682
A25: Key Indicators 2026 (Budget)
A26: Indicator | B26: January | C26: February | D26: March | E26: April | F26: May | G26: June | H26: July | I26: August | J26: September | K26: October | L26: November | M26: December | N26: TOTAL
A27: Total available Rooms | B27: =Rooms!C27 -> 930 | C27: =Rooms!D27 -> 840 | D27: =Rooms!E27 -> 930 | E27: =Rooms!F27 -> 900 | F27: =Rooms!G27 -> 930 | G27: =Rooms!H27 -> 900 | H27: =Rooms!I27 -> 930 | I27: =Rooms!J27 -> 930 | ... N27: =Rooms!O27 -> 10020
A28: Total Rooms Occupied | B28: =Rooms!C28 -> 697.5 | C28: =Rooms!D28 -> 638.4 | D28: =Rooms!E28 -> 607.7 | E28: =Rooms!F28 -> 332 | F28: =Rooms!G28 -> 232.48621 | G28: =Rooms!H28 -> 167.65517 | H28: =Rooms!I28 -> 332.1 | I28: =Rooms!J28 -> 251.32 | ... N28: =Rooms!O28 -> 4363.2889
A29: Total Guests | B29: =Rooms!C29 -> 1255.5 | C29: =Rooms!D29 -> 1149.12 | D29: =Rooms!E29 -> 1093.86 | E29: =Rooms!F29 -> 597.6 | F29: =Rooms!G29 -> 418.47517 | G29: =Rooms!H29 -> 301.77931 | H29: =Rooms!I29 -> 597.78 | I29: =Rooms!J29 -> 452.376 | ... N29: =Rooms!O29 -> 7853.92
A30: % Occupancy | B30: =Rooms!C30 -> 0.75 | C30: =Rooms!D30 -> 0.76 | D30: =Rooms!E30 -> 0.65344086 | E30: =Rooms!F30 -> 0.36888889 | F30: =Rooms!G30 -> 0.24998517 | G30: =Rooms!H30 -> 0.18628352 | H30: =Rooms!I30 -> 0.35709677 | I30: =Rooms!J30 -> 0.27023656 | ... N30: =Rooms!O30 -> 0.43545797
A31: Average Daily Room Only | B31: =Rooms!C31 -> 595.27155 | C31: =Rooms!D31 -> 583.47405 | D31: =Rooms!E31 -> 590.96203 | E31: =Rooms!F31 -> 635.29075 | F31: =Rooms!G31 -> 521.40328 | G31: =Rooms!H31 -> 553.7017 | H31: =Rooms!I31 -> 566.23141 | I31: =Rooms!J31 -> 520.6179 | ... N31: =Rooms!O31 -> 596.88852
A34: Revenue by Month
A35: Label | B35: January | C35: February | D35: March | E35: April | F35: May | G35: June | H35: July | I35: August | J35: September | K35: October | L35: November | M35: December | N35: TOTAL
A36: Revenue 2024 | B36: 0 | C36: 0 | D36: 0 | E36: 0 | F36: 0 | G36: 0 | H36: 0 | I36: 0 | J36: 0 | K36: 0 | L36: 0 | M36: 0 | N36: =SUM(B36:M36) -> 0
A37: Revenue 2025 | B37: 0 | C37: 0 | D37: 0 | E37: 0 | F37: 0 | G37: 0 | H37: 33694.582 | I37: 28.455862 | N37: =SUM(B37:M37) -> 33723.037
A38: Revenue 2026 Budget | B38: 0 | C38: 0 | D38: 0 | E38: 0 | F38: 0 | G38: 0 | H38: 0 | I38: 0 | J38: 0 | K38: 0 | L38: 0 | M38: 0 | N38: =SUM(B38:M38) -> 0
A41: Drivers (Assumptions)
A42: Driver | B42: Definition / Notes | C42: Value / Unit
A43: Driver 1
A44: Driver 2

Sheet Spa Revenue
A1: ⟵ Back to Summary | C1: Spa Revenue – Key Indicators & Budget
A11: Key Indicators 2024
A12: Indicator | B12: January | C12: February | D12: March | E12: April | F12: May | G12: June | H12: July | I12: August | J12: September | K12: October | L12: November | M12: December | N12: TOTAL
A13: Total available Rooms | B13: =Rooms!C13 -> 930 | C13: =Rooms!D13 -> 870 | D13: =Rooms!E13 -> 930 | E13: =Rooms!F13 -> 900 | F13: =Rooms!G13 -> 930 | G13: =Rooms!H13 -> 900 | H13: =Rooms!I13 -> 930 | I13: =Rooms!J13 -> 930 | ... N13: =Rooms!O13 -> 10980
A14: Total Rooms Occupied | B14: =Rooms!C14 -> 429 | C14: =Rooms!D14 -> 456 | D14: =Rooms!E14 -> 448 | E14: =Rooms!F14 -> 259 | F14: =Rooms!G14 -> 176 | G14: =Rooms!H14 -> 98 | H14: =Rooms!I14 -> 249 | I14: =Rooms!J14 -> 157 | ... N14: =Rooms!O14 -> 2774
A15: Total Guests | B15: =Rooms!C15 -> 711 | C15: =Rooms!D15 -> 834 | D15: =Rooms!E15 -> 835 | E15: =Rooms!F15 -> 544 | F15: =Rooms!G15 -> 311 | G15: =Rooms!H15 -> 160 | H15: =Rooms!I15 -> 429 | I15: =Rooms!J15 -> 310 | ... N15: =Rooms!O15 -> 5076
A16: % Occupancy | B16: =Rooms!C16 -> 0.4613 | C16: =Rooms!D16 -> 0.5241 | D16: =Rooms!E16 -> 0.4817 | E16: =Rooms!F16 -> 0.2878 | F16: =Rooms!G16 -> 0.1892 | G16: =Rooms!H16 -> 0.1089 | H16: =Rooms!I16 -> 0.2677 | I16: =Rooms!J16 -> 0.1688 | ... N16: =Rooms!O16 -> 0.25264117
A17: Average Daily Room Only | B17: =Rooms!C17 -> 359.84047 | C17: =Rooms!D17 -> 465.18852 | D17: =Rooms!E17 -> 389.00314 | E17: =Rooms!F17 -> 378.9522 | F17: =Rooms!G17 -> 231.30814 | G17: =Rooms!H17 -> 291.12236 | H17: =Rooms!I17 -> 426.03102 | I17: =Rooms!J17 -> 403.28888 | ... N17: =Rooms!O17 -> 431.01011
A18: Key Indicators 2025
A19: Indicator | B19: January | C19: February | D19: March | E19: April | F19: May | G19: June | H19: July | I19: August | J19: September | K19: October | L19: November | M19: December | N19: TOTAL
A20: Total available Rooms | B20: =Rooms!C20 -> 930 | C20: =Rooms!D20 -> 840 | D20: =Rooms!E20 -> 930 | E20: =Rooms!F20 -> 900 | F20: =Rooms!G20 -> 930 | G20: =Rooms!H20 -> 900 | H20: =Rooms!I20 -> 930 | I20: =Rooms!J20 -> 930 | ... N20: =Rooms!O20 -> 10950
A21: Total Rooms Occupied | B21: =Rooms!C21 -> 454 | C21: =Rooms!D21 -> 479 | D21: =Rooms!E21 -> 519 | E21: =Rooms!F21 -> 239 | F21: =Rooms!G21 -> 114 | G21: =Rooms!H21 -> 102 | H21: =Rooms!I21 -> 274 | I21: =Rooms!J21 -> 220 | ... N21: =Rooms!O21 -> 3179
A22: Total Guests | B22: =Rooms!C22 -> 809 | C22: =Rooms!D22 -> 893 | D22: =Rooms!E22 -> 962 | E22: =Rooms!F22 -> 428 | F22: =Rooms!G22 -> 228 | G22: =Rooms!H22 -> 183 | H22: =Rooms!I22 -> 611 | I22: =Rooms!J22 -> 411 | ... N22: =Rooms!O22 -> 5677
A23: % Occupancy | B23: =Rooms!C23 -> 0.48817204 | C23: =Rooms!D23 -> 0.5702381 | D23: =Rooms!E23 -> 0.55806452 | E23: =Rooms!F23 -> 0.26555556 | F23: =Rooms!G23 -> 0.12258065 | G23: =Rooms!H23 -> 0.11333333 | H23: =Rooms!I23 -> 0.29462366 | I23: =Rooms!J23 -> 0.23655914 | ... N23: =Rooms!O23 -> 0.29031963
A24: Average Daily Room Only | B24: =Rooms!C24 -> 473.50649 | C24: =Rooms!D24 -> 550.00104 | D24: =Rooms!E24 -> 478.48852 | E24: =Rooms!F24 -> 497.89901 | F24: =Rooms!G24 -> 482.76039 | G24: =Rooms!H24 -> 379.47717 | H24: =Rooms!I24 -> 508.05451 | I24: =Rooms!J24 -> 371.59366 | ... N24: =Rooms!O24 -> 484.67682
A25: Key Indicators 2026 (Budget)
A26: Indicator | B26: January | C26: February | D26: March | E26: April | F26: May | G26: June | H26: July | I26: August | J26: September | K26: October | L26: November | M26: December | N26: TOTAL
A27: Total available Rooms | B27: =Rooms!C27 -> 930 | C27: =Rooms!D27 -> 840 | D27: =Rooms!E27 -> 930 | E27: =Rooms!F27 -> 900 | F27: =Rooms!G27 -> 930 | G27: =Rooms!H27 -> 900 | H27: =Rooms!I27 -> 930 | I27: =Rooms!J27 -> 930 | ... N27: =Rooms!O27 -> 10020
A28: Total Rooms Occupied | B28: =Rooms!C28 -> 697.5 | C28: =Rooms!D28 -> 638.4 | D28: =Rooms!E28 -> 607.7 | E28: =Rooms!F28 -> 332 | F28: =Rooms!G28 -> 232.48621 | G28: =Rooms!H28 -> 167.65517 | H28: =Rooms!I28 -> 332.1 | I28: =Rooms!J28 -> 251.32 | ... N28: =Rooms!O28 -> 4363.2889
A29: Total Guests | B29: =Rooms!C29 -> 1255.5 | C29: =Rooms!D29 -> 1149.12 | D29: =Rooms!E29 -> 1093.86 | E29: =Rooms!F29 -> 597.6 | F29: =Rooms!G29 -> 418.47517 | G29: =Rooms!H29 -> 301.77931 | H29: =Rooms!I29 -> 597.78 | I29: =Rooms!J29 -> 452.376 | ... N29: =Rooms!O29 -> 7853.92
A30: % Occupancy | B30: =Rooms!C30 -> 0.75 | C30: =Rooms!D30 -> 0.76 | D30: =Rooms!E30 -> 0.65344086 | E30: =Rooms!F30 -> 0.36888889 | F30: =Rooms!G30 -> 0.24998517 | G30: =Rooms!H30 -> 0.18628352 | H30: =Rooms!I30 -> 0.35709677 | I30: =Rooms!J30 -> 0.27023656 | ... N30: =Rooms!O30 -> 0.43545797
A31: Average Daily Room Only | B31: =Rooms!C31 -> 595.27155 | C31: =Rooms!D31 -> 583.47405 | D31: =Rooms!E31 -> 590.96203 | E31: =Rooms!F31 -> 635.29075 | F31: =Rooms!G31 -> 521.40328 | G31: =Rooms!H31 -> 553.7017 | H31: =Rooms!I31 -> 566.23141 | I31: =Rooms!J31 -> 520.6179 | ... N31: =Rooms!O31 -> 596.88852
A34: Revenue by Month
A35: Label | B35: January | C35: February | D35: March | E35: April | F35: May | G35: June | H35: July | I35: August | J35: September | K35: October | L35: November | M35: December | N35: TOTAL
A36: Revenue 2024 | B36: 2609.9181 | C36: 2686.4514 | D36: 2436.6407 | E36: 2246.1571 | F36: 1706.7846 | G36: 829.79373 | H36: 780.02352 | I36: 1309.8757 | J36: 0 | K36: 0 | L36: 690.99205 | M36: 2891.0677 | N36: =SUM(B36:M36) -> 18187.705
A37: Revenue 2025 | B37: 4663.1676 | C37: 2486.391 | D37: 3391.2718 | E37: 1621.2288 | F37: 1606.5792 | G37: 926.92807 | H37: 2384.8766 | I37: 1345.0302 | J37: 4500 | K37: 0 | L37: 3375 | M37: 6200 | N37: =SUM(B37:M37) -> 32500.473
A38: Revenue 2026 Budget | B38: =+'Key Indicators'!C331 -> 5812.5 | C38: =+'Key Indicators'!D331 -> 5250 | D38: =+'Key Indicators'!E331 -> 5812.5 | E38: =+'Key Indicators'!F331 -> 5625 | F38: =+'Key Indicators'!G331 -> 5812.5 | G38: =+'Key Indicators'!H331 -> 5625 | H38: =+'Key Indicators'!I331 -> 5812.5 | I38: =+'Key Indicators'!J331 -> 5812.5 | ... M38: =+'Key Indicators'!N331 -> 5812.5 | N38: =SUM(B38:M38) -> 62625
A40: Revenue per Occupied Room 2024 | B40: =+B36/B14 -> 6.0837252 | C40: =+C36/C14 -> 5.8913409 | D40: =+D36/D14 -> 5.4389302 | E40: =+E36/E14 -> 8.6724212 | F40: =+F36/F14 -> 9.69764 | G40: =+G36/G14 -> 8.467283 | H40: =+H36/H14 -> 3.1326246 | I40: =+I36/I14 -> 8.3431575 | ... N40: =+N36/N14 -> 6.5564905
A41: Revenue per Occupied Room 2025 | B41: =+B37/B21 -> 10.271294 | C41: =+C37/C21 -> 5.1907954 | D41: =+D37/D21 -> 6.5342423 | E41: =+E37/E21 -> 6.7833843 | F41: =+F37/F21 -> 14.0928 | G41: =+G37/G21 -> 9.0875301 | H41: =+H37/H21 -> 8.7039291 | I41: =+I37/I21 -> 6.1137736 | ... N41: =+N37/N21 -> 10.22349
A42: Revenue per Occupied Room 2026
A44: Revenue by Guest 2024 | B44: =+B36/B15 -> 3.6707709 | C44: =+C36/C15 -> 3.2211648 | D44: =+D36/D15 -> 2.9181326 | E44: =+E36/E15 -> 4.1289652 | F44: =+F36/F15 -> 5.4880535 | G44: =+G36/G15 -> 5.1862108 | H44: =+H36/H15 -> 1.8182366 | I44: =+I36/I15 -> 4.2254056 | ... N44: =+N36/N15 -> 3.5830782
A45: Revenue by Guest 2025 | B45: =+B37/B29 -> 3.7141916 | C45: =+C37/C29 -> 2.1637348 | D45: =+D37/D29 -> 3.1002795 | E45: =+E37/E29 -> 2.7128997 | F45: =+F37/F29 -> 3.8391266 | G45: =+G37/G29 -> 3.0715428 | H45: =+H37/H29 -> 3.9895556 | I45: =+I37/I29 -> 2.9732572 | ... N45: =+N37/N29 -> 4.1381213

Sheet Retail Gift Shop
A1: ⟵ Back to Summary | C1: Retail Gift Shop – Key Indicators & Budget
A11: Key Indicators 2024
A12: Indicator | B12: January | C12: February | D12: March | E12: April | F12: May | G12: June | H12: July | I12: August | J12: September | K12: October | L12: November | M12: December | N12: TOTAL
A13: Total available Rooms | B13: =Rooms!C13 -> 930 | C13: =Rooms!D13 -> 870 | D13: =Rooms!E13 -> 930 | E13: =Rooms!F13 -> 900 | F13: =Rooms!G13 -> 930 | G13: =Rooms!H13 -> 900 | H13: =Rooms!I13 -> 930 | I13: =Rooms!J13 -> 930 | ... N13: =Rooms!O13 -> 10980
A14: Total Rooms Occupied | B14: =Rooms!C14 -> 429 | C14: =Rooms!D14 -> 456 | D14: =Rooms!E14 -> 448 | E14: =Rooms!F14 -> 259 | F14: =Rooms!G14 -> 176 | G14: =Rooms!H14 -> 98 | H14: =Rooms!I14 -> 249 | I14: =Rooms!J14 -> 157 | ... N14: =Rooms!O14 -> 2774
A15: Total Guests | B15: =Rooms!C15 -> 711 | C15: =Rooms!D15 -> 834 | D15: =Rooms!E15 -> 835 | E15: =Rooms!F15 -> 544 | F15: =Rooms!G15 -> 311 | G15: =Rooms!H15 -> 160 | H15: =Rooms!I15 -> 429 | I15: =Rooms!J15 -> 310 | ... N15: =Rooms!O15 -> 5076
A16: % Occupancy | B16: =Rooms!C16 -> 0.4613 | C16: =Rooms!D16 -> 0.5241 | D16: =Rooms!E16 -> 0.4817 | E16: =Rooms!F16 -> 0.2878 | F16: =Rooms!G16 -> 0.1892 | G16: =Rooms!H16 -> 0.1089 | H16: =Rooms!I16 -> 0.2677 | I16: =Rooms!J16 -> 0.1688 | ... N16: =Rooms!O16 -> 0.25264117
A17: Average Daily Room Only | B17: =Rooms!C17 -> 359.84047 | C17: =Rooms!D17 -> 465.18852 | D17: =Rooms!E17 -> 389.00314 | E17: =Rooms!F17 -> 378.9522 | F17: =Rooms!G17 -> 231.30814 | G17: =Rooms!H17 -> 291.12236 | H17: =Rooms!I17 -> 426.03102 | I17: =Rooms!J17 -> 403.28888 | ... N17: =Rooms!O17 -> 431.01011
A18: Key Indicators 2025
A19: Indicator | B19: January | C19: February | D19: March | E19: April | F19: May | G19: June | H19: July | I19: August | J19: September | K19: October | L19: November | M19: December | N19: TOTAL
A20: Total available Rooms | B20: =Rooms!C20 -> 930 | C20: =Rooms!D20 -> 840 | D20: =Rooms!E20 -> 930 | E20: =Rooms!F20 -> 900 | F20: =Rooms!G20 -> 930 | G20: =Rooms!H20 -> 900 | H20: =Rooms!I20 -> 930 | I20: =Rooms!J20 -> 930 | ... N20: =Rooms!O20 -> 10950
A21: Total Rooms Occupied | B21: =Rooms!C21 -> 454 | C21: =Rooms!D21 -> 479 | D21: =Rooms!E21 -> 519 | E21: =Rooms!F21 -> 239 | F21: =Rooms!G21 -> 114 | G21: =Rooms!H21 -> 102 | H21: =Rooms!I21 -> 274 | I21: =Rooms!J21 -> 220 | ... N21: =Rooms!O21 -> 3179
A22: Total Guests | B22: =Rooms!C22 -> 809 | C22: =Rooms!D22 -> 893 | D22: =Rooms!E22 -> 962 | E22: =Rooms!F22 -> 428 | F22: =Rooms!G22 -> 228 | G22: =Rooms!H22 -> 183 | H22: =Rooms!I22 -> 611 | I22: =Rooms!J22 -> 411 | ... N22: =Rooms!O22 -> 5677
A23: % Occupancy | B23: =Rooms!C23 -> 0.48817204 | C23: =Rooms!D23 -> 0.5702381 | D23: =Rooms!E23 -> 0.55806452 | E23: =Rooms!F23 -> 0.26555556 | F23: =Rooms!G23 -> 0.12258065 | G23: =Rooms!H23 -> 0.11333333 | H23: =Rooms!I23 -> 0.29462366 | I23: =Rooms!J23 -> 0.23655914 | ... N23: =Rooms!O23 -> 0.29031963
A24: Average Daily Room Only | B24: =Rooms!C24 -> 473.50649 | C24: =Rooms!D24 -> 550.00104 | D24: =Rooms!E24 -> 478.48852 | E24: =Rooms!F24 -> 497.89901 | F24: =Rooms!G24 -> 482.76039 | G24: =Rooms!H24 -> 379.47717 | H24: =Rooms!I24 -> 508.05451 | I24: =Rooms!J24 -> 371.59366 | ... N24: =Rooms!O24 -> 484.67682
A25: Key Indicators 2026 (Budget)
A26: Indicator | B26: January | C26: February | D26: March | E26: April | F26: May | G26: June | H26: July | I26: August | J26: September | K26: October | L26: November | M26: December | N26: TOTAL
A27: Total available Rooms | B27: =Rooms!C27 -> 930 | C27: =Rooms!D27 -> 840 | D27: =Rooms!E27 -> 930 | E27: =Rooms!F27 -> 900 | F27: =Rooms!G27 -> 930 | G27: =Rooms!H27 -> 900 | H27: =Rooms!I27 -> 930 | I27: =Rooms!J27 -> 930 | ... N27: =Rooms!O27 -> 10020
A28: Total Rooms Occupied | B28: =Rooms!C28 -> 697.5 | C28: =Rooms!D28 -> 638.4 | D28: =Rooms!E28 -> 607.7 | E28: =Rooms!F28 -> 332 | F28: =Rooms!G28 -> 232.48621 | G28: =Rooms!H28 -> 167.65517 | H28: =Rooms!I28 -> 332.1 | I28: =Rooms!J28 -> 251.32 | ... N28: =Rooms!O28 -> 4363.2889
A29: Total Guests | B29: =Rooms!C29 -> 1255.5 | C29: =Rooms!D29 -> 1149.12 | D29: =Rooms!E29 -> 1093.86 | E29: =Rooms!F29 -> 597.6 | F29: =Rooms!G29 -> 418.47517 | G29: =Rooms!H29 -> 301.77931 | H29: =Rooms!I29 -> 597.78 | I29: =Rooms!J29 -> 452.376 | ... N29: =Rooms!O29 -> 7853.92
A30: % Occupancy | B30: =Rooms!C30 -> 0.75 | C30: =Rooms!D30 -> 0.76 | D30: =Rooms!E30 -> 0.65344086 | E30: =Rooms!F30 -> 0.36888889 | F30: =Rooms!G30 -> 0.24998517 | G30: =Rooms!H30 -> 0.18628352 | H30: =Rooms!I30 -> 0.35709677 | I30: =Rooms!J30 -> 0.27023656 | ... N30: =Rooms!O30 -> 0.43545797
A31: Average Daily Room Only | B31: =Rooms!C31 -> 595.27155 | C31: =Rooms!D31 -> 583.47405 | D31: =Rooms!E31 -> 590.96203 | E31: =Rooms!F31 -> 635.29075 | F31: =Rooms!G31 -> 521.40328 | G31: =Rooms!H31 -> 553.7017 | H31: =Rooms!I31 -> 566.23141 | I31: =Rooms!J31 -> 520.6179 | ... N31: =Rooms!O31 -> 596.88852
A34: Revenue by Month
A35: Label | B35: January | C35: February | D35: March | E35: April | F35: May | G35: June | H35: July | I35: August | J35: September | K35: October | L35: November | M35: December | N35: TOTAL
A36: Revenue 2024 | B36: 778.5 | C36: 778.5 | D36: 778.5 | E36: 778.5 | F36: 778.5 | G36: 778.5 | H36: 778.5 | I36: 778.5 | J36: 778.5 | K36: 778.5 | L36: 778.5 | M36: 778.5 | N36: =SUM(B36:M36) -> 9342
A37: Revenue 2025 | B37: 2988.2954 | C37: 2207.0827 | D37: 3171.7132 | E37: 2096.9719 | F37: 814.49086 | G37: 645.62889 | H37: 2120.9385 | I37: 1361.6524 | J37: 144 | K37: 0 | L37: 745.2 | M37: 1874.8 | N37: =SUM(B37:M37) -> 18170.774
A38: Revenue 2026 Budget | B38: =+'Key Indicators'!C332 -> 4982.4229 | C38: =+'Key Indicators'!D332 -> 4469.878 | D38: =+'Key Indicators'!E332 -> 4309.5315 | E38: =+'Key Indicators'!F332 -> 2530.9984 | F38: =+'Key Indicators'!G332 -> 1454.6288 | G38: =+'Key Indicators'!H332 -> 1113.9714 | H38: =+'Key Indicators'!I332 -> 2256.5454 | I38: =+'Key Indicators'!J332 -> 1570.1003 | ... M38: =+'Key Indicators'!N332 -> 5386.1832 | N38: =SUM(B38:M38) -> 31252.765
A40: Room Revenues
A42: Revenue 2024 | B42: =+Rooms!C36 -> 154371.56 | C42: =+Rooms!D36 -> 212125.96 | D42: =+Rooms!E36 -> 174273.41 | E42: =+Rooms!F36 -> 98148.619 | F42: =+Rooms!G36 -> 40710.232 | G42: =+Rooms!H36 -> 28529.992 | H42: =+Rooms!I36 -> 106081.72 | I42: =+Rooms!J36 -> 63316.354 | ... N42: =+Rooms!O36 -> 1195622
A43: Revenue 2025 | B43: =+Rooms!C37 -> 214971.95 | C43: =+Rooms!D37 -> 263450.5 | D43: =+Rooms!E37 -> 248335.54 | E43: =+Rooms!F37 -> 118997.86 | F43: =+Rooms!G37 -> 55034.684 | G43: =+Rooms!H37 -> 38706.671 | H43: =+Rooms!I37 -> 139206.94 | I43: =+Rooms!J37 -> 81750.604 | ... N43: =+Rooms!O37 -> 1540787.6
A44: Revenue 2026 Budget | B44: =+Rooms!C38 -> 415201.91 | C44: =+Rooms!D38 -> 372489.83 | D44: =+Rooms!E38 -> 359127.63 | E44: =+Rooms!F38 -> 210916.53 | F44: =+Rooms!G38 -> 121219.07 | G44: =+Rooms!H38 -> 92830.953 | H44: =+Rooms!I38 -> 188045.45 | I44: =+Rooms!J38 -> 130841.69 | ... N44: =+Rooms!O38 -> 2604397.1
A47: Retail Revenue based on Room Revenues
A49: Revenue 2024 | B49: =+B36/B42 -> 0.0050430273 | C49: =+C36/C42 -> 0.0036699892 | D49: =+D36/D42 -> 0.0044671187 | E49: =+E36/E42 -> 0.0079318487 | F49: =+F36/F42 -> 0.019122957 | G49: =+G36/G42 -> 0.027287074 | H49: =+H36/H42 -> 0.0073386816 | I49: =+I36/I42 -> 0.012295402 | J49: =+J36/J42 -> 0.2987359 | L49: =+L36/L42 -> 0.0092278677 | M49: =+M36/M42 -> 0.0033687564 | N49: =+N36/N42 -> 0.0078135061
A50: Revenue 2025 | B50: =+B37/B43 -> 0.013900862 | C50: =+C37/C43 -> 0.0083775991 | D50: =+D37/D43 -> 0.012771886 | E50: =+E37/E43 -> 0.017621929 | F50: =+F37/F43 -> 0.014799592 | G50: =+G37/G43 -> 0.016680042 | H50: =+H37/H43 -> 0.015235868 | I50: =+I37/I43 -> 0.016656175 | J50: =+J37/J43 -> 0.012762722 | L50: =+L37/L43 -> 0.008 | M50: =+M37/M43 -> 0.0073191489 | N50: =+N37/N43 -> 0.011793172
A51: Revenue 2026 Budget | B51: =+B38/B44 -> 0.012 | C51: =+C38/C44 -> 0.012 | D51: =+D38/D44 -> 0.012 | E51: =+E38/E44 -> 0.012 | F51: =+F38/F44 -> 0.012 | G51: =+G38/G44 -> 0.012 | H51: =+H38/H44 -> 0.012 | I51: =+I38/I44 -> 0.012 | J51: =+J38/J44 -> 0.012 | L51: =+L38/L44 -> 0.012 | M51: =+M38/M44 -> 0.012 | N51: =+N38/N44 -> 0.012
N53: GO BACK

Sheet Activities
A1: ⟵ Back to Summary | C1: Activities – Key Indicators & Budget
A11: Key Indicators 2024
A12: Indicator | B12: January | C12: February | D12: March | E12: April | F12: May | G12: June | H12: July | I12: August | J12: September | K12: October | L12: November | M12: December | N12: TOTAL
A13: Total available Rooms | B13: =Rooms!C13 -> 930 | C13: =Rooms!D13 -> 870 | D13: =Rooms!E13 -> 930 | E13: =Rooms!F13 -> 900 | F13: =Rooms!G13 -> 930 | G13: =Rooms!H13 -> 900 | H13: =Rooms!I13 -> 930 | I13: =Rooms!J13 -> 930 | ... N13: =Rooms!O13 -> 10980
A14: Total Rooms Occupied | B14: =Rooms!C14 -> 429 | C14: =Rooms!D14 -> 456 | D14: =Rooms!E14 -> 448 | E14: =Rooms!F14 -> 259 | F14: =Rooms!G14 -> 176 | G14: =Rooms!H14 -> 98 | H14: =Rooms!I14 -> 249 | I14: =Rooms!J14 -> 157 | ... N14: =Rooms!O14 -> 2774
A15: Total Guests | B15: =Rooms!C15 -> 711 | C15: =Rooms!D15 -> 834 | D15: =Rooms!E15 -> 835 | E15: =Rooms!F15 -> 544 | F15: =Rooms!G15 -> 311 | G15: =Rooms!H15 -> 160 | H15: =Rooms!I15 -> 429 | I15: =Rooms!J15 -> 310 | ... N15: =Rooms!O15 -> 5076
A16: % Occupancy | B16: =Rooms!C16 -> 0.4613 | C16: =Rooms!D16 -> 0.5241 | D16: =Rooms!E16 -> 0.4817 | E16: =Rooms!F16 -> 0.2878 | F16: =Rooms!G16 -> 0.1892 | G16: =Rooms!H16 -> 0.1089 | H16: =Rooms!I16 -> 0.2677 | I16: =Rooms!J16 -> 0.1688 | ... N16: =Rooms!O16 -> 0.25264117
A17: Average Daily Room Only | B17: =Rooms!C17 -> 359.84047 | C17: =Rooms!D17 -> 465.18852 | D17: =Rooms!E17 -> 389.00314 | E17: =Rooms!F17 -> 378.9522 | F17: =Rooms!G17 -> 231.30814 | G17: =Rooms!H17 -> 291.12236 | H17: =Rooms!I17 -> 426.03102 | I17: =Rooms!J17 -> 403.28888 | ... N17: =Rooms!O17 -> 431.01011
A18: Key Indicators 2025
A19: Indicator | B19: January | C19: February | D19: March | E19: April | F19: May | G19: June | H19: July | I19: August | J19: September | K19: October | L19: November | M19: December | N19: TOTAL
A20: Total available Rooms | B20: =Rooms!C20 -> 930 | C20: =Rooms!D20 -> 840 | D20: =Rooms!E20 -> 930 | E20: =Rooms!F20 -> 900 | F20: =Rooms!G20 -> 930 | G20: =Rooms!H20 -> 900 | H20: =Rooms!I20 -> 930 | I20: =Rooms!J20 -> 930 | ... N20: =Rooms!O20 -> 10950
A21: Total Rooms Occupied | B21: =Rooms!C21 -> 454 | C21: =Rooms!D21 -> 479 | D21: =Rooms!E21 -> 519 | E21: =Rooms!F21 -> 239 | F21: =Rooms!G21 -> 114 | G21: =Rooms!H21 -> 102 | H21: =Rooms!I21 -> 274 | I21: =Rooms!J21 -> 220 | ... N21: =Rooms!O21 -> 3179
A22: Total Guests | B22: =Rooms!C22 -> 809 | C22: =Rooms!D22 -> 893 | D22: =Rooms!E22 -> 962 | E22: =Rooms!F22 -> 428 | F22: =Rooms!G22 -> 228 | G22: =Rooms!H22 -> 183 | H22: =Rooms!I22 -> 611 | I22: =Rooms!J22 -> 411 | ... N22: =Rooms!O22 -> 5677
A23: % Occupancy | B23: =Rooms!C23 -> 0.48817204 | C23: =Rooms!D23 -> 0.5702381 | D23: =Rooms!E23 -> 0.55806452 | E23: =Rooms!F23 -> 0.26555556 | F23: =Rooms!G23 -> 0.12258065 | G23: =Rooms!H23 -> 0.11333333 | H23: =Rooms!I23 -> 0.29462366 | I23: =Rooms!J23 -> 0.23655914 | ... N23: =Rooms!O23 -> 0.29031963
A24: Average Daily Room Only | B24: =Rooms!C24 -> 473.50649 | C24: =Rooms!D24 -> 550.00104 | D24: =Rooms!E24 -> 478.48852 | E24: =Rooms!F24 -> 497.89901 | F24: =Rooms!G24 -> 482.76039 | G24: =Rooms!H24 -> 379.47717 | H24: =Rooms!I24 -> 508.05451 | I24: =Rooms!J24 -> 371.59366 | ... N24: =Rooms!O24 -> 484.67682
A25: Key Indicators 2026 (Budget)
A26: Indicator | B26: January | C26: February | D26: March | E26: April | F26: May | G26: June | H26: July | I26: August | J26: September | K26: October | L26: November | M26: December | N26: TOTAL
A27: Total available Rooms | B27: =Rooms!C27 -> 930 | C27: =Rooms!D27 -> 840 | D27: =Rooms!E27 -> 930 | E27: =Rooms!F27 -> 900 | F27: =Rooms!G27 -> 930 | G27: =Rooms!H27 -> 900 | H27: =Rooms!I27 -> 930 | I27: =Rooms!J27 -> 930 | ... N27: =Rooms!O27 -> 10020
A28: Total Rooms Occupied | B28: =Rooms!C28 -> 697.5 | C28: =Rooms!D28 -> 638.4 | D28: =Rooms!E28 -> 607.7 | E28: =Rooms!F28 -> 332 | F28: =Rooms!G28 -> 232.48621 | G28: =Rooms!H28 -> 167.65517 | H28: =Rooms!I28 -> 332.1 | I28: =Rooms!J28 -> 251.32 | ... N28: =Rooms!O28 -> 4363.2889
A29: Total Guests | B29: =Rooms!C29 -> 1255.5 | C29: =Rooms!D29 -> 1149.12 | D29: =Rooms!E29 -> 1093.86 | E29: =Rooms!F29 -> 597.6 | F29: =Rooms!G29 -> 418.47517 | G29: =Rooms!H29 -> 301.77931 | H29: =Rooms!I29 -> 597.78 | I29: =Rooms!J29 -> 452.376 | ... N29: =Rooms!O29 -> 7853.92
A30: % Occupancy | B30: =Rooms!C30 -> 0.75 | C30: =Rooms!D30 -> 0.76 | D30: =Rooms!E30 -> 0.65344086 | E30: =Rooms!F30 -> 0.36888889 | F30: =Rooms!G30 -> 0.24998517 | G30: =Rooms!H30 -> 0.18628352 | H30: =Rooms!I30 -> 0.35709677 | I30: =Rooms!J30 -> 0.27023656 | ... N30: =Rooms!O30 -> 0.43545797
A31: Average Daily Room Only | B31: =Rooms!C31 -> 595.27155 | C31: =Rooms!D31 -> 583.47405 | D31: =Rooms!E31 -> 590.96203 | E31: =Rooms!F31 -> 635.29075 | F31: =Rooms!G31 -> 521.40328 | G31: =Rooms!H31 -> 553.7017 | H31: =Rooms!I31 -> 566.23141 | I31: =Rooms!J31 -> 520.6179 | ... N31: =Rooms!O31 -> 596.88852
A34: Revenue by Month
A35: Label | B35: January | C35: February | D35: March | E35: April | F35: May | G35: June | H35: July | I35: August | J35: September | K35: October | L35: November | M35: December | N35: TOTAL
A36: Revenue 2024 | B36: 23251.898 | C36: 35457.988 | D36: 29360.589 | E36: 19914.132 | F36: 4278.6451 | G36: 4884.2611 | H36: 12683.715 | I36: 11513.628 | J36: 513.1923 | K36: 792.42503 | L36: 15512.893 | M36: 28389.368 | N36: =SUM(B36:M36) -> 186552.73 | O36: =+Innoceanna!N36 -> 141959.13 | P36: =+N36+O36 -> 328511.87
A37: Revenue 2025 | B37: 40198.406 | C37: 42643.297 | D37: 49187.767 | E37: 27966.927 | F37: 11004.493 | G37: 8206.2238 | H37: 25587.581 | I37: 17736.76 | J37: 5691.6 | K37: 0 | L37: 26181.36 | M37: 48947.76 | N37: =SUM(B37:M37) -> 303352.17 | O37: =+Innoceanna!N37 -> 178974.46 | P37: =+N37+O37 -> 482326.63
A38: Revenue 2026 Budget | B38: =+'Key Indicators'!C333 -> 106009.4 | C38: =+'Key Indicators'!D333 -> 97027.096 | D38: =+'Key Indicators'!E333 -> 92361.163 | E38: =+'Key Indicators'!F333 -> 50458.954 | F38: =+'Key Indicators'!G333 -> 35334.37 | G38: =+'Key Indicators'!H333 -> 25481.038 | H38: =+'Key Indicators'!I333 -> 50474.152 | I38: =+'Key Indicators'!J333 -> 38196.82 | ... M38: =+'Key Indicators'!N333 -> 92970.242 | N38: =SUM(B38:M38) -> 663153.59 | P38: =+N38 -> 663153.59 | Q38: =+P38-P37 -> 180826.96
A40: Revenue per Occupied Room 2024 | B40: =+B36/B14 -> 54.200227 | C40: =+C36/C14 -> 77.758747 | D40: =+D36/D14 -> 65.537029 | E40: =+E36/E14 -> 76.888542 | F40: =+F36/F14 -> 24.310483 | G40: =+G36/G14 -> 49.839399 | H40: =+H36/H14 -> 50.938613 | I40: =+I36/I14 -> 73.335208 | ... N40: =+N36/N14 -> 67.250445
A41: Revenue per Occupied Room 2025 | B41: =+B37/B21 -> 88.542744 | C41: =+C37/C21 -> 89.025672 | D41: =+D37/D21 -> 94.774117 | E41: =+E37/E21 -> 117.01643 | F41: =+F37/F21 -> 96.53064 | G41: =+G37/G21 -> 80.453175 | H41: =+H37/H21 -> 93.385331 | I41: =+I37/I21 -> 80.621636 | ... N41: =+N37/N21 -> 95.423773 | O41: =+N41-N40 -> 28.173328 | P41: =+O41/N40 -> 0.41893147
A42: Revenue per Occupied Room 2026 | B42: =+B38/B28 -> 151.9848 | C42: =+C38/C28 -> 151.9848 | D42: =+D38/D28 -> 151.9848 | E42: =+E38/E28 -> 151.9848 | F42: =+F38/F28 -> 151.9848 | G42: =+G38/G28 -> 151.9848 | H42: =+H38/H28 -> 151.9848 | I42: =+I38/I28 -> 151.9848 | ... N42: =+N38/N28 -> 151.9848 | O42: =+N42-N41 -> 56.561027 | P42: =+O42/N41 -> 0.59273518
A44: Revenue by Guest 2024 | B44: =+B36/B15 -> 32.703091 | C44: =+C36/C15 -> 42.515574 | D44: =+D36/D15 -> 35.162382 | E44: =+E36/E15 -> 36.606861 | F44: =+F36/F15 -> 13.757701 | G44: =+G36/G15 -> 30.526632 | H44: =+H36/H15 -> 29.565768 | I44: =+I36/I15 -> 37.140734 | ... N44: =+N36/N15 -> 36.751918
A45: Revenue by Guest 2025 | B45: =+B37/B29 -> 32.017846 | C45: =+C37/C29 -> 37.109524 | D45: =+D37/D29 -> 44.96715 | E45: =+E37/E29 -> 46.798741 | F45: =+F37/F29 -> 26.296645 | G45: =+G37/G29 -> 27.192798 | H45: =+H37/H29 -> 42.804344 | I45: =+I37/I29 -> 39.208004 | ... N45: =+N37/N29 -> 38.624302
A46: Revenue by Guest 2026 | B46: =+B38/B29 -> 84.436 | C46: =+C38/C29 -> 84.436 | D46: =+D38/D29 -> 84.436 | E46: =+E38/E29 -> 84.436 | F46: =+F38/F29 -> 84.436 | G46: =+G38/G29 -> 84.436 | H46: =+H38/H29 -> 84.436 | I46: =+I38/I29 -> 84.436 | ... N46: =+N38/N29 -> 84.436 | O46: =+N46-N45 -> 45.811698 | P46: =+O46/N45 -> 1.1860848

Sheet Transportation
A1: ⟵ Back to Summary | C1: Transportation – Key Indicators & Budget
A11: Key Indicators 2024
A12: Indicator | B12: January | C12: February | D12: March | E12: April | F12: May | G12: June | H12: July | I12: August | J12: September | K12: October | L12: November | M12: December | N12: TOTAL
A13: Total available Rooms | B13: =Rooms!C13 -> 930 | C13: =Rooms!D13 -> 870 | D13: =Rooms!E13 -> 930 | E13: =Rooms!F13 -> 900 | F13: =Rooms!G13 -> 930 | G13: =Rooms!H13 -> 900 | H13: =Rooms!I13 -> 930 | I13: =Rooms!J13 -> 930 | ... N13: =Rooms!O13 -> 10980
A14: Total Rooms Occupied | B14: =Rooms!C14 -> 429 | C14: =Rooms!D14 -> 456 | D14: =Rooms!E14 -> 448 | E14: =Rooms!F14 -> 259 | F14: =Rooms!G14 -> 176 | G14: =Rooms!H14 -> 98 | H14: =Rooms!I14 -> 249 | I14: =Rooms!J14 -> 157 | ... N14: =Rooms!O14 -> 2774
A15: Total Guests | B15: =Rooms!C15 -> 711 | C15: =Rooms!D15 -> 834 | D15: =Rooms!E15 -> 835 | E15: =Rooms!F15 -> 544 | F15: =Rooms!G15 -> 311 | G15: =Rooms!H15 -> 160 | H15: =Rooms!I15 -> 429 | I15: =Rooms!J15 -> 310 | ... N15: =Rooms!O15 -> 5076
A16: % Occupancy | B16: =Rooms!C16 -> 0.4613 | C16: =Rooms!D16 -> 0.5241 | D16: =Rooms!E16 -> 0.4817 | E16: =Rooms!F16 -> 0.2878 | F16: =Rooms!G16 -> 0.1892 | G16: =Rooms!H16 -> 0.1089 | H16: =Rooms!I16 -> 0.2677 | I16: =Rooms!J16 -> 0.1688 | ... N16: =Rooms!O16 -> 0.25264117
A17: Average Daily Room Only | B17: =Rooms!C17 -> 359.84047 | C17: =Rooms!D17 -> 465.18852 | D17: =Rooms!E17 -> 389.00314 | E17: =Rooms!F17 -> 378.9522 | F17: =Rooms!G17 -> 231.30814 | G17: =Rooms!H17 -> 291.12236 | H17: =Rooms!I17 -> 426.03102 | I17: =Rooms!J17 -> 403.28888 | ... N17: =Rooms!O17 -> 431.01011
A18: Key Indicators 2025
A19: Indicator | B19: January | C19: February | D19: March | E19: April | F19: May | G19: June | H19: July | I19: August | J19: September | K19: October | L19: November | M19: December | N19: TOTAL
A20: Total available Rooms | B20: =Rooms!C20 -> 930 | C20: =Rooms!D20 -> 840 | D20: =Rooms!E20 -> 930 | E20: =Rooms!F20 -> 900 | F20: =Rooms!G20 -> 930 | G20: =Rooms!H20 -> 900 | H20: =Rooms!I20 -> 930 | I20: =Rooms!J20 -> 930 | ... N20: =Rooms!O20 -> 10950
A21: Total Rooms Occupied | B21: =Rooms!C21 -> 454 | C21: =Rooms!D21 -> 479 | D21: =Rooms!E21 -> 519 | E21: =Rooms!F21 -> 239 | F21: =Rooms!G21 -> 114 | G21: =Rooms!H21 -> 102 | H21: =Rooms!I21 -> 274 | I21: =Rooms!J21 -> 220 | ... N21: =Rooms!O21 -> 3179
A22: Total Guests | B22: =Rooms!C22 -> 809 | C22: =Rooms!D22 -> 893 | D22: =Rooms!E22 -> 962 | E22: =Rooms!F22 -> 428 | F22: =Rooms!G22 -> 228 | G22: =Rooms!H22 -> 183 | H22: =Rooms!I22 -> 611 | I22: =Rooms!J22 -> 411 | ... N22: =Rooms!O22 -> 5677
A23: % Occupancy | B23: =Rooms!C23 -> 0.48817204 | C23: =Rooms!D23 -> 0.5702381 | D23: =Rooms!E23 -> 0.55806452 | E23: =Rooms!F23 -> 0.26555556 | F23: =Rooms!G23 -> 0.12258065 | G23: =Rooms!H23 -> 0.11333333 | H23: =Rooms!I23 -> 0.29462366 | I23: =Rooms!J23 -> 0.23655914 | ... N23: =Rooms!O23 -> 0.29031963
A24: Average Daily Room Only | B24: =Rooms!C24 -> 473.50649 | C24: =Rooms!D24 -> 550.00104 | D24: =Rooms!E24 -> 478.48852 | E24: =Rooms!F24 -> 497.89901 | F24: =Rooms!G24 -> 482.76039 | G24: =Rooms!H24 -> 379.47717 | H24: =Rooms!I24 -> 508.05451 | I24: =Rooms!J24 -> 371.59366 | ... N24: =Rooms!O24 -> 484.67682
A25: Key Indicators 2026 (Budget)
A26: Indicator | B26: January | C26: February | D26: March | E26: April | F26: May | G26: June | H26: July | I26: August | J26: September | K26: October | L26: November | M26: December | N26: TOTAL
A27: Total available Rooms | B27: =Rooms!C27 -> 930 | C27: =Rooms!D27 -> 840 | D27: =Rooms!E27 -> 930 | E27: =Rooms!F27 -> 900 | F27: =Rooms!G27 -> 930 | G27: =Rooms!H27 -> 900 | H27: =Rooms!I27 -> 930 | I27: =Rooms!J27 -> 930 | ... N27: =Rooms!O27 -> 10020
A28: Total Rooms Occupied | B28: =Rooms!C28 -> 697.5 | C28: =Rooms!D28 -> 638.4 | D28: =Rooms!E28 -> 607.7 | E28: =Rooms!F28 -> 332 | F28: =Rooms!G28 -> 232.48621 | G28: =Rooms!H28 -> 167.65517 | H28: =Rooms!I28 -> 332.1 | I28: =Rooms!J28 -> 251.32 | ... N28: =Rooms!O28 -> 4363.2889
A29: Total Guests | B29: =Rooms!C29 -> 1255.5 | C29: =Rooms!D29 -> 1149.12 | D29: =Rooms!E29 -> 1093.86 | E29: =Rooms!F29 -> 597.6 | F29: =Rooms!G29 -> 418.47517 | G29: =Rooms!H29 -> 301.77931 | H29: =Rooms!I29 -> 597.78 | I29: =Rooms!J29 -> 452.376 | ... N29: =Rooms!O29 -> 7853.92
A30: % Occupancy | B30: =Rooms!C30 -> 0.75 | C30: =Rooms!D30 -> 0.76 | D30: =Rooms!E30 -> 0.65344086 | E30: =Rooms!F30 -> 0.36888889 | F30: =Rooms!G30 -> 0.24998517 | G30: =Rooms!H30 -> 0.18628352 | H30: =Rooms!I30 -> 0.35709677 | I30: =Rooms!J30 -> 0.27023656 | ... N30: =Rooms!O30 -> 0.43545797
A31: Average Daily Room Only | B31: =Rooms!C31 -> 595.27155 | C31: =Rooms!D31 -> 583.47405 | D31: =Rooms!E31 -> 590.96203 | E31: =Rooms!F31 -> 635.29075 | F31: =Rooms!G31 -> 521.40328 | G31: =Rooms!H31 -> 553.7017 | H31: =Rooms!I31 -> 566.23141 | I31: =Rooms!J31 -> 520.6179 | ... N31: =Rooms!O31 -> 596.88852
A34: Revenue by Month
A35: Label | B35: January | C35: February | D35: March | E35: April | F35: May | G35: June | H35: July | I35: August | J35: September | K35: October | L35: November | M35: December | N35: TOTAL
A36: Revenue 2024 | B36: 6839.4117 | C36: 8643.119 | D36: 9479.8495 | E36: 4705.2109 | F36: 971.64709 | G36: 1180.5132 | H36: 18097.012 | I36: 2716.9387 | J36: 1088.3086 | K36: 68.442552 | L36: 3294.4656 | M36: 7363.247 | N36: =SUM(B36:M36) -> 64448.166
A37: Revenue 2025 | B37: 11835.556 | C37: 14786.668 | D37: 17991.069 | E37: 18846.319 | F37: 4777.0945 | G37: 5542.9628 | H37: 10251.493 | I37: 9337.3146 | J37: 1959.5 | K37: 0 | L37: 9013.7 | M37: 16851.7 | N37: =SUM(B37:M37) -> 121193.38
A38: Revenue 2026 Budget | B38: =+'Key Indicators'!C334 -> 36735.93 | C38: =+'Key Indicators'!D334 -> 33623.251 | D38: =+'Key Indicators'!E334 -> 32006.344 | E38: =+'Key Indicators'!F334 -> 17485.776 | F38: =+'Key Indicators'!G334 -> 12244.584 | G38: =+'Key Indicators'!H334 -> 8830.0626 | H38: =+'Key Indicators'!I334 -> 17491.043 | I38: =+'Key Indicators'!J334 -> 13236.522 | ... M38: =+'Key Indicators'!N334 -> 32217.411 | N38: =SUM(B38:M38) -> 229805.7 | O38: =+N38-N37 -> 108612.32 | P38: =+O38/N37 -> 0.89619026
A40: Revenue per Occupied Room 2024 | B40: =+B36/B14 -> 15.942685 | C40: =+C36/C14 -> 18.954208 | D40: =+D36/D14 -> 21.160378 | E40: =+E36/E14 -> 18.166838 | F40: =+F36/F14 -> 5.5207221 | G40: =+G36/G14 -> 12.046053 | H40: =+H36/H14 -> 72.678765 | I40: =+I36/I14 -> 17.305342 | ... N40: =+N36/N14 -> 23.232937
A41: Revenue per Occupied Room 2025 | B41: =+B37/B21 -> 26.069506 | C41: =+C37/C21 -> 30.86987 | D41: =+D37/D21 -> 34.664872 | E41: =+E37/E21 -> 78.854889 | F41: =+F37/F21 -> 41.904338 | G41: =+G37/G21 -> 54.342773 | H41: =+H37/H21 -> 37.414209 | I41: =+I37/I21 -> 42.442339 | ... N41: =+N37/N21 -> 38.123113 | O41: =+N41-N40 -> 14.890176 | P41: =+O41/N40 -> 0.64090806
A42: Revenue per Occupied Room 2026 | B42: =+B38/B28 -> 52.668 | C42: =+C38/C28 -> 52.668 | D42: =+D38/D28 -> 52.668 | E42: =+E38/E28 -> 52.668 | F42: =+F38/F28 -> 52.668 | G42: =+G38/G28 -> 52.668 | H42: =+H38/H28 -> 52.668 | I42: =+I38/I28 -> 52.668 | ... N42: =+N38/N28 -> 52.668 | O42: =+N42-N41 -> 14.544887 | P42: =+O42/N41 -> 0.38152412
A44: Revenue by Guest 2024 | B44: =+B36/B15 -> 9.6194258 | C44: =+C36/C15 -> 10.363452 | D44: =+D36/D15 -> 11.353113 | E44: =+E36/E15 -> 8.6492848 | F44: =+F36/F15 -> 3.1242672 | G44: =+G36/G15 -> 7.3782076 | H44: =+H36/H15 -> 42.184178 | I44: =+I36/I15 -> 8.7643185 | ... N44: =+N36/N15 -> 12.696644
A45: Revenue by Guest 2025 | B45: =+B37/B29 -> 9.426966 | C45: =+C37/C29 -> 12.867819 | D45: =+D37/D29 -> 16.447323 | E45: =+E37/E29 -> 31.536678 | F45: =+F37/F29 -> 11.415479 | G45: =+G37/G29 -> 18.367604 | H45: =+H37/H29 -> 17.149274 | I45: =+I37/I29 -> 20.640606 | ... N45: =+N37/N29 -> 15.430941
A46: Revenue by Guest 2026 | B46: =+B38/B29 -> 29.26 | C46: =+C38/C29 -> 29.26 | D46: =+D38/D29 -> 29.26 | E46: =+E38/E29 -> 29.26 | F46: =+F38/F29 -> 29.26 | G46: =+G38/G29 -> 29.26 | H46: =+H38/H29 -> 29.26 | I46: =+I38/I29 -> 29.26 | ... N46: =+N38/N29 -> 29.26 | O46: =+N46-N45 -> 13.829059 | P46: =+O46/N45 -> 0.89619026
B48: 35 | C48: 35 | D48: 35 | E48: 35 | F48: 35 | G48: 35 | H48: 35 | I48: 35 | J48: 35 | K48: 35 | L48: 35 | M48: 35
B49: =+B48*B22 -> 28315 | C49: =+C48*C22 -> 31255 | D49: =+D48*D22 -> 33670 | E49: =+E48*E22 -> 14980 | F49: =+F48*F22 -> 7980 | G49: =+G48*G22 -> 6405 | H49: =+H48*H22 -> 21385 | I49: =+I48*I22 -> 14385 | ... M49: =+M48*M22 -> 24675

Sheet Innoceanna
A1: ⟵ Back to Summary | C1: Innoceanna – Key Indicators & Budget
A11: Key Indicators 2024
A12: Indicator | B12: January | C12: February | D12: March | E12: April | F12: May | G12: June | H12: July | I12: August | J12: September | K12: October | L12: November | M12: December | N12: TOTAL
A13: Total available Rooms | B13: =Rooms!C13 -> 930 | C13: =Rooms!D13 -> 870 | D13: =Rooms!E13 -> 930 | E13: =Rooms!F13 -> 900 | F13: =Rooms!G13 -> 930 | G13: =Rooms!H13 -> 900 | H13: =Rooms!I13 -> 930 | I13: =Rooms!J13 -> 930 | ... N13: =Rooms!O13 -> 10980
A14: Total Rooms Occupied | B14: =Rooms!C14 -> 429 | C14: =Rooms!D14 -> 456 | D14: =Rooms!E14 -> 448 | E14: =Rooms!F14 -> 259 | F14: =Rooms!G14 -> 176 | G14: =Rooms!H14 -> 98 | H14: =Rooms!I14 -> 249 | I14: =Rooms!J14 -> 157 | ... N14: =Rooms!O14 -> 2774
A15: Total Guests | B15: =Rooms!C15 -> 711 | C15: =Rooms!D15 -> 834 | D15: =Rooms!E15 -> 835 | E15: =Rooms!F15 -> 544 | F15: =Rooms!G15 -> 311 | G15: =Rooms!H15 -> 160 | H15: =Rooms!I15 -> 429 | I15: =Rooms!J15 -> 310 | ... N15: =Rooms!O15 -> 5076
A16: % Occupancy | B16: =Rooms!C16 -> 0.4613 | C16: =Rooms!D16 -> 0.5241 | D16: =Rooms!E16 -> 0.4817 | E16: =Rooms!F16 -> 0.2878 | F16: =Rooms!G16 -> 0.1892 | G16: =Rooms!H16 -> 0.1089 | H16: =Rooms!I16 -> 0.2677 | I16: =Rooms!J16 -> 0.1688 | ... N16: =Rooms!O16 -> 0.25264117
A17: Average Daily Room Only | B17: =Rooms!C17 -> 359.84047 | C17: =Rooms!D17 -> 465.18852 | D17: =Rooms!E17 -> 389.00314 | E17: =Rooms!F17 -> 378.9522 | F17: =Rooms!G17 -> 231.30814 | G17: =Rooms!H17 -> 291.12236 | H17: =Rooms!I17 -> 426.03102 | I17: =Rooms!J17 -> 403.28888 | ... N17: =Rooms!O17 -> 431.01011
A18: Key Indicators 2025
A19: Indicator | B19: January | C19: February | D19: March | E19: April | F19: May | G19: June | H19: July | I19: August | J19: September | K19: October | L19: November | M19: December | N19: TOTAL
A20: Total available Rooms | B20: =Rooms!C20 -> 930 | C20: =Rooms!D20 -> 840 | D20: =Rooms!E20 -> 930 | E20: =Rooms!F20 -> 900 | F20: =Rooms!G20 -> 930 | G20: =Rooms!H20 -> 900 | H20: =Rooms!I20 -> 930 | I20: =Rooms!J20 -> 930 | ... N20: =Rooms!O20 -> 10950
A21: Total Rooms Occupied | B21: =Rooms!C21 -> 454 | C21: =Rooms!D21 -> 479 | D21: =Rooms!E21 -> 519 | E21: =Rooms!F21 -> 239 | F21: =Rooms!G21 -> 114 | G21: =Rooms!H21 -> 102 | H21: =Rooms!I21 -> 274 | I21: =Rooms!J21 -> 220 | ... N21: =Rooms!O21 -> 3179
A22: Total Guests | B22: =Rooms!C22 -> 809 | C22: =Rooms!D22 -> 893 | D22: =Rooms!E22 -> 962 | E22: =Rooms!F22 -> 428 | F22: =Rooms!G22 -> 228 | G22: =Rooms!H22 -> 183 | H22: =Rooms!I22 -> 611 | I22: =Rooms!J22 -> 411 | ... N22: =Rooms!O22 -> 5677
A23: % Occupancy | B23: =Rooms!C23 -> 0.48817204 | C23: =Rooms!D23 -> 0.5702381 | D23: =Rooms!E23 -> 0.55806452 | E23: =Rooms!F23 -> 0.26555556 | F23: =Rooms!G23 -> 0.12258065 | G23: =Rooms!H23 -> 0.11333333 | H23: =Rooms!I23 -> 0.29462366 | I23: =Rooms!J23 -> 0.23655914 | ... N23: =Rooms!O23 -> 0.29031963
A24: Average Daily Room Only | B24: =Rooms!C24 -> 473.50649 | C24: =Rooms!D24 -> 550.00104 | D24: =Rooms!E24 -> 478.48852 | E24: =Rooms!F24 -> 497.89901 | F24: =Rooms!G24 -> 482.76039 | G24: =Rooms!H24 -> 379.47717 | H24: =Rooms!I24 -> 508.05451 | I24: =Rooms!J24 -> 371.59366 | ... N24: =Rooms!O24 -> 484.67682
A25: Key Indicators 2026 (Budget)
A26: Indicator | B26: January | C26: February | D26: March | E26: April | F26: May | G26: June | H26: July | I26: August | J26: September | K26: October | L26: November | M26: December | N26: TOTAL
A27: Total available Rooms | B27: =Rooms!C27 -> 930 | C27: =Rooms!D27 -> 840 | D27: =Rooms!E27 -> 930 | E27: =Rooms!F27 -> 900 | F27: =Rooms!G27 -> 930 | G27: =Rooms!H27 -> 900 | H27: =Rooms!I27 -> 930 | I27: =Rooms!J27 -> 930 | ... N27: =Rooms!O27 -> 10020
A28: Total Rooms Occupied | B28: =Rooms!C28 -> 697.5 | C28: =Rooms!D28 -> 638.4 | D28: =Rooms!E28 -> 607.7 | E28: =Rooms!F28 -> 332 | F28: =Rooms!G28 -> 232.48621 | G28: =Rooms!H28 -> 167.65517 | H28: =Rooms!I28 -> 332.1 | I28: =Rooms!J28 -> 251.32 | ... N28: =Rooms!O28 -> 4363.2889
A29: Total Guests | B29: =Rooms!C29 -> 1255.5 | C29: =Rooms!D29 -> 1149.12 | D29: =Rooms!E29 -> 1093.86 | E29: =Rooms!F29 -> 597.6 | F29: =Rooms!G29 -> 418.47517 | G29: =Rooms!H29 -> 301.77931 | H29: =Rooms!I29 -> 597.78 | I29: =Rooms!J29 -> 452.376 | ... N29: =Rooms!O29 -> 7853.92
A30: % Occupancy | B30: =Rooms!C30 -> 0.75 | C30: =Rooms!D30 -> 0.76 | D30: =Rooms!E30 -> 0.65344086 | E30: =Rooms!F30 -> 0.36888889 | F30: =Rooms!G30 -> 0.24998517 | G30: =Rooms!H30 -> 0.18628352 | H30: =Rooms!I30 -> 0.35709677 | I30: =Rooms!J30 -> 0.27023656 | ... N30: =Rooms!O30 -> 0.43545797
A31: Average Daily Room Only | B31: =Rooms!C31 -> 595.27155 | C31: =Rooms!D31 -> 583.47405 | D31: =Rooms!E31 -> 590.96203 | E31: =Rooms!F31 -> 635.29075 | F31: =Rooms!G31 -> 521.40328 | G31: =Rooms!H31 -> 553.7017 | H31: =Rooms!I31 -> 566.23141 | I31: =Rooms!J31 -> 520.6179 | ... N31: =Rooms!O31 -> 596.88852
A34: Revenue by Month
A35: Label | B35: January | C35: February | D35: March | E35: April | F35: May | G35: June | H35: July | I35: August | J35: September | K35: October | L35: November | M35: December | N35: TOTAL
A36: Revenue 2024 | B36: 19035.44 | C36: 24083.111 | D36: 23552.045 | E36: 14307.943 | F36: 5683.7656 | G36: 6108.9314 | H36: 11978.498 | I36: 9877.4202 | J36: 514.09332 | K36: 0 | L36: 7821.1375 | M36: 18996.75 | N36: =SUM(B36:M36) -> 141959.13
A37: Revenue 2025 | B37: 23824.917 | C37: 29052.61 | D37: 29098.835 | E37: 17280.51 | F37: 6406.4185 | G37: 8041.9542 | H37: 18147.843 | I37: 12571.37 | J37: 1800 | K37: 0 | L37: 9315 | M37: 23435 | N37: =SUM(B37:M37) -> 178974.46
A38: Revenue 2026 Budget | B38: =+'Key Indicators'!C335 -> 2076.0095 | C38: =+'Key Indicators'!D335 -> 1862.4492 | D38: =+'Key Indicators'!E335 -> 1795.6381 | E38: =+'Key Indicators'!F335 -> 1054.5827 | F38: =+'Key Indicators'!G335 -> 606.09535 | G38: =+'Key Indicators'!H335 -> 464.15477 | H38: =+'Key Indicators'!I335 -> 940.22726 | I38: =+'Key Indicators'!J335 -> 654.20846 | ... M38: =+'Key Indicators'!N335 -> 2244.243 | N38: =SUM(B38:M38) -> 13021.985
A41: Revenue by Monthper Year
A42: Label | B42: January | C42: February | D42: March | E42: April | F42: May | G42: June | H42: July | I42: August | J42: September | K42: October | L42: November | M42: December | N42: TOTAL
A43: Revenue 2024 | B43: =+Rooms!C36 -> 154371.56 | C43: =+Rooms!D36 -> 212125.96 | D43: =+Rooms!E36 -> 174273.41 | E43: =+Rooms!F36 -> 98148.619 | F43: =+Rooms!G36 -> 40710.232 | G43: =+Rooms!H36 -> 28529.992 | H43: =+Rooms!I36 -> 106081.72 | I43: =+Rooms!J36 -> 63316.354 | ... N43: =+Rooms!O36 -> 1195622
A44: Revenue 2025 | B44: =+Rooms!C37 -> 214971.95 | C44: =+Rooms!D37 -> 263450.5 | D44: =+Rooms!E37 -> 248335.54 | E44: =+Rooms!F37 -> 118997.86 | F44: =+Rooms!G37 -> 55034.684 | G44: =+Rooms!H37 -> 38706.671 | H44: =+Rooms!I37 -> 139206.94 | I44: =+Rooms!J37 -> 81750.604 | ... N44: =+Rooms!O37 -> 1540787.6
A45: Revenue 2026 Budget | B45: =+Rooms!C38 -> 415201.91 | C45: =+Rooms!D38 -> 372489.83 | D45: =+Rooms!E38 -> 359127.63 | E45: =+Rooms!F38 -> 210916.53 | F45: =+Rooms!G38 -> 121219.07 | G45: =+Rooms!H38 -> 92830.953 | H45: =+Rooms!I38 -> 188045.45 | I45: =+Rooms!J38 -> 130841.69 | ... N45: =+Rooms!O38 -> 2604397.1
A48: Revenue 2026 Budget | B48: =+B38/B45 -> 0.005 | C48: =+C38/C45 -> 0.005 | D48: =+D38/D45 -> 0.005 | E48: =+E38/E45 -> 0.005 | F48: =+F38/F45 -> 0.005 | G48: =+G38/G45 -> 0.005 | H48: =+H38/H45 -> 0.005 | I48: =+I38/I45 -> 0.005 | J48: =+J38/J45 -> 0.005 | L48: =+L38/L45 -> 0.005 | M48: =+M38/M45 -> 0.005 | N48: =+N38/N45 -> 0.005

Sheet Sustainability Fee
A1: ⟵ Back to Summary | C1: Sustainability Fee – Key Indicators & Budget
A11: Key Indicators 2024
A12: Indicator | B12: January | C12: February | D12: March | E12: April | F12: May | G12: June | H12: July | I12: August | J12: September | K12: October | L12: November | M12: December | N12: TOTAL
A13: Total available Rooms | B13: =Rooms!C13 -> 930 | C13: =Rooms!D13 -> 870 | D13: =Rooms!E13 -> 930 | E13: =Rooms!F13 -> 900 | F13: =Rooms!G13 -> 930 | G13: =Rooms!H13 -> 900 | H13: =Rooms!I13 -> 930 | I13: =Rooms!J13 -> 930 | ... N13: =Rooms!O13 -> 10980
A14: Total Rooms Occupied | B14: =Rooms!C14 -> 429 | C14: =Rooms!D14 -> 456 | D14: =Rooms!E14 -> 448 | E14: =Rooms!F14 -> 259 | F14: =Rooms!G14 -> 176 | G14: =Rooms!H14 -> 98 | H14: =Rooms!I14 -> 249 | I14: =Rooms!J14 -> 157 | ... N14: =Rooms!O14 -> 2774
A15: Total Guests | B15: =Rooms!C15 -> 711 | C15: =Rooms!D15 -> 834 | D15: =Rooms!E15 -> 835 | E15: =Rooms!F15 -> 544 | F15: =Rooms!G15 -> 311 | G15: =Rooms!H15 -> 160 | H15: =Rooms!I15 -> 429 | I15: =Rooms!J15 -> 310 | ... N15: =Rooms!O15 -> 5076
A16: % Occupancy | B16: =Rooms!C16 -> 0.4613 | C16: =Rooms!D16 -> 0.5241 | D16: =Rooms!E16 -> 0.4817 | E16: =Rooms!F16 -> 0.2878 | F16: =Rooms!G16 -> 0.1892 | G16: =Rooms!H16 -> 0.1089 | H16: =Rooms!I16 -> 0.2677 | I16: =Rooms!J16 -> 0.1688 | ... N16: =Rooms!O16 -> 0.25264117
A17: Average Daily Room Only | B17: =Rooms!C17 -> 359.84047 | C17: =Rooms!D17 -> 465.18852 | D17: =Rooms!E17 -> 389.00314 | E17: =Rooms!F17 -> 378.9522 | F17: =Rooms!G17 -> 231.30814 | G17: =Rooms!H17 -> 291.12236 | H17: =Rooms!I17 -> 426.03102 | I17: =Rooms!J17 -> 403.28888 | ... N17: =Rooms!O17 -> 431.01011
A18: Key Indicators 2025
A19: Indicator | B19: January | C19: February | D19: March | E19: April | F19: May | G19: June | H19: July | I19: August | J19: September | K19: October | L19: November | M19: December | N19: TOTAL
A20: Total available Rooms | B20: =Rooms!C20 -> 930 | C20: =Rooms!D20 -> 840 | D20: =Rooms!E20 -> 930 | E20: =Rooms!F20 -> 900 | F20: =Rooms!G20 -> 930 | G20: =Rooms!H20 -> 900 | H20: =Rooms!I20 -> 930 | I20: =Rooms!J20 -> 930 | ... N20: =Rooms!O20 -> 10950
A21: Total Rooms Occupied | B21: =Rooms!C21 -> 454 | C21: =Rooms!D21 -> 479 | D21: =Rooms!E21 -> 519 | E21: =Rooms!F21 -> 239 | F21: =Rooms!G21 -> 114 | G21: =Rooms!H21 -> 102 | H21: =Rooms!I21 -> 274 | I21: =Rooms!J21 -> 220 | ... N21: =Rooms!O21 -> 3179
A22: Total Guests | B22: =Rooms!C22 -> 809 | C22: =Rooms!D22 -> 893 | D22: =Rooms!E22 -> 962 | E22: =Rooms!F22 -> 428 | F22: =Rooms!G22 -> 228 | G22: =Rooms!H22 -> 183 | H22: =Rooms!I22 -> 611 | I22: =Rooms!J22 -> 411 | ... N22: =Rooms!O22 -> 5677
A23: % Occupancy | B23: =Rooms!C23 -> 0.48817204 | C23: =Rooms!D23 -> 0.5702381 | D23: =Rooms!E23 -> 0.55806452 | E23: =Rooms!F23 -> 0.26555556 | F23: =Rooms!G23 -> 0.12258065 | G23: =Rooms!H23 -> 0.11333333 | H23: =Rooms!I23 -> 0.29462366 | I23: =Rooms!J23 -> 0.23655914 | ... N23: =Rooms!O23 -> 0.29031963
A24: Average Daily Room Only | B24: =Rooms!C24 -> 473.50649 | C24: =Rooms!D24 -> 550.00104 | D24: =Rooms!E24 -> 478.48852 | E24: =Rooms!F24 -> 497.89901 | F24: =Rooms!G24 -> 482.76039 | G24: =Rooms!H24 -> 379.47717 | H24: =Rooms!I24 -> 508.05451 | I24: =Rooms!J24 -> 371.59366 | ... N24: =Rooms!O24 -> 484.67682
A25: Key Indicators 2026 (Budget)
A26: Indicator | B26: January | C26: February | D26: March | E26: April | F26: May | G26: June | H26: July | I26: August | J26: September | K26: October | L26: November | M26: December | N26: TOTAL
A27: Total available Rooms | B27: =Rooms!C27 -> 930 | C27: =Rooms!D27 -> 840 | D27: =Rooms!E27 -> 930 | E27: =Rooms!F27 -> 900 | F27: =Rooms!G27 -> 930 | G27: =Rooms!H27 -> 900 | H27: =Rooms!I27 -> 930 | I27: =Rooms!J27 -> 930 | ... N27: =Rooms!O27 -> 10020
A28: Total Rooms Occupied | B28: =Rooms!C28 -> 697.5 | C28: =Rooms!D28 -> 638.4 | D28: =Rooms!E28 -> 607.7 | E28: =Rooms!F28 -> 332 | F28: =Rooms!G28 -> 232.48621 | G28: =Rooms!H28 -> 167.65517 | H28: =Rooms!I28 -> 332.1 | I28: =Rooms!J28 -> 251.32 | ... N28: =Rooms!O28 -> 4363.2889
A29: Total Guests | B29: =Rooms!C29 -> 1255.5 | C29: =Rooms!D29 -> 1149.12 | D29: =Rooms!E29 -> 1093.86 | E29: =Rooms!F29 -> 597.6 | F29: =Rooms!G29 -> 418.47517 | G29: =Rooms!H29 -> 301.77931 | H29: =Rooms!I29 -> 597.78 | I29: =Rooms!J29 -> 452.376 | ... N29: =Rooms!O29 -> 7853.92
A30: % Occupancy | B30: =Rooms!C30 -> 0.75 | C30: =Rooms!D30 -> 0.76 | D30: =Rooms!E30 -> 0.65344086 | E30: =Rooms!F30 -> 0.36888889 | F30: =Rooms!G30 -> 0.24998517 | G30: =Rooms!H30 -> 0.18628352 | H30: =Rooms!I30 -> 0.35709677 | I30: =Rooms!J30 -> 0.27023656 | ... N30: =Rooms!O30 -> 0.43545797
A31: Average Daily Room Only | B31: =Rooms!C31 -> 595.27155 | C31: =Rooms!D31 -> 583.47405 | D31: =Rooms!E31 -> 590.96203 | E31: =Rooms!F31 -> 635.29075 | F31: =Rooms!G31 -> 521.40328 | G31: =Rooms!H31 -> 553.7017 | H31: =Rooms!I31 -> 566.23141 | I31: =Rooms!J31 -> 520.6179 | ... N31: =Rooms!O31 -> 596.88852
A34: Revenue by Month
A35: Label | B35: January | C35: February | D35: March | E35: April | F35: May | G35: June | H35: July | I35: August | J35: September | K35: October | L35: November | M35: December | N35: TOTAL
A36: Revenue 2024 | B36: 0 | C36: 0 | D36: 0 | E36: 0 | F36: 0 | G36: 44.357877 | H36: 753.07831 | I36: 1265.7321 | J36: 0 | K36: 0 | L36: 4006.1814 | M36: 7524.7718 | N36: =SUM(B36:M36) -> 13594.122
A37: Revenue 2025 | B37: 12471.268 | C37: 15628.972 | D37: 16011.264 | E37: 10939.195 | F37: 5052.0297 | G37: 3797.2238 | H37: 8661.5231 | I37: 6901.8361 | J37: 1842.9204 | K37: 0 | L37: 8477.4336 | M37: 15849.115 | N37: =SUM(B37:M37) -> 105632.78
A38: Revenue 2026 Budget | B38: =+'Key Indicators'!C336 -> 35154 | C38: =+'Key Indicators'!D336 -> 32175.36 | D38: =+'Key Indicators'!E336 -> 30628.08 | E38: =+'Key Indicators'!F336 -> 16732.8 | F38: =+'Key Indicators'!G336 -> 11717.305 | G38: =+'Key Indicators'!H336 -> 8449.8207 | H38: =+'Key Indicators'!I336 -> 16737.84 | I38: =+'Key Indicators'!J336 -> 12666.528 | ... M38: =+'Key Indicators'!N336 -> 30830.058 | N38: =SUM(B38:M38) -> 219909.76
A40: Revenue per Occupied Room 2024 | B40: =+B36/B14 -> 0 | C40: =+C36/C14 -> 0 | D40: =+D36/D14 -> 0 | E40: =+E36/E14 -> 0 | F40: =+F36/F14 -> 0 | G40: =+G36/G14 -> 0.4526314 | H40: =+H36/H14 -> 3.0244109 | I40: =+I36/I14 -> 8.0619876 | ... N40: =+N36/N14 -> 4.9005485
A41: Revenue per Occupied Room 2025 | B41: =+B37/B21 -> 27.469754 | C41: =+C37/C21 -> 32.628333 | D41: =+D37/D21 -> 30.850219 | E41: =+E37/E21 -> 45.770692 | F41: =+F37/F21 -> 44.31605 | G41: =+G37/G21 -> 37.227684 | H41: =+H37/H21 -> 31.611398 | I41: =+I37/I21 -> 31.371982 | ... N41: =+N37/N21 -> 33.228305
A42: Revenue per Occupied Room 2026 | B42: =+B38/B28 -> 50.4 | C42: =+C38/C28 -> 50.4 | D42: =+D38/D28 -> 50.4 | E42: =+E38/E28 -> 50.4 | F42: =+F38/F28 -> 50.4 | G42: =+G38/G28 -> 50.4 | H42: =+H38/H28 -> 50.4 | I42: =+I38/I28 -> 50.4 | ... N42: =+N38/N28 -> 50.4
A44: Revenue by Guest 2024 | B44: =+B36/B15 -> 0 | C44: =+C36/C15 -> 0 | D44: =+D36/D15 -> 0 | E44: =+E36/E15 -> 0 | F44: =+F36/F15 -> 0 | G44: =+G36/G15 -> 0.27723673 | H44: =+H36/H15 -> 1.7554273 | I44: =+I36/I15 -> 4.0830066 | ... N44: =+N36/N15 -> 2.6781169
A45: Revenue by Guest 2025 | B45: =+B37/B29 -> 9.9333081 | C45: =+C37/C29 -> 13.600818 | D45: =+D37/D29 -> 14.637397 | E45: =+E37/E29 -> 18.305213 | F45: =+F37/F29 -> 12.072472 | G45: =+G37/G29 -> 12.582784 | H45: =+H37/H29 -> 14.489483 | I45: =+I37/I29 -> 15.256857 | ... N45: =+N37/N29 -> 13.449689
A46: Revenue by Guest 2026 | B46: =+B38/B29 -> 28 | C46: =+C38/C29 -> 28 | D46: =+D38/D29 -> 28 | E46: =+E38/E29 -> 28 | F46: =+F38/F29 -> 28 | G46: =+G38/G29 -> 28 | H46: =+H38/H29 -> 28 | I46: =+I38/I29 -> 28 | ... N46: =+N38/N29 -> 28

Sheet Laundry
A1: ⟵ Back to Summary | C1: Laundry – Key Indicators & Budget
A11: Key Indicators 2024
A12: Indicator | B12: January | C12: February | D12: March | E12: April | F12: May | G12: June | H12: July | I12: August | J12: September | K12: October | L12: November | M12: December | N12: TOTAL
A13: Total available Rooms | B13: =Rooms!C13 -> 930 | C13: =Rooms!D13 -> 870 | D13: =Rooms!E13 -> 930 | E13: =Rooms!F13 -> 900 | F13: =Rooms!G13 -> 930 | G13: =Rooms!H13 -> 900 | H13: =Rooms!I13 -> 930 | I13: =Rooms!J13 -> 930 | ... N13: =Rooms!O13 -> 10980
A14: Total Rooms Occupied | B14: =Rooms!C14 -> 429 | C14: =Rooms!D14 -> 456 | D14: =Rooms!E14 -> 448 | E14: =Rooms!F14 -> 259 | F14: =Rooms!G14 -> 176 | G14: =Rooms!H14 -> 98 | H14: =Rooms!I14 -> 249 | I14: =Rooms!J14 -> 157 | ... N14: =Rooms!O14 -> 2774
A15: Total Guests | B15: =Rooms!C15 -> 711 | C15: =Rooms!D15 -> 834 | D15: =Rooms!E15 -> 835 | E15: =Rooms!F15 -> 544 | F15: =Rooms!G15 -> 311 | G15: =Rooms!H15 -> 160 | H15: =Rooms!I15 -> 429 | I15: =Rooms!J15 -> 310 | ... N15: =Rooms!O15 -> 5076
A16: % Occupancy | B16: =Rooms!C16 -> 0.4613 | C16: =Rooms!D16 -> 0.5241 | D16: =Rooms!E16 -> 0.4817 | E16: =Rooms!F16 -> 0.2878 | F16: =Rooms!G16 -> 0.1892 | G16: =Rooms!H16 -> 0.1089 | H16: =Rooms!I16 -> 0.2677 | I16: =Rooms!J16 -> 0.1688 | ... N16: =Rooms!O16 -> 0.25264117
A17: Average Daily Room Only | B17: =Rooms!C17 -> 359.84047 | C17: =Rooms!D17 -> 465.18852 | D17: =Rooms!E17 -> 389.00314 | E17: =Rooms!F17 -> 378.9522 | F17: =Rooms!G17 -> 231.30814 | G17: =Rooms!H17 -> 291.12236 | H17: =Rooms!I17 -> 426.03102 | I17: =Rooms!J17 -> 403.28888 | ... N17: =Rooms!O17 -> 431.01011
A18: Key Indicators 2025
A19: Indicator | B19: January | C19: February | D19: March | E19: April | F19: May | G19: June | H19: July | I19: August | J19: September | K19: October | L19: November | M19: December | N19: TOTAL
A20: Total available Rooms | B20: =Rooms!C20 -> 930 | C20: =Rooms!D20 -> 840 | D20: =Rooms!E20 -> 930 | E20: =Rooms!F20 -> 900 | F20: =Rooms!G20 -> 930 | G20: =Rooms!H20 -> 900 | H20: =Rooms!I20 -> 930 | I20: =Rooms!J20 -> 930 | ... N20: =Rooms!O20 -> 10950
A21: Total Rooms Occupied | B21: =Rooms!C21 -> 454 | C21: =Rooms!D21 -> 479 | D21: =Rooms!E21 -> 519 | E21: =Rooms!F21 -> 239 | F21: =Rooms!G21 -> 114 | G21: =Rooms!H21 -> 102 | H21: =Rooms!I21 -> 274 | I21: =Rooms!J21 -> 220 | ... N21: =Rooms!O21 -> 3179
A22: Total Guests | B22: =Rooms!C22 -> 809 | C22: =Rooms!D22 -> 893 | D22: =Rooms!E22 -> 962 | E22: =Rooms!F22 -> 428 | F22: =Rooms!G22 -> 228 | G22: =Rooms!H22 -> 183 | H22: =Rooms!I22 -> 611 | I22: =Rooms!J22 -> 411 | ... N22: =Rooms!O22 -> 5677
A23: % Occupancy | B23: =Rooms!C23 -> 0.48817204 | C23: =Rooms!D23 -> 0.5702381 | D23: =Rooms!E23 -> 0.55806452 | E23: =Rooms!F23 -> 0.26555556 | F23: =Rooms!G23 -> 0.12258065 | G23: =Rooms!H23 -> 0.11333333 | H23: =Rooms!I23 -> 0.29462366 | I23: =Rooms!J23 -> 0.23655914 | ... N23: =Rooms!O23 -> 0.29031963
A24: Average Daily Room Only | B24: =Rooms!C24 -> 473.50649 | C24: =Rooms!D24 -> 550.00104 | D24: =Rooms!E24 -> 478.48852 | E24: =Rooms!F24 -> 497.89901 | F24: =Rooms!G24 -> 482.76039 | G24: =Rooms!H24 -> 379.47717 | H24: =Rooms!I24 -> 508.05451 | I24: =Rooms!J24 -> 371.59366 | ... N24: =Rooms!O24 -> 484.67682
A25: Key Indicators 2026 (Budget)
A26: Indicator | B26: January | C26: February | D26: March | E26: April | F26: May | G26: June | H26: July | I26: August | J26: September | K26: October | L26: November | M26: December | N26: TOTAL
A27: Total available Rooms | B27: =Rooms!C27 -> 930 | C27: =Rooms!D27 -> 840 | D27: =Rooms!E27 -> 930 | E27: =Rooms!F27 -> 900 | F27: =Rooms!G27 -> 930 | G27: =Rooms!H27 -> 900 | H27: =Rooms!I27 -> 930 | I27: =Rooms!J27 -> 930 | ... N27: =Rooms!O27 -> 10020
A28: Total Rooms Occupied | B28: =Rooms!C28 -> 697.5 | C28: =Rooms!D28 -> 638.4 | D28: =Rooms!E28 -> 607.7 | E28: =Rooms!F28 -> 332 | F28: =Rooms!G28 -> 232.48621 | G28: =Rooms!H28 -> 167.65517 | H28: =Rooms!I28 -> 332.1 | I28: =Rooms!J28 -> 251.32 | ... N28: =Rooms!O28 -> 4363.2889
A29: Total Guests | B29: =Rooms!C29 -> 1255.5 | C29: =Rooms!D29 -> 1149.12 | D29: =Rooms!E29 -> 1093.86 | E29: =Rooms!F29 -> 597.6 | F29: =Rooms!G29 -> 418.47517 | G29: =Rooms!H29 -> 301.77931 | H29: =Rooms!I29 -> 597.78 | I29: =Rooms!J29 -> 452.376 | ... N29: =Rooms!O29 -> 7853.92
A30: % Occupancy | B30: =Rooms!C30 -> 0.75 | C30: =Rooms!D30 -> 0.76 | D30: =Rooms!E30 -> 0.65344086 | E30: =Rooms!F30 -> 0.36888889 | F30: =Rooms!G30 -> 0.24998517 | G30: =Rooms!H30 -> 0.18628352 | H30: =Rooms!I30 -> 0.35709677 | I30: =Rooms!J30 -> 0.27023656 | ... N30: =Rooms!O30 -> 0.43545797
A31: Average Daily Room Only | B31: =Rooms!C31 -> 595.27155 | C31: =Rooms!D31 -> 583.47405 | D31: =Rooms!E31 -> 590.96203 | E31: =Rooms!F31 -> 635.29075 | F31: =Rooms!G31 -> 521.40328 | G31: =Rooms!H31 -> 553.7017 | H31: =Rooms!I31 -> 566.23141 | I31: =Rooms!J31 -> 520.6179 | ... N31: =Rooms!O31 -> 596.88852
A34: Revenue by Month
A35: Label | B35: January | C35: February | D35: March | E35: April | F35: May | G35: June | H35: July | I35: August | J35: September | K35: October | L35: November | M35: December | N35: TOTAL
A36: Revenue 2024 | B36: 1057.5777 | C36: 1705.995 | D36: 2060.9848 | E36: 1412.55 | F36: 445.89118 | G36: 569.43434 | H36: 421.22071 | I36: 338.19589 | J36: 44.072603 | K36: 1065.1839 | L36: 762.07087 | M36: 33.48 | N36: =SUM(B36:M36) -> 9916.657
A37: Revenue 2025 | B37: 639.97343 | C37: 509.78357 | D37: 575.97723 | E37: 309.64348 | F37: 331.48465 | G37: 88.58094 | H37: 450.38698 | I37: 474.10849 | J37: 900 | K37: 0 | L37: 900 | M37: 900 | N37: =SUM(B37:M37) -> 6079.9388
A38: Revenue 2026 Budget | B38: =+'Key Indicators'!C337 -> 900 | C38: =+'Key Indicators'!D337 -> 900 | D38: =+'Key Indicators'!E337 -> 900 | E38: =+'Key Indicators'!F337 -> 900 | F38: =+'Key Indicators'!G337 -> 900 | G38: =+'Key Indicators'!H337 -> 900 | H38: =+'Key Indicators'!I337 -> 900 | I38: =+'Key Indicators'!J337 -> 900 | ... M38: =+'Key Indicators'!N337 -> 900 | N38: =SUM(B38:M38) -> 9900
A40: Revenue per Occupied Room 2024 | B40: =+B36/B14 -> 2.4652162 | C40: =+C36/C14 -> 3.7412171 | D40: =+D36/D14 -> 4.6004125 | E40: =+E36/E14 -> 5.453861 | F40: =+F36/F14 -> 2.5334726 | G40: =+G36/G14 -> 5.8105545 | H40: =+H36/H14 -> 1.6916494 | I40: =+I36/I14 -> 2.1541139 | ... N40: =+N36/N14 -> 3.5748583
A41: Revenue per Occupied Room 2025 | B41: =+B37/B21 -> 1.4096331 | C41: =+C37/C21 -> 1.0642663 | D41: =+D37/D21 -> 1.1097827 | E41: =+E37/E21 -> 1.2955794 | F41: =+F37/F21 -> 2.90776 | G41: =+G37/G21 -> 0.86844058 | H41: =+H37/H21 -> 1.6437481 | I41: =+I37/I21 -> 2.1550386 | ... N41: =+N37/N21 -> 1.9125319
A42: Revenue per Occupied Room 2026 | B42: =+B38/B28 -> 1.2903226 | C42: =+C38/C28 -> 1.4097744 | D42: =+D38/D28 -> 1.4809939 | E42: =+E38/E28 -> 2.7108434 | F42: =+F38/F28 -> 3.8711974 | G42: =+G38/G28 -> 5.3681613 | H42: =+H38/H28 -> 2.7100271 | I42: =+I38/I28 -> 3.5810918 | ... N42: =+N38/N28 -> 2.2689307
A44: Revenue by Guest 2024 | B44: =+B36/B15 -> 1.4874511 | C44: =+C36/C15 -> 2.0455575 | D44: =+D36/D15 -> 2.4682452 | E44: =+E36/E15 -> 2.5965992 | F44: =+F36/F15 -> 1.4337337 | G44: =+G36/G15 -> 3.5589646 | H44: =+H36/H15 -> 0.98186645 | I44: =+I36/I15 -> 1.0909545 | ... N44: =+N36/N15 -> 1.9536361
A45: Revenue by Guest 2025 | B45: =+B37/B29 -> 0.5097359 | C45: =+C37/C29 -> 0.44362954 | D45: =+D37/D29 -> 0.5265548 | E45: =+E37/E29 -> 0.51814505 | F45: =+F37/F29 -> 0.792125 | G45: =+G37/G29 -> 0.29352887 | H45: =+H37/H29 -> 0.75343266 | I45: =+I37/I29 -> 1.0480408 | ... N45: =+N37/N29 -> 0.77412792
A46: Revenue by Guest 2026 | B46: =+B38/B29 -> 0.71684588 | C46: =+C38/C29 -> 0.78320802 | D46: =+D38/D29 -> 0.8227744 | E46: =+E38/E29 -> 1.5060241 | F46: =+F38/F29 -> 2.1506652 | G46: =+G38/G29 -> 2.9823118 | H46: =+H38/H29 -> 1.5055706 | I46: =+I38/I29 -> 1.9894955 | ... N46: =+N38/N29 -> 1.260517

Sheet Final 2026 Rates
C1: Rooms
C2: ANALYSI | D2: BUDGET 2025 | M2: PROPOSAL BLAKE`S
D3: HOLIDAY SEASON | M3: HOLIDAY SEASON
D4: DEC 15TH,2024 TO JAN 05TH, 2025 | M4: DEC 21TH,2025 TO JAN 05TH, 2026
D6: ADULTS SINGLE | F6: ADULTS DOUBLE | H6: ADULTS TPL/QDPL | J6: CHILDREN | M6: ADULTS SINGLE | O6: ADULTS DOUBLE | Q6: ADULTS TPL/QDPL | S6: CHILDREN
D7: RACK | E7: NETA | F7: RACK | G7: NETA | H7: RACK | I7: NETA | J7: RACK | K7: NETA | M7: RACK | N7: NETA | O7: RACK | P7: NETA | R7: NETA | S7: RACK | T7: NETA
C8: FIVE ELEMENTS OCEAN VIEW TREEHOUSE | D8: =2227.5+(2227.5*0.15) -> 2561.625 | E8: =D8-(D8*0.3) -> 1793.1375 | F8: =2164.32+(2164.32*0.1) -> 2380.752 | G8: =F8-(F8*0.3) -> 1666.5264 | H8: NA | I8: NA | J8: NA | K8: NA | M8: 3586.275 | N8: 2510.3925 | O8: 3333.0528 | P8: 2333.137 | Q8: NA | R8: NA | S8: NA | T8: NA | W8: =+M8 -> 3586.275 | X8: =+O8*2 -> 6666.1056 | Y8: =+X8/3 -> 2222.0352
C9: OCEAN VIEW SPA TREEHOUSE | D9: =2127.5+(2127.5*0.15) -> 2446.625 | E9: =D9-(D9*0.3) -> 1712.6375 | F9: =2064.32+(2064.32*0.1) -> 2270.752 | G9: =F9-(F9*0.3) -> 1589.5264 | H9: NA | I9: NA | J9: NA | K9: NA | M9: 3180.6125 | N9: 2226.4288 | O9: 2951.9776 | P9: 2066.3843 | Q9: NA | R9: NA | S9: NA | T9: NA | W9: =+W8/3 -> 1195.425 | X9: =+X8/3 -> 2222.0352
C10: OCEAN VIEW TREEHOUSE | D10: =2127.5+(2127.5*0.15) -> 2446.625 | E10: =D10-(D10*0.3) -> 1712.6375 | F10: =2064.32+(2064.32*0.1) -> 2270.752 | G10: =F10-(F10*0.3) -> 1589.5264 | H10: NA | I10: NA | J10: NA | K10: NA | M10: 2935.95 | N10: 2055.165 | O10: 2724.9024 | P10: 1907.4317 | Q10: NA | R10: NA | S10: NA | T10: NA
C11: DULCE RAINFOREST VILLA | D11: =1850+(1850*0.15) -> 2127.5 | E11: =D11-(D11*0.3) -> 1489.25 | F11: =1795+(1795*0.1) -> 1974.5 | G11: =F11-(F11*0.3) -> 1382.15 | H11: NA | I11: NA | J11: NA | K11: NA | M11: 2659.375 | N11: 1861.5625 | O11: 2468.125 | P11: 1727.6875 | Q11: NA | R11: NA | S11: NA | T11: NA | W11: 100 | X11: 200
C12: CORCOVADO RAINFOREST VILLA | D12: =1745+(1745*0.15) -> 2006.75 | E12: =D12-(D12*0.3) -> 1404.725 | F12: =1580+(1580*0.1) -> 1738 | G12: =F12-(F12*0.3) -> 1216.6 | H12: NA | I12: NA | J12: NA | K12: NA | M12: 2508.4375 | N12: 1755.9062 | O12: 2172.5 | P12: 1520.75 | Q12: NA | R12: NA | S12: NA | T12: NA
C13: CARATE RAINFOREST VILLA | D13: =1745+(1745*0.15) -> 2006.75 | E13: =D13-(D13*0.3) -> 1404.725 | F13: =1580+(1580*0.1) -> 1738 | G13: =F13-(F13*0.3) -> 1216.6 | H13: =1580+(1580*0.1) -> 1738 | I13: =H13-(H13*0.3) -> 1216.6 | J13: 850 | K13: 595 | M13: 2408.1 | N13: 1685.67 | O13: 2085.6 | P13: 1459.92 | Q13: 2085.6 | R13: 1459.92 | S13: 1020 | T13: 714 | W13: =+W9-W11 -> 1095.425 | X13: =+X9-X11 -> 2022.0352
C14: AGUJAS RAINFOREST SUITE | D14: 1690 | E14: =D14-(D14*0.3) -> 1183 | F14: 1525 | G14: =F14-(F14*0.3) -> 1067.5 | H14: 1525 | I14: =H14-(H14*0.3) -> 1067.5 | J14: 850 | K14: 595 | M14: 2028 | N14: 1419.6 | O14: 1830 | P14: 1281 | Q14: 1830 | R14: 1281 | S14: 1020 | T14: 714
C15: SIRENA RAINFOREST SUITE | D15: 1690 | E15: =D15-(D15*0.3) -> 1183 | F15: 1525 | G15: =F15-(F15*0.3) -> 1067.5 | H15: NA | I15: NA | J15: NA | K15: NA | M15: 2028 | N15: 1419.6 | O15: 1830 | P15: 1281 | Q15: NA | R15: NA | S15: NA | T15: NA | W15: =+W13*0.85 -> 931.11125 | X15: =+X13*0.85 -> 1718.7299
C16: LlORONA RAINFOREST SUITE | D16: 1690 | E16: =D16-(D16*0.3) -> 1183 | F16: 1525 | G16: =F16-(F16*0.3) -> 1067.5 | H16: NA | I16: NA | J16: NA | K16: NA | M16: 2028 | N16: 1419.6 | O16: 1830 | P16: 1281 | Q16: NA | R16: NA | S16: NA | T16: NA
W17: =+W15+W11 -> 1031.1112 | X17: =+X15+X11 -> 1918.7299
D19: $ Increase versus 2026 Versus 2025 | M19: % Increase versus 2026 Versus 2025
C20: FIVE ELEMENTS OCEAN VIEW TREEHOUSE | D20: =+M8-D8 -> 1024.65 | E20: =+N8-E8 -> 717.255 | F20: =+O8-F8 -> 952.3008 | G20: =+P8-G8 -> 666.61056 | L20: 0.4 | M20: =+D20/D8 -> 0.4 | N20: =+E20/E8 -> 0.4 | O20: =+F20/F8 -> 0.4 | P20: =+G20/G8 -> 0.4
C21: OCEAN VIEW SPA TREEHOUSE | D21: =+M9-D9 -> 733.9875 | E21: =+N9-E9 -> 513.79125 | F21: =+O9-F9 -> 681.2256 | G21: =+P9-G9 -> 476.85792 | L21: 0.3 | M21: =+D21/D9 -> 0.3 | N21: =+E21/E9 -> 0.3 | O21: =+F21/F9 -> 0.3 | P21: =+G21/G9 -> 0.3
C22: OCEAN VIEW TREEHOUSE | D22: =+M10-D10 -> 489.325 | E22: =+N10-E10 -> 342.5275 | F22: =+O10-F10 -> 454.1504 | G22: =+P10-G10 -> 317.90528 | L22: 0.2 | M22: =+D22/D10 -> 0.2 | N22: =+E22/E10 -> 0.2 | O22: =+F22/F10 -> 0.2 | P22: =+G22/G10 -> 0.2
C23: DULCE RAINFOREST VILLA | D23: =+M11-D11 -> 531.875 | E23: =+N11-E11 -> 372.3125 | F23: =+O11-F11 -> 493.625 | G23: =+P11-G11 -> 345.5375 | L23: 0.25 | M23: =+D23/D11 -> 0.25 | N23: =+E23/E11 -> 0.25 | O23: =+F23/F11 -> 0.25 | P23: =+G23/G11 -> 0.25
C24: CORCOVADO RAINFOREST VILLA | D24: =+M12-D12 -> 501.6875 | E24: =+N12-E12 -> 351.18125 | F24: =+O12-F12 -> 434.5 | G24: =+P12-G12 -> 304.15 | L24: 0.25 | M24: =+D24/D12 -> 0.25 | N24: =+E24/E12 -> 0.25 | O24: =+F24/F12 -> 0.25 | P24: =+G24/G12 -> 0.25
C25: CARATE RAINFOREST VILLA | D25: =+M13-D13 -> 401.35 | E25: =+N13-E13 -> 280.945 | F25: =+O13-F13 -> 347.6 | G25: =+P13-G13 -> 243.32 | H25: =+Q13-H13 -> 347.6 | I25: =+R13-I13 -> 243.32 | J25: =+S13-J13 -> 170 | K25: =+T13-K13 -> 119 | L25: 0.2 | M25: =+D25/D13 -> 0.2 | N25: =+E25/E13 -> 0.2 | O25: =+F25/F13 -> 0.2 | P25: =+G25/G13 -> 0.2 | Q25: =+H25/H13 -> 0.2 | R25: =+I25/I13 -> 0.2 | S25: =+J25/J13 -> 0.2 | T25: =+K25/K13 -> 0.2
C26: AGUJAS RAINFOREST SUITE | D26: =+M14-D14 -> 338 | E26: =+N14-E14 -> 236.6 | F26: =+O14-F14 -> 305 | G26: =+P14-G14 -> 213.5 | H26: =+Q14-H14 -> 305 | I26: =+R14-I14 -> 213.5 | J26: =+S14-J14 -> 170 | K26: =+T14-K14 -> 119 | L26: 0.2 | M26: =+D26/D14 -> 0.2 | N26: =+E26/E14 -> 0.2 | O26: =+F26/F14 -> 0.2 | P26: =+G26/G14 -> 0.2 | Q26: =+H26/H14 -> 0.2 | R26: =+I26/I14 -> 0.2 | S26: =+J26/J14 -> 0.2 | T26: =+K26/K14 -> 0.2
C27: SIRENA RAINFOREST SUITE | D27: =+M15-D15 -> 338 | E27: =+N15-E15 -> 236.6 | F27: =+O15-F15 -> 305 | G27: =+P15-G15 -> 213.5 | L27: 0.2 | M27: =+D27/D15 -> 0.2 | N27: =+E27/E15 -> 0.2 | O27: =+F27/F15 -> 0.2 | P27: =+G27/G15 -> 0.2
C28: LlORONA RAINFOREST SUITE | D28: =+M16-D16 -> 338 | E28: =+N16-E16 -> 236.6 | F28: =+O16-F16 -> 305 | G28: =+P16-G16 -> 213.5 | L28: 0.2 | M28: =+D28/D16 -> 0.2 | N28: =+E28/E16 -> 0.2 | O28: =+F28/F16 -> 0.2 | P28: =+G28/G16 -> 0.2
M30: average | O30: =AVERAGE(O20:O29) -> 0.24444444
D32: BUDGET 2025 | M32: PROPOSAL BLAKE`S
D33: HOLIDAY SEASON | M33: HIGH SEASON
D34: JAN 06, 2025 TO APRIL 30TH, 2025 | M34: JAN 06, 2026 TO APRIL 30TH, 2026
D36: ADULTS SINGLE | F36: ADULTS DOUBLE | H36: ADULTS TPL/QDPL | J36: CHILDREN | M36: ADULTS SINGLE | O36: ADULTS DOUBLE | Q36: ADULTS TPL/QDPL | S36: CHILDREN
D37: RACK | E37: NETA | F37: RACK | G37: NETA | H37: RACK | I37: NETA | J37: RACK | K37: NETA | M37: RACK | N37: NETA | O37: RACK | P37: NETA | Q37: RACK | R37: NETA | S37: RACK | T37: NETA
C38: FIVE ELEMENTS OCEAN VIEW TREEHOUSE | D38: =2043.5+(2043.5*0.15) -> 2350.025 | E38: =D38-(D38*0.3) -> 1645.0175 | F38: =1997.5+(1997*0.1) -> 2197.2 | G38: =F38-(F38*0.3) -> 1538.04 | H38: NA | I38: NA | J38: NA | K38: NA | M38: 3290.035 | N38: 2303.0245 | O38: 3076.08 | P38: 2153.256 | Q38: NA | R38: NA | S38: NA | T38: NA
C39: OCEAN VIEW SPA TREEHOUSE | D39: =1943.5+(1943.5*0.15) -> 2235.025 | E39: =D39-(D39*0.3) -> 1564.5175 | F39: =1897.5+(1897*0.1) -> 2087.2 | G39: =F39-(F39*0.3) -> 1461.04 | H39: NA | I39: NA | J39: NA | K39: NA | M39: 2905.5325 | N39: 2033.8727 | O39: 2713.36 | P39: 1899.352 | Q39: NA | R39: NA | S39: NA | T39: NA
C40: OCEAN VIEW TREEHOUSE | D40: =1943.5+(1943.5*0.15) -> 2235.025 | E40: =D40-(D40*0.3) -> 1564.5175 | F40: =1897.5+(1897*0.1) -> 2087.2 | G40: =F40-(F40*0.3) -> 1461.04 | H40: NA | I40: NA | J40: NA | K40: NA | M40: 2682.03 | N40: 1877.421 | O40: 2504.64 | P40: 1753.248 | Q40: NA | R40: NA | S40: NA | T40: NA
C41: DULCE RAINFOREST VILLA | D41: =1690+(1690*0.15) -> 1943.5 | E41: =D41-(D41*0.3) -> 1360.45 | F41: =1650+(1650*0.1) -> 1815 | G41: =F41-(F41*0.3) -> 1270.5 | H41: NA | I41: NA | J41: NA | K41: NA | M41: 2429.375 | N41: 1700.5625 | O41: 2268.75 | P41: 1588.125 | Q41: NA | R41: NA | S41: NA | T41: NA
C42: CORCOVADO RAINFOREST VILLA | D42: =1580+(1580*0.15) -> 1817 | E42: =D42-(D42*0.3) -> 1271.9 | F42: =1415+(1415*0.1) -> 1556.5 | G42: =F42-(F42*0.3) -> 1089.55 | H42: NA | I42: NA | J42: NA | K42: NA | M42: 2271.25 | N42: 1589.875 | O42: 1945.625 | P42: 1361.9375 | Q42: NA | R42: NA | S42: NA | T42: NA
